Workbook

Sheet LISEZ-MOI
B1: StatApp 2026-2027 : sélection des sujets (KC)
B2: État du classeur
B3: Phases 1 et 2 réalisées : critères avec ancres (feuille « Critères »), identification des 83 sujets (« Identification »), scoring (« Scoring »), classement High / Mid / Ne pas toucher (« Classement »), règles (« Règles de classement ») et sources de la recherche web (« Sources web »). Tout est provisoire et à relire : les ancres et les critères n'ont pas encore été validés.
B4: Source : les 83 fiches PDF du dossier Docs/ (sujets n° 279 à 366 ; les numéros 283, 286, 287, 335 et 336 n'existent pas dans le dossier). Le lien « Ouvrir le PDF » est relatif à l'emplacement de ce classeur.
B5: Conventions de la feuille Identification
B6: Extraites telles quelles de la fiche : n°, organisme, titre, catégorie ENSAE, proposant, notation et commentaire ENSAE.
B7: Rédigées à la lecture de la fiche, sans jugement de valeur : type d'organisme, domaine réel, résumé, thèmes, méthodes, nature et statut des données, outils. Une information absente de la fiche est notée « non précisée » ou « à définir », jamais complétée par supposition.
B8: « Cohérence label ↔ contenu » : Oui, Partiel ou Non. Elle signale les sujets dont la catégorie ENSAE ne reflète pas bien le contenu. C'est un repérage, pas un score.
B9: « Type d'organisme » : déduit du nom et de la fiche ; les cas incertains sont marqués « à vérifier ». Les organismes CREST (toutes variantes de nom) sont regroupés pour le comptage.
B10: « Nb de fiches du même organisme » : valeur calculée une fois par script (non liée par formule).
B11: Notation ENSAE : à lire avec prudence
B12: Seules 20 fiches sur 83 portent une notation (8 « 3 », 7 « 2 », 5 « 1 »). L'absence de note n'est pas une mauvaise note : c'est une inconnue. Les agents d'analyse recevront cette information uniquement dans la lentille Note et faisabilité, pour ne pas biaiser les autres lentilles.
... B33: Les sujets 281, 282 et 361 (HSBC) se recoupent, comme 332, 333, 364 et 365 (Symbiotics) : il est inutile d'en demander plusieurs du même encadrant.

Sheet Critères
A1: Critères de scoring des sujets StatApp : version 2 (à valider)
A2: Échelle : 1 à 5 avec des ancres décrites par critère (rédigées, à relire). Pour « Valeur », 5 = excellent. Pour « Coût et risque », 5 = très coûteux ou risqué. Pas de pondération à ce stade. AJOUT = demandé lors de la dernière session.
A4: Code | B4: Famille | C4: Critère | D4: Ce que mesure le critère | E4: Sens | F4: Source d'information | G4: Lentille (agent) | H4: Statut vs v1 | I4: Ancre 1 | J4: Ancre 3 | K4: Ancre 5
A5: A1 | B5: A. Adéquation carrière | C5: Actuariat non-vie / ACAS | D5: GLM, fréquence-sévérité, tarification, provisionnement, théorie du risque (filière CAS) | E5: Valeur | F5: Fiche | G5: L1 Carrière | H5: v1 | I5: Aucun lien avec l'assurance non-vie ni la théorie du risque. | J5: Assurance non-vie en simple contexte, ou méthode de la filière (GLM, séries temporelles) appliquée hors assurance. | K5: Tarification, fréquence-sévérité, provisionnement ou théorie du risque non-vie au cœur du sujet, sur données d'assurance.
A6: A2 | B6: A. Adéquation carrière | C6: Réassurance / risque extrême / catastrophe | D6: Valeurs extrêmes, queues épaisses, copules, scénarios, climat et périls naturels, assurabilité | E6: Valeur | F6: Fiche | G6: L1 Carrière | H6: v1 | I6: Aucun lien avec les extrêmes, les périls naturels ou la réassurance. | J6: Risque climatique ou périls naturels abordés sans queues épaisses ni scénarios, ou méthodes d'extrêmes sur un objet non assurantiel. | K6: Valeurs extrêmes, copules, modélisation de catastrophes ou assurabilité du risque climatique au cœur du sujet.
A7: A3 | B7: A. Adéquation carrière | C7: Assurance vie / prévoyance (exploration) | D7: Mortalité, longévité, incapacité, ALM, Solvabilité II. Critère d'exploration : la filière ACAS n'est pas vie | E7: Valeur | F7: Fiche | G7: L1 Carrière | H7: AJOUT | I7: Aucun lien avec la mortalité, la longévité, l'incapacité ou l'ALM. | J7: Un volet vie ou prévoyance parmi d'autres (mortalité en variable annexe, ALM survolé). | K7: Mortalité, longévité, incapacité, ALM ou Solvabilité II vie au cœur du sujet. Critère d'exploration.
A8: A4 | B8: A. Adéquation carrière | C8: Quant finance (research / trading) | D8: Maths stochastiques, séries temporelles, dérivés, rigueur ; niveau mathématique lisible | E8: Valeur | F8: Fiche | G8: L1 Carrière | H8: v1 | I8: Aucun lien avec la finance de marché ; mathématiques élémentaires. | J8: Finance de marché (taux, actions, crédit) avec séries temporelles ou modèles classiques ; mathématiques peu visibles dans la fiche. | K8: Modèles stochastiques, dérivés, courbe de taux ou séries financières, avec un niveau mathématique clairement lisible dans la fiche.
A9: A5 | B9: A. Adéquation carrière | C9: Conseil généraliste (stratégie / risque) | D9: Cas business, restitution client, sectoriel (type Oliver Wyman, ICG) | E9: Valeur | F9: Fiche + web | G9: L1 Carrière | H9: v1 | I9: Sujet purement académique, sans client ni lecture business. | J9: Question métier réelle mais mono-sectorielle, ou restitution à un client seulement implicite. | K9: Cas business avec restitution à un client et décision à éclairer, dans l'esprit d'un cabinet de stratégie ou de risque.
A10: A6 | B10: A. Adéquation carrière | C10: Conseil spécialisé actuariat | D10: Missions actuarielles en cabinet : modèles, provisionnement, réglementaire, études pour assureurs et réassureurs | E10: Valeur | F10: Fiche + web | G10: L1 Carrière | H10: AJOUT | I10: Aucune mission de type actuariat en cabinet. | J10: Étude actuarielle ou réglementaire menée en interne chez un assureur ou une banque, ou cabinet sur un sujet non actuariel. | K10: Mission type d'un cabinet d'actuariat : modèle, provisionnement, réglementaire, étude pour assureurs ou réassureurs.
A11: A7 | B11: A. Adéquation carrière | C11: Institutions et développement | D11: Assurance paramétrique, pays émergents, secteur public, risque climatique souverain (type African Risk Capacity) | E11: Valeur | F11: Fiche + web | G11: L1 Carrière | H11: v1 | I11: Aucun lien avec le secteur public, les pays émergents ou l'assurance paramétrique. | J11: Institution publique ou question de développement, sans lien direct avec le risque ou l'assurance. | K11: Assurance paramétrique, risque climatique souverain, pays émergents ou institution internationale, avec lien direct au risque.
A12: A8 | B12: A. Adéquation carrière | C12: Compétences portables | D12: Compétences réutilisables dans plusieurs voies (R/Python, bayésien, survie, spatial, ML) | E12: Valeur | F12: Fiche | G12: L1 Carrière | H12: v1 | I12: Méthode ou outil de niche, difficilement réutilisable ailleurs. | J12: Deux ou trois compétences standard (Python, ML classique, séries temporelles), réutilisables mais génériques. | K12: Plusieurs compétences recherchées dans plusieurs voies (bayésien, survie, spatial, ML, R et Python) réellement pratiquées.
A13: A9 | B13: A. Adéquation carrière | C13: Motivation réelle | D13: Intérêt intrinsèque du sujet pour KC et le groupe sur quatre à cinq mois | E13: Valeur | F13: KC | G13: KC (humain) | H13: v1 | I13: Aucun intérêt ; sujet subi. Note donnée par KC, jamais par un agent. | J13: Intérêt correct, sans enthousiasme. | K13: Vrai intérêt personnel, tenable sur quatre à cinq mois pour KC et le groupe.
A14: B1 | B14: B. Signal marque et encadrant | C14: Notoriété de l'organisme | D14: Marque connue et influente, tous secteurs | E14: Valeur | F14: Web | G14: L2 Signal & exit | H14: v1 | I14: Organisme inconnu hors de son cercle. | J14: Connu dans son secteur ou en France. | K14: Marque connue et influente dans plusieurs secteurs, reconnue à l'international.
A15: B2 | B15: B. Signal marque et encadrant | C15: Pertinence de la marque pour nos cibles | D15: Poids de la marque auprès des réassureurs, cabinets, quant et institutions visés | E15: Valeur | F15: Web | G15: L2 Signal & exit | H15: v1 | I15: Marque sans poids auprès des réassureurs, cabinets, acteurs quant ou institutions visés. | J15: Marque connue d'une partie seulement des cibles. | K15: Marque qui compte directement auprès de plusieurs types de cibles (réassureurs, cabinets, quant, institutions).
... A40: F8 | B40: F. Coût et faisabilité | C40: Probabilité d'obtenir le sujet | D40: Demande attendue des autres élèves ; attribution par classement de 12 vœux | E40: Coût et risque | F40: Fiche + autres lentilles | G40: L4 Apprentissage & différenciation | H40: AJOUT | I40: Demande probablement faible : très bonnes chances de l'obtenir avec un bon rang de vœu. | J40: Demande moyenne. | K40: Très demandé (marque connue, sujet populaire, note 3) ; peu de chances même en vœu 1.
A42: Total : 36 critères (6 ajoutés).

Sheet Identification
A1: N° sujet | B1: Organisme | C1: Titre (fiche) | D1: Catégorie ENSAE (label officiel) | E1: Type d'organisme | F1: Proposant | G1: Langue | H1: Domaine réel (déduit du contenu) | I1: Résumé (en une à deux phrases) | J1: Thèmes / mots-clés | K1: Méthodes annoncées | L1: Nature des données | M1: Statut des données | N1: Outils cités | O1: Notation ENSAE (1-3) | P1: Commentaire ENSAE | Q1: Cohérence label ↔ contenu | R1: Note sur le label | S1: Nb de fiches du même organisme | T1: Fiche PDF
A2: 281 | B2: HSBC Global Asset Management | C2: Corrélation entre indices Action et Obligataire | D2: Actuariat | E2: Gestion d'actifs | F2: BRACH Loic | G2: FR | H2: Assurance vie — ALM / Solvabilité II | I2: Effet de Solvabilité II sur l'allocation d'actifs des assureurs vie européens (2014-2024, SFCR/EIOPA) + modèle ALM stylisé (SCR, ratio de solvabilité, volatilité du surplus) avec scénarios d'évolution du cadre. | J2: Solvabilité II, ALM, allocation stratégique, SCR, assureurs vie | K2: Formule standard Solvabilité II, optimisation de type Markowitz, simulation de scénarios | L2: Mixte | M2: Précisées (données de marché + SFCR/EIOPA publics) | O2: 2 | P2: C'est un sujet un peu avancé par rapport à la deuxième année de formation. Donc les élèves doivent en être conscients. | Q2: Partiel | R2: Le titre (corrélation actions/obligations) masque un sujet ALM / Solvabilité II pour assureurs vie | S2: 3 | T2: Ouvrir le PDF
A3: 285 | B3: SCOR | C3: Life and health insurance pricing with geographical data | D3: Actuariat | E3: Réassurance | F3: Luong Romain | G3: EN | H3: Assurance vie / prévoyance | I3: La localisation géographique améliore-t-elle la tarification du décès et de l'incapacité de travail ? Hypothèse : effet sur l'incapacité, pas sur la mortalité. | J3: Prévoyance, mortalité, incapacité, segmentation territoriale, tarification | K3: Logit, GLM, fréquence-sévérité, modèles de durée, random forests, DeepSurv | L3: Mixte | M3: Précisées (portefeuille(s) SCOR internes + open data externes) | N3: R, Python | O3: 3 | P3: Sujet intéressant, en parfaite adéquation avec les enseignements de 2A. | Q3: Oui | S3: 1 | T3: Ouvrir le PDF
A4: 292 | B4: CREST ENSAE | C4: Semantic Credit Risk Pricing with Large Language Models | D4: Actuariat | E4: Recherche académique | F4: NIAKH Fallou | G4: FR | H4: Risque de crédit (ML) | I4: Scoring de crédit par embeddings sémantiques de LLM (prompt → embedding → ACP → régression logistique), transposé de travaux récents sur la tarification en assurance. | J4: Scoring de crédit, LLM, embeddings, attributs protégés | K4: Régression logistique, XGBoost/LightGBM, embeddings LLM, ACP, fine-tuning contrastif | L4: Publiques | M4: Précisées (German Credit Data, 1 000 obs.) | Q4: Partiel | R4: Classé Actuariat ; objet = risque de crédit ; méthode importée de la tarification assurance | S4: 19 | T4: Ouvrir le PDF
A5: 309 | B5: Ekimetrics | C5: Apprentissage de lois a priori par transfert entre portefeuilles : une approche de meta-learning bayésien | D5: Actuariat | E5: Conseil / data science | F5: HU François | G5: FR | H5: Statistique bayésienne — crédibilité actuarielle | I5: Transfert de lois a priori entre portefeuilles par meta-learning bayésien ; deux terrains simulés : mesure d'efficacité marketing et portefeuilles d'assurance non-vie (GLM Poisson hiérarchique, comparaison à Bühlmann-Straub). | J5: Théorie de la crédibilité, bayésien hiérarchique, meta-learning, tarification non-vie | K5: GLM Poisson hiérarchique, régression bayésienne hiérarchique, NUTS/PyMC, estimateur de Bühlmann-Straub | L5: Simulées | M5: Précisées (générateur fourni par l'encadrant ; validation sur données réelles optionnelle) | N5: Python (PyMC) | Q5: Oui | R5: Contenu actuariel réel (crédibilité, comptage non-vie) sous un habillage méthodologique | S5: 6 | T5: Ouvrir le PDF
A6: 347 | B6: BNP Paribas Cardif | C6: Implémentation d'un outil de veille réglementaire assisté par l'intelligence artificielle en assurance | D6: Actuariat | E6: Assurance | F6: TOUKAM Eugénie Rinelle | G6: FR | H6: Assurance — réglementaire / NLP | I6: Outil de veille réglementaire (EIOPA, ACPR, Commission européenne) assisté par LLM / RAG pour un assureur. | J6: Solvabilité II, réglementation assurance, NLP, RAG | K6: NLP, LLM, RAG | L6: Publiques | M6: Précisées (textes réglementaires publics) | O6: 2 | P6: Le sujet me semble peu technique et donc il y a un risque élevé de contenu scientifique limité. Il faudra donc bien faire attention à ce point. | Q6: Partiel | R6: Contexte assurance mais contenu NLP/LLM ; pas de modélisation actuarielle | S6: 1 | T6: Ouvrir le PDF
A7: 348 | B7: KORFED SAS | C7: Modélisation et prédiction du risque auto : comparaison des méthodes actuarielles, du Machine Learning et de l'Intelligence Artificielle générative | D7: Actuariat | E7: Non précisé dans la fiche | F7: KORFED Marouan | G7: FR | H7: Assurance non-vie (auto) | I7: Comparer plusieurs générations de modèles de risque auto : GLM actuariels (fréquence et coût), ML (boosting, réseaux de neurones) et IA générative ; arbitrage performance / interprétabilité. | J7: Tarification auto, fréquence-sévérité, interprétabilité, ML vs GLM | K7: GLM (Poisson, binomiale négative, Gamma, log-normale), RF, boosting, réseaux de neurones, IA générative, explicabilité | L7: Internes (fournies) | M7: Partielles (contrats et sinistres auto anonymisés ; disponibilité non confirmée, cf. commentaire ENSAE) | O7: 3 | P7: Le sujet est adéquat aux attendus du Statapp. Je n'ai pas vu d'infos sur la disponibilité des données. | Q7: Oui | S7: 1 | T7: Ouvrir le PDF
A8: 280 | B8: HeadMind Partners | C8: Visual Search – Classification d'image | D8: Autre | E8: Conseil / ESN | F8: DEFOSSEZ Lucie | G8: FR | H8: ML — vision par ordinateur | I8: Pipeline de recherche visuelle pour l'e-commerce mode : classifier les vêtements portés sur une photo et retrouver l'article du catalogue. | J8: Vision par ordinateur, classification d'images | K8: Vision par ordinateur moderne (voir fiche) | L8: Non précisées | M8: Non précisées (la section Données décrit des objectifs) | O8: 1 | P8: Sujet hors scope ENSAE, nous ne faisons pas de détection d'image ni de fine tuning de modèles. | Q8: Oui | S8: 2 | T8: Ouvrir le PDF
A9: 288 | B9: Société Générale | C9: L'incertitude des systèmes multi-agents | D9: Autre | E9: Banque | F9: VIGNARD Alexis | G9: FR | H9: ML — LLM multi-agents | I9: Quantifier l'incertitude des systèmes multi-agents fondés sur des LLM (LangGraph, benchmarks d'agents). | J9: LLM, agents, incertitude, benchmarks | K9: Agents LangGraph, modèles open source pré-entraînés | L9: Publiques | M9: Partielles (environnement d'évaluation à identifier et à déployer) | N9: LangGraph | O9: 2 | P9: Sujet intéressant mais très déconseillé: le gros du travail nécessite une compréhension et une maîtrise de ce qu'est un LLM (programme de fin de 3A) et utilise assez peu la formation ENSAE 1A-2A. Le sujet semble être un programme de recherche de thèse, pas un stat-app. | Q9: Oui | S9: 2 | T9: Ouvrir le PDF
A10: 314 | B10: Ekimetrics | C10: Why Is the Model Uncertain? Explaining and Reducing Predictive Uncertainty in Machine Learning | D10: Autre | E10: Conseil / data science | F10: AGNIMO Yedidia | G10: EN | H10: ML — incertitude prédictive | I10: Expliquer pourquoi un modèle ML est incertain pour une observation donnée (au-delà de l'intervalle de prédiction) ; application aux ventes immobilières d'Ames. | J10: Quantification d'incertitude, conformal prediction, SHAP, régression quantile | K10: Régression linéaire, arbres, régression quantile, conformal prediction, SHAP | L10: Publiques | M10: Précisées (Ames Housing, 2 930 ventes) | Q10: Oui | R10: Pas de lien métier assurance/finance dans la fiche | S10: 6 | T10: Ouvrir le PDF
A11: 291 | B11: RTE | C11: Analyse longitudinale de la base OPERAT - Comment les consommations énergétiques des établissements tertiaires français ont-elles évolué entre 2020 et 2024, et quels facteurs expliquent l'hétérogénéité des trajectoires ? | D11: Environnement Energie et Mobilité | E11: Industrie / énergie | F11: Crocombette Christophe | G11: FR | H11: Énergie — consommation tertiaire | I11: Évolution 2020-2024 de l'intensité énergétique d'environ 250 000 établissements tertiaires (base OPERAT) et facteurs d'hétérogénéité. | J11: Efficacité énergétique, hétérogénéité, longitudinal | K11: Régression, clustering, logit | L11: Internes (fournies) | M11: Précisées (~1 M d'entrées, base OPERAT) | Q11: Oui | S11: 1 | T11: Ouvrir le PDF
A12: 304 | B12: GazTransport et Technigaz | C12: Identification des anomalies de trajectoires de méthaniers pour l'obtention de statistiques agrégées sur les temps d'attente permettant de quantifier les gains d'une approche « Just-in-time » | D12: Environnement Energie et Mobilité | E12: Industrie / maritime-GNL | F12: Montiel Antoine | G12: FR | H12: Transport / logistique | I12: Détecter les temps d'attente anormaux des méthaniers à partir des trajectoires AIS (~900 navires) et chiffrer les gains d'une approche « just-in-time ». | J12: AIS, détection d'anomalies, séries temporelles de position | K12: Indicateurs de trajectoire, probabilités conditionnelles, modèles supervisés | L12: Internes (fournies) | M12: Précisées (AIS, navires, armateurs, terminaux) | Q12: Oui | S12: 1 | T12: Ouvrir le PDF
A13: 305 | B13: CREST | C13: Disaster Risk Reduction and Climate Change Adaptation in European Metropolises | D13: Environnement Energie et Mobilité | E13: Recherche académique | F13: Rufat Samuel | G13: EN | H13: Risque de catastrophe / adaptation climatique | I13: Comportements d'adaptation aux inondations et canicules dans les grandes métropoles européennes (projet ERC FiBeGa) : prédicteurs locaux et simulation spatialement explicite. | J13: Catastrophes naturelles, adaptation, perception du risque, spatial, ABM | K13: Analyse de données R/Python, modélisation multi-agents (ABM, apprentissage possible) | L13: Mixte | M13: Précisées (enquêtes n=5 000, recensement carroyé, hospitalisations, climat/catastrophes) | N13: R, Python | Q13: Partiel | R13: Classé Environnement ; sujet de risque de catastrophe naturelle | S13: 19 | T13: Ouvrir le PDF
A14: 339 | B14: INRAE | C14: Les arbitrages spatiaux des ménages : coûts du logement, coûts de mobilité et contraintes temporelles | D14: Environnement Energie et Mobilité | E14: Recherche académique | F14: BOUSCASSE HELENE | G14: FR | H14: Économie des ménages (logement / mobilité) | I14: Arbitrage coût du logement / coût et temps de transport : appariement statistique Budget de famille × Emploi du temps, puis coût résidentiel généralisé. | J14: Mobilité, logement, valeur du temps, appariement statistique | K14: Régression bêta / logit fractionnaire, modèles à zéros, régression quantile, hot-deck / PMM, imputation multiple | L14: Publiques | M14: Précisées (Budget de famille 2011/2017, Emploi du temps) | Q14: Oui | S14: 2 | T14: Ouvrir le PDF
A15: 342 | B15: CREST | C15: Quel prix pour l'eau potable – Demande, hétérogénéité et ciblage des subventions en Inde rurale | D15: Environnement Energie et Mobilité | E15: Recherche académique | F15: Crepon Bruno | G15: FR | H15: Économie du développement | I15: Demande d'eau potable livrée à domicile et ciblage des subventions, à partir d'une expérience randomisée (Inde rurale, ~60 000 ménages). | J15: Évaluation d'impact, demande, élasticité-prix, WTP/WTA, ciblage | K15: Effets de traitement, estimation de demande, panel à effets fixes, hétérogénéité | L15: Internes (fournies) | M15: Précisées (expérience randomisée, Odisha) | Q15: Oui | S15: 19 | T15: Ouvrir le PDF
A16: 344 | B16: INRAE | C16: Homo economicus prend-il le volant – Rationalité limitée et coûts de mobilité | D16: Environnement Energie et Mobilité | E16: Recherche académique | F16: BOUSCASSE HELENE | G16: FR | H16: Économie comportementale (mobilité) | I16: Les ménages connaissent-ils le coût de leur voiture ? Rationalité limitée, postes oubliés, préférence pour le présent. | J16: Économie comportementale, coût de la voiture, biais de perception | K16: Statistique descriptive, régression, modèles à variable dépendante qualitative, maximum de vraisemblance (option) | L16: Enquête | M16: Précisées (enquête LocarEsid 2023-2024) | Q16: Oui | S16: 2 | T16: Ouvrir le PDF
A17: 351 | B17: ENPC | C17: Mesurer l'économie productive dans les quartiers de gare du Grand Paris Express | D17: Environnement Energie et Mobilité | E17: Recherche académique | F17: Crague Gilles | G17: FR | H17: Économie urbaine | I17: Mesurer l'économie productive autour des 68 gares du Grand Paris Express (rayon 800 m) à partir de données ouvertes. | J17: Économie urbaine, établissements, géolocalisation, observatoire | K17: Méthodes ouvertes (au choix des élèves) | L17: Publiques | M17: Précisées (Sirene géolocalisée et autres open data) | Q17: Oui | S17: 1 | T17: Ouvrir le PDF
A18: 353 | B18: CREST | C18: When a critical material becomes scarce, do firms dig in and innovate around it, or pivot into new activities? And does their existing technological know-how pull them toward the same constrained input? | D18: Environnement Energie et Mobilité | E18: Recherche académique | F18: Zerbib Olivier David | G18: EN | H18: Économie industrielle / innovation | I18: Face à la raréfaction d'un matériau critique, les firmes innovent-elles ou se redéploient-elles ? | J18: Matériaux critiques, innovation, brevets, chocs d'offre | K18: Event study, différences-de-différences | L18: Internes (fournies) | M18: Précisées (dépendance aux matériaux, ruptures, portefeuilles produits/brevets ; mise en forme à prévoir) | Q18: Oui | S18: 19 | T18: Ouvrir le PDF
A19: 360 | B19: EDF R&D | C19: Méthodes statistiques pour la prévision de production renouvelable | D19: Environnement Energie et Mobilité | E19: Industrie / énergie | F19: Upton Henri | G19: FR | H19: Énergie — prévision renouvelable | I19: Prévision de la production éolienne nationale à partir de prévisions météo (données de type compétition Codabench). | J19: Éolien, prévision, météo | K19: Deep learning, modèles de fondation, boosting, random forest | L19: Publiques | M19: Précisées (page de compétition privée, déjà disponible) | Q19: Oui | R19: Fiche très courte | S19: 1 | T19: Ouvrir le PDF
A20: 362 | B20: CANOPY ENERGIES | C20: Peut-on prédire la croissance du Pongamia à partir du sol – Modélisation statistique et spatiale d'une plantation agroforestière à Madagascar | D20: Environnement Energie et Mobilité | E20: Environnement / projet de restauration | F20: GARCHERY Guillaume | G20: FR | H20: Environnement — agronomie / spatial | I20: Prédire survie et croissance du Pongamia à Madagascar (projet Fagnako) à partir du sol, de l'âge, de la topographie ; modélisation longitudinale et spatiale. | J20: Agroforesterie, statistique spatiale, croissance, survie | K20: GAM, effets mixtes, modèles de survie, statistique spatiale, RF/boosting, validation croisée spatiale | L20: Internes (fournies) | M20: Précisées (campagnes d'inventaire du projet) | Q20: Oui | S20: 1 | T20: Ouvrir le PDF
A21: 282 | B21: HSBC Global Asset Management | C21: Stratégies optionnelles de protection pour investisseurs de long terme | D21: Finance | E21: Gestion d'actifs | F21: BRACH Loic | G21: FR | H21: Gestion d'actifs / produits structurés | I21: Stratégies optionnelles de protection (puts, collars, CPPI/OBPI, volatilité cible) pour investisseurs de long terme ; efficacité selon le régime de marché. | J21: Protection de portefeuille, options, CPPI, backtesting | K21: Pricing et simulation stochastique, backtesting de stratégies | L21: Marché | M21: Précisées (historiques de prix d'indices actions et obligataires) | O21: 3 | P21: Le sujet est bien adéquat au contenu des enseignements de deuxième année. Il y a des composantes techniques mais aussi opérationnelles. | Q21: Oui | S21: 3 | T21: Ouvrir le PDF
A22: 296 | B22: Partners Group | C22: Mandates representation and optimization via cross trades | D22: Finance | E22: Gestion d'actifs | F22: Memmi Pierre | G22: EN | H22: Gestion d'actifs — private markets | I22: Représentation de portefeuilles d'investisseurs et optimisation par échanges d'actifs (cross trades). | J22: Portefeuilles, similarité, cross trades | K22: À confirmer (TBC) | L22: Internes (fournies) | M22: Partielles (variables listées ; objectifs et modèles à confirmer, cf. commentaire ENSAE) | O22: 2 | P22: Il n'y a pas suffisamment d'informations sur le sujet, notamment sur les objectifs de l'étude, la disponibilité des données et, surtout, les méthodes qui seront utilisées durant le projet. | Q22: Oui | S22: 1 | T22: Ouvrir le PDF
A23: 324 | B23: Banque de France | C23: Modélisation du risque de crédit en intégrant les engagements hors bilan | D23: Finance | E23: Institution publique | F23: BOUFFIN Joshua | G23: FR | H23: Risque de crédit | I23: Intégrer les engagements hors bilan (cas des hyperscalers) dans les modèles de risque de crédit (Merton/KMV, Altman Z). | J23: Risque de crédit, hors bilan, modèles structurels, hyperscalers | K23: Merton / KMV, Altman Z-score | L23: Marché | M23: Précisées (Bloomberg, marchés européens et américains) | O23: 3 | P23: Je trouve que le sujet est adéquat et la démarche attendue est bien explicitée. | Q23: Oui | S23: 2 | T23: Ouvrir le PDF
A24: 332 | B24: Symbiotics Asset Management | C24: Constructing Yield Curves in Illiquid Emerging Market | D24: Finance | E24: Gestion d'actifs | F24: Belpaire Michael | G24: EN | H24: Marchés de taux / dérivés | I24: Construire des courbes de taux sur marchés émergents illiquides (réplication de Khakimzhanov et al., 2019 : Nelson-Siegel sur données éparses). | J24: Courbe des taux, illiquidité, Nelson-Siegel | K24: Nelson-Siegel adapté aux transactions éparses | L24: Publiques | M24: Partielles (sources potentielles : banques centrales, bourses, ministères) | O24: 3 | P24: Sujet adéquat | Q24: Oui | S24: 4 | T24: Ouvrir le PDF
A25: 333 | B25: Symbiotics Asset Management | C25: Simplifying Corporate Default Risk Prediction Using Public Financial Data | D25: Finance | E25: Gestion d'actifs | F25: Belpaire Michael | G25: EN | H25: Risque de crédit | I25: Prédire la défaillance d'entreprises cotées avec peu d'indicateurs publics et interprétables ; comparaison à Altman/Ohlson, hazard et ML. | J25: Défaut d'entreprise, parcimonie, interprétabilité | K25: Ratios (Altman, Ohlson), logit / hazard (Shumway, Campbell et al.), benchmark ML | L25: Publiques | M25: Précisées (SEC EDGAR) | O25: 3 | P25: Sujet adéquat | Q25: Oui | S25: 4 | T25: Ouvrir le PDF
A26: 338 | B26: Société Générale | C26: Explaining Cheapest-to-Deliver (CTD) Bond Transitions in Government Bond Futures | D26: Finance | E26: Banque | F26: Draghia Denisa | G26: EN | H26: Marchés de taux / dérivés | I26: Expliquer et prévoir les changements de Cheapest-to-Deliver dans les futures obligataires souverains. | J26: Futures obligataires, CTD, courbe des taux | K26: Régression, random forest, XGBoost, modèle stochastique | L26: Marché | M26: Précisées (données de marché du future) | O26: 3 | P26: Ok même si je ne suis pas expert du sujet. | Q26: Oui | S26: 2 | T26: Ouvrir le PDF
A27: 355 | B27: Ornikar Assurance | C27: Mesure de l'assurabilité en assurance Auto | D27: Finance | E27: Assurance | F27: GORGE Guillaume | G27: FR | H27: Assurance non-vie (auto) — assurabilité | I27: Mesurer la « frontière de l'assurabilité » en auto (prix, exclusions, nombre d'assureurs répondant) à partir de demandes de cotation. | J27: Assurabilité, climat, prix, exclusions | K27: Autoencodeur, réseaux de neurones, XGBoost, classification | L27: Internes (fournies) | M27: Précisées (demandes de cotation du marché) | Q27: Partiel | R27: Classé Finance ; contenu = assurance non-vie | S27: 1 | T27: Ouvrir le PDF
A28: 356 | B28: VIA AM | C28: Finding Factors Using NLP/LLMs on 10-K/10-Q/8-K Filings | D28: Finance | E28: Gestion d'actifs | F28: Molinaro Matéo | G28: EN | H28: Finance quantitative — NLP | I28: Extraire des facteurs du texte des filings SEC (10-K/10-Q/8-K) par NLP/LLM et tester leur apport face aux facteurs classiques. | J28: Facteurs, filings SEC, NLP, asset pricing | K28: TF-IDF, embeddings, FinBERT / LLM, lasso/ridge/elastic net, LightGBM/XGBoost, régression | L28: Publiques | M28: Précisées (SEC EDGAR, Open Source Asset Pricing) | Q28: Oui | S28: 1 | T28: Ouvrir le PDF
A29: 361 | B29: HSBC Global Asset Management | C29: Gestion d'actif – Conception de portefeuilles optionnels protégés sous contrainte Solvabilité II | D29: Finance | E29: Gestion d'actifs | F29: BRACH Loic | G29: FR | H29: Gestion d'actifs / Solvabilité II (assureurs vie) | I29: Concevoir des portefeuilles optionnels protégés pour assureurs vie et fonds de retraite sous contrainte de capital Solvabilité II. | J29: Solvabilité II, options, CPPI/OBPI, assureurs vie | K29: Simulation de marché (diffusion géométrique, volatilité stochastique, bootstrap), calibration | L29: Marché | M29: Précisées (historiques de prix d'indices) | Q29: Partiel | R29: Classé Finance ; contrainte réglementaire d'assurance vie centrale | S29: 3 | T29: Ouvrir le PDF
A30: 364 | B30: Symbiotics Asset Management | C30: Statistical Modelling, Stress Testing and Optimal Structuring of a Blended Finance Fund | D30: Finance | E30: Gestion d'actifs | F30: Belpaire Michael | G30: EN | H30: Finance de développement — structuration | I30: Modélisation statistique, stress tests et structuration optimale (tranches junior / senior) d'un fonds de blended finance. | J30: Blended finance, tranche first-loss, stress test, structuration | K30: À définir | L30: À définir | M30: À définir (données et modèles « to be defined ») | Q30: Oui | R30: Cœur du sujet = structuration en tranches de pertes (first-loss) et stress tests | S30: 4 | T30: Ouvrir le PDF
A31: 365 | B31: Symbiotics Asset Management | C31: Modélisation factorielle et stratégie de couverture d'un portefeuille marchés émergents | D31: Finance | E31: Gestion d'actifs | F31: Belpaire Michael | G31: FR | H31: Marchés émergents — devises | I31: Modèle factoriel (ACP) des devises émergentes et frontières, déterminants, portage, puis stratégie de couverture backtestée. | J31: Devises émergentes, ACP, portage, couverture | K31: ACP, économétrie, backtest | L31: Internes (fournies) | M31: Précisées (données financières fournies par l'entreprise) | N31: R | Q31: Oui | S31: 4 | T31: Ouvrir le PDF
A32: 366 | B32: BPCE SA | C32: Estimation des pertes extrêmes en risque de crédit | D32: Finance | E32: Banque | F32: SICAN Silas | G32: FR | H32: Risque de crédit — dépendance extrême | I32: VaR 99,9 % d'un portefeuille de crédit multivarié avec copules (Gaussienne, Student, archimédiennes) pour capter la dépendance de queue. | J32: Copules, dépendance de queue, VaR, capital économique | K32: Copules, séries temporelles des marges, économétrie | L32: Internes (fournies) | M32: Partielles (séries multivariées de taux de défaut et pertes attendues ; origine à confirmer) | Q32: Oui | R32: Classé Finance ; cœur du sujet = risque extrême / dépendance de queue | S32: 1 | T32: Ouvrir le PDF
A33: 289 | B33: DG Trésor | C33: Analyse sectorielle des fluctuations du prix du pétrole | D33: Macroeconomie | E33: Institution publique | F33: LEE Raphael | G33: FR | H33: Macroéconomie — pétrole | I33: Effets sectoriels des chocs de prix du pétrole sur l'activité (guerre en Ukraine, Moyen-Orient). | J33: Prix du pétrole, chocs, VAR sectoriel | K33: VAR, caractérisation statistique des séries | L33: Publiques | M33: Précisées (OCDE, FMI) | Q33: Oui | S33: 2 | T33: Ouvrir le PDF
A34: 290 | B34: DG Trésor | C34: L'impact économique du vieillissement | D34: Macroeconomie | E34: Institution publique | F34: LEE Raphaël | G34: FR | H34: Macroéconomie — démographie | I34: Effets du vieillissement sur la consommation et la croissance du PIB. | J34: Vieillissement, consommation, croissance | K34: Non précisées (analyse puis estimation des effets sur données macro) | L34: Publiques | M34: Précisées (OCDE, FMI) | Q34: Oui | S34: 2 | T34: Ouvrir le PDF
A35: 293 | B35: QuantCube Technology | C35: Nowcasting hiérarchique de la consommation des ménages en Espagne | D35: Macroeconomie | E35: Data / fintech | F35: de Roux Nicolas de Roux | G35: FR | H35: Macroéconomie — nowcasting | I35: Nowcasting hiérarchique de la consommation des ménages espagnols (agrégat trimestriel et postes de dépense) avec cohérence comptable. | J35: Nowcasting, prévision hiérarchique, réconciliation | K35: Lasso/Ridge, SARIMA, VAR, facteurs dynamiques à fréquence mixte, forêts aléatoires | L35: Mixte | M35: Précisées (INE, Banco de España, Eurostat + données alternatives) | Q35: Oui | S35: 2 | T35: Ouvrir le PDF
A36: 295 | B36: QuantCube Technology | C36: Nowcasting des Nonfarm Payrolls américains à partir de données alternatives haute fréquence | D36: Macroeconomie | E36: Data / fintech | F36: MEREAU Julien | G36: FR | H36: Macroéconomie — nowcasting | I36: Nowcasting des Nonfarm Payrolls américains avec des données alternatives haute fréquence. | J36: Nowcasting, emploi, données alternatives, fréquences mixtes | K36: SARIMAX, VAR, modèles à facteurs dynamiques, modèles espace-état | L36: Mixte | M36: Précisées (BLS, jobless claims, JOLTS + données alternatives) | Q36: Oui | S36: 2 | T36: Ouvrir le PDF
A37: 300 | B37: European University Institute | C37: The Effects of Geopolitical Risk on Innovation: Evidence from International Patent Data | D37: Macroeconomie | E37: Recherche académique | F37: Lomo Pedro | G37: EN | H37: Macroéconomie — innovation | I37: Effets du risque géopolitique sur l'innovation internationale à partir des brevets OCDE. | J37: Risque géopolitique, brevets, flux de connaissances | K37: Économétrie de panel (effets fixes) | L37: Publiques | M37: Précisées (brevets et citations OCDE, mesures de risque géopolitique) | Q37: Oui | S37: 1 | T37: Ouvrir le PDF
A38: 326 | B38: Banque de France | C38: Un modèle de gravité pour expliquer les flux touristiques entrants en France par nationalité | D38: Macroeconomie | E38: Institution publique | F38: Pradelle Félix | G38: FR | H38: Macroéconomie — commerce / tourisme | I38: Modèle de gravité des flux de voyageurs entrants en France par nationalité (2022-2025). | J38: Gravité, tourisme, balance des paiements | K38: MCO à effets fixes, PPML, LASSO (option) | L38: Internes (fournies) | M38: Précisées (séries mensuelles agrégées et légèrement bruitées) | Q38: Oui | S38: 2 | T38: Ouvrir le PDF
A39: 354 | B39: Lazard Frères | C39: Dynamique de la dette française | D39: Macroeconomie | E39: Banque d'affaires / conseil | F39: Quisefit Antonin | G39: FR | H39: Macro-finance — dette souveraine | I39: Dette française : déterminants du spread OAT-Bund (macro, risque global, politique) et signaux avant-coureurs de changement de régime (early warning, équilibres multiples). | J39: Spread souverain, event study, early warning, changement de régime | K39: Régression sur séries temporelles, event study, Markov-switching, probit/logit | L39: Marché | M39: Précisées (Bloomberg/Refinitiv ou séries publiques BCE, BdF, Eurostat) | Q39: Oui | S39: 1 | T39: Ouvrir le PDF
A40: 301 | B40: Withings SAS | C40: Souscription et résiliation d'un abonnement de santé connectée : détecter les signaux d'usage précurseurs et identifier les leviers d'action | D40: Marketing Quantitatif | E40: Entreprise (santé connectée) | F40: CARRIE Hugo | G40: FR | H40: Marketing / data business — survie et rétention | I40: Détecter les signaux d'usage qui précèdent la souscription et la résiliation d'un abonnement santé connectée, puis ceux sur lesquels l'entreprise peut agir. | J40: Rétention, churn, modèle de durée, prédiction vs effet d'une intervention | K40: Courbes de rétention, modèle de Cox ou à temps discret, prédiction, volet décisionnel (effet d'une intervention) | L40: Internes (fournies) | M40: Précisées (extraction pseudonymisée, plusieurs centaines de milliers d'utilisateurs, 24-36 mois) | Q40: Oui | S40: 1 | T40: Ouvrir le PDF
A41: 308 | B41: Ekimetrics | C41: Sensibilité au choix des lois a priori dans les modèles bayésiens hiérarchiques : effets sur l'estimation et sur la décision | D41: Marketing Quantitatif | E41: Conseil / data science | F41: HU François | G41: FR | H41: Statistique bayésienne — marketing mix | I41: Sensibilité au choix des lois a priori dans les modèles bayésiens de mesure d'efficacité publicitaire, jusqu'à la décision d'allocation budgétaire. | J41: Marketing mix modeling, priors, power-scaling, regret décisionnel | K41: Régression bayésienne hiérarchique, NUTS/PyMC, power-scaling (PSIS), optimisation sous contrainte | L41: Simulées | M41: Précisées (générateur fourni ; validation sur données réelles optionnelle) | N41: Python (PyMC), R (priorsense) | Q41: Oui | S41: 6 | T41: Ouvrir le PDF
A42: 337 | B42: Sia Partners | C42: Prédiction de la popularité de contenus vidéo marketing pour les marques de luxe par analyse multimodale (computer vision, NLP) | D42: Marketing Quantitatif | E42: Conseil | F42: NADLER Côme | G42: FR | H42: Marketing / ML multimodal | I42: Prédire la popularité de vidéos de marques de luxe (TikTok, Reels, Shorts) par analyse visuelle, audio et texte. | J42: Vidéo, popularité, multimodal, luxe | K42: CNN / ViT / CLIP, détection d'objets, scoring esthétique (voir fiche) | L42: Publiques (à collecter) | M42: Précisées (vidéos de marques et métriques d'engagement) | O42: 2 | P42: Les transformers et les modèles de vision sont hors programme de la 2A et sont notoirement difficiles. Il semble très ambitieux d'en faire quelquechose de bien pour un étudiant en début de 2A qui découvre les fondamentaux du ML. La seconde partie est toutefois tout à fait adaptée. Je ne recommande pas ce sujet et maintient son caractère hors de propos et extrêmement dangereux pour un étudiant de 2A. | Q42: Oui | S42: 1 | T42: Ouvrir le PDF
A43: 302 | B43: WOAH | C43: Animal Health as Market and Trade Intelligence | D43: Microéconomie Appliquée | E43: Organisation internationale | F43: Guillot Gilles | G43: EN | H43: Économie agricole / commerce — chocs sanitaires | I43: Impact des épizooties (grippe aviaire, peste porcine africaine, fièvre aphteuse…) sur les marchés et le commerce de la viande. | J43: Épizooties, marchés de matières premières, event study, ruptures | K43: Event study, ruptures structurelles (Chow, Bai-Perron), modèles à seuils / régimes | L43: Mixte | M43: Précisées (FAOSTAT, prix de la viande + données d'événements WOAH) | Q43: Oui | S43: 2 | T43: Ouvrir le PDF
A44: 306 | B44: CREST UMR 9194 | C44: Résultats des élections municipales à Paris et caractéristiques des quartiers | D44: Microéconomie Appliquée | E44: Recherche académique | F44: Kamionka Thierry | G44: FR | H44: Économie politique locale | I44: Résultats des municipales 2026 à Paris et caractéristiques socio-économiques des 80 quartiers. | J44: Vote, quartiers, géographie | K44: Modèles de probabilité linéaire, panel, ML | L44: Publiques | M44: Précisées (open data Paris, data.gouv) | Q44: Oui | S44: 19 | T44: Ouvrir le PDF
A45: 307 | B45: CREST UMR 9194 | C45: Prix des forêts, composition du couvert forestier et caractéristiques locales | D45: Microéconomie Appliquée | E45: Recherche académique | F45: Kamionka Thierry | G45: FR | H45: Économie de l'environnement / foncier forestier | I45: Prix des forêts selon la composition du couvert forestier et les caractéristiques locales. | J45: Prix hédoniques, forêts, spatial | K45: Économétrie de panel, ML | L45: Publiques | M45: Précisées (DVF+, BD Forêt, BD Alti…) | Q45: Oui | S45: 19 | T45: Ouvrir le PDF
A46: 311 | B46: CREST et Univ. Paris 1 Panthéon-Sorbonne | C46: Les discriminations salariales entre hommes et femmes : étude des enquêtes du Céreq | D46: Microéconomie Appliquée | E46: Recherche académique | F46: Gary Bobo Robert | G46: FR | H46: Économie du travail | I46: Écarts de salaire hommes/femmes dans l'enquête Génération du Céreq, avec maternité et origine. | J46: Discrimination salariale, genre, origine, insertion | K46: Régression linéaire, panel, variables instrumentales | L46: Enquête | M46: Précisées (Génération 2017 à 3 ans, Céreq) | Q46: Oui | S46: 19 | T46: Ouvrir le PDF
A47: 312 | B47: Univ. Paris 1 Panthéon-Sorbonne (CES) | C47: L'efficacité économique des hôpitaux publics et privés : étude économétrique sur données françaises | D47: Microéconomie Appliquée | E47: Recherche académique | F47: Gary Bobo Robert | G47: FR | H47: Économie de la santé | I47: Efficacité économique des hôpitaux publics et privés : fonction de demande contingente de personnel, rôle de l'ambulatoire. | J47: Hôpitaux, productivité, ambulatoire | K47: Régression avec ou sans variables instrumentales, observations répétées | L47: Publiques | M47: Précisées (bases publiques de santé) | Q47: Oui | S47: 1 | T47: Ouvrir le PDF
A48: 317 | B48: CREST | C48: Cartographier la diversité dans la science, l'innovation et l'entrepreneuriat en France | D48: Microéconomie Appliquée | E48: Recherche académique | F48: Signorelli Sara | G48: FR | H48: Économie de l'innovation / diversité | I48: Cartographier la diversité (genre, origine migratoire) parmi les inventeurs, chercheurs et entrepreneurs en France par classification de noms et prénoms. | J48: Diversité, innovation, brevets, classification de noms | K48: Classification supervisée, ML, IA générative | L48: Publiques | M48: Précisées (OpenAlex, INPI, registre du commerce) | Q48: Oui | S48: 19 | T48: Ouvrir le PDF
A49: 318 | B49: RITM (Univ. Paris-Saclay) | C49: Exposition au bruit et réussite scolaire | D49: Microéconomie Appliquée | E49: Recherche académique | F49: Garrouste Manon | G49: FR | H49: Économie de l'éducation / environnement | I49: Effet de l'exposition au bruit des transports sur la réussite scolaire (brevet des collèges). | J49: Bruit, éducation, externalités, spatial | K49: Économétrie exploitant variations temporelles du trafic et variations spatiales du bruit | L49: Publiques | M49: Précisées (cartes de bruit, établissements, résultats, IPS, recensement) | Q49: Oui | S49: 1 | T49: Ouvrir le PDF
A50: 358 | B50: Drees | C50: Coefficients géographiques frontaliers | D50: Microéconomie Appliquée | E50: Institution publique | F50: Ourliac Benoit | G50: FR | H50: Économie de la santé / territoriale | I50: Coefficients géographiques frontaliers (T2A) : les hôpitaux frontaliers versent-ils des salaires plus élevés ? | J50: Salaires hospitaliers, zones frontalières, tarification | K50: Décomposition d'Oaxaca-Blinder, extensions distributionnelles | L50: Publiques | M50: Précisées (BTS Insee, SAE Drees, données géographiques) | Q50: Oui | S50: 1 | T50: Ouvrir le PDF
A51: 359 | B51: CREST | C51: Unpacking the drivers of turnover in industrial firms | D51: Microéconomie Appliquée | E51: Recherche académique | F51: Grosset-Touba Florian | G51: EN | H51: Économie du travail | I51: Moteurs du turnover dans des usines (Éthiopie, Côte d'Ivoire) à partir de dossiers RH détaillés et d'enquêtes. | J51: Turnover, salaires, usines, pays en développement | K51: Lasso, random forest, réseaux de neurones, outils de diagnostic, modèles AKM | L51: Internes (fournies) | M51: Précisées (dossiers RH confidentiels + enquêtes appariées) | Q51: Oui | S51: 19 | T51: Ouvrir le PDF
A52: 279 | B52: HeadMind Partners | C52: Newsletter AI | D52: NLP | E52: Conseil / ESN | F52: DEFOSSEZ Lucie | G52: FR | H52: ML — LLM (veille) | I52: Pipeline de newsletter hebdomadaire sur l'IA (veille multi-sources, LLM, prompt engineering). | J52: Veille, LLM, automatisation éditoriale | K52: LLM, prompt engineering | L52: Publiques (sources web) | M52: Partielles (sources de veille citées, pas de jeu de données) | O52: 1 | P52: LLM fine tuning, complètement hors scope de l'ENSAE surtout en 2A (serait déjà très limite en 3A comme projet du cours de NLP) | Q52: Oui | S52: 2 | T52: Ouvrir le PDF
A53: 303 | B53: WOAH | C53: Embeddings for Epidemic Intelligence | D53: NLP | E53: Organisation internationale | F53: Guillot Gilles | G53: EN | H53: ML — NLP / veille épidémique | I53: Évaluer des modèles d'embeddings pour détecter les signaux faibles de maladies animales dans la presse. | J53: Veille épidémique, embeddings, multilinguisme | K53: Revue et évaluation de modèles d'embeddings (voir fiche) | L53: Mixte | M53: Précisées (WAHIS, PADI-web, presse) | Q53: Oui | S53: 2 | T53: Ouvrir le PDF
A54: 313 | B54: Inria | C54: Quantifying and Mitigating Cultural Bias in Language Models | D54: NLP | E54: Recherche académique | F54: Le Bellier Gabrielle | G54: EN | H54: ML — biais culturels des LLM | I54: Mesurer les disparités culturelles de LLM (CulturalBench, 45 pays/régions) et évaluer des méthodes de mitigation. | J54: Biais, LLM, mesure statistique par groupe | K54: Modèles open-weight (Llama-3.2, Qwen2.5), inférence statistique par groupe | L54: Publiques | M54: Précisées (CulturalBench) | Q54: Oui | S54: 3 | T54: Ouvrir le PDF
A55: 315 | B55: Ekimetrics | C55: Efficient Evaluation of LLM-based Agents under a Limited Budget | D55: NLP | E55: Conseil / data science | F55: AGNIMO Yedidia | G55: EN | H55: ML — évaluation d'agents LLM | I55: Allocation efficace du budget de rollouts pour évaluer des agents LLM (biais, variance, calibration des intervalles). | J55: Évaluation d'agents, plans d'échantillonnage, SWE-bench | K55: Estimation, allocation adaptative, calibration d'intervalles de confiance | L55: Publiques | M55: Précisées (ASSERT-KTH : 500 tâches SWE-bench × 10 exécutions) | Q55: Oui | S55: 6 | T55: Ouvrir le PDF
A56: 334 | B56: Thales | C56: Algorithmes de deep learning pour le débruitage audio | D56: NLP | E56: Industrie / défense | F56: Lampe Rodolphe | G56: FR | H56: ML — audio | I56: Débruitage audio par deep learning, du CNN 1D aux Transformers. | J56: Audio, débruitage, deep learning | K56: CNN 1D, Transformers | L56: Publiques | M56: Précisées (VoxCeleb, LibriSpeech, DNS) | N56: Python, PyTorch | O56: 1 | P56: Totalement hors champ, les algorithmes de débruitage sont hors champ ENSAE et de niveau post M2. | Q56: Oui | S56: 1 | T56: Ouvrir le PDF
A57: 340 | B57: Devoteam SAS | C57: Evaluating Multilingual Reasoning in Language Models | D57: NLP | E57: Conseil / ESN | F57: riabi arij | G57: EN | H57: ML — LLM multilingue | I57: Robustesse statistique du raisonnement des LLM selon la langue (MMLU-ProX, 29 langues). | J57: LLM, multilinguisme, évaluation | K57: Petits modèles open-weight (Qwen, Llama), comparaisons appariées | L57: Publiques | M57: Précisées (MMLU-ProX) | O57: 1 | P57: LLM hors champ ENSAE en 2A. | Q57: Oui | S57: 2 | T57: Ouvrir le PDF
A58: 343 | B58: Devoteam SAS | C58: Une hallucination a-t-elle une forme – Géométrie interne des représentations et détection des erreurs des modèles de langage | D58: NLP | E58: Conseil / ESN | F58: NOËL Valentin | G58: FR | H58: ML — LLM (géométrie des représentations) | I58: Détecter les hallucinations par la géométrie interne des représentations de LLM (dimension intrinsèque, spectres). | J58: Hallucinations, géométrie, matrices aléatoires | K58: Dimension intrinsèque (Levina-Bickel), SVD, loi de Marchenko-Pastur, analyse spectrale | L58: Publiques | M58: Précisées (jeux QA publics, calcul sur ordinateur portable) | O58: 2 | P58: Sujet merveilleux mais d'une difficulté théorique énorme qui me semble être plutôt d'un niveau thèse. La géométrie est hors champ ENSAE, les LLMs sont vus en fin de 3A, quant aux graphes d'attention... il me semble que ça s'adresse plus à un diplômé du MVA | Q58: Oui | S58: 2 | T58: Ouvrir le PDF
A59: 345 | B59: Sans entreprise (application) | C59: Rapprochement automatique d'adresses d'entreprises avec la Base Adresse Nationale | D59: NLP | E59: Non applicable (sujet hors entreprise) | F59: Iakimova Iuliia | G59: FR | H59: NLP / record linkage | I59: Rapprocher automatiquement des adresses Sirene (variantes d'écriture) avec la Base Adresse Nationale ; construire un score de correspondance. | J59: Record linkage, appariement d'adresses, similarité de chaînes | K59: Distances de chaînes, phonétique, record linkage probabiliste, ML supervisé | L59: Publiques | M59: Précisées (5 000 établissements parisiens, 152 628 adresses BAN) | O59: 2 | P59: Le sujet est convaincant et sans doute "le moins impossible" de la classe des sujets NLP mais il consiste en l'utilisation de modèle de niveau fin de 3A. Il me semble "borderline" | Q59: Oui | S59: 1 | T59: Ouvrir le PDF
A60: 352 | B60: Euro-Information Développements | C60: Dictée Vocale de code LaTex | D60: NLP | E60: IT bancaire (à vérifier) | F60: Klein Antoine | G60: FR | H60: ML — parole et LLM | I60: Pipeline de dictée vocale d'équations mathématiques vers du code LaTeX (STT + LLM). | J60: Speech-to-text, LaTeX, Whisper / Voxtral / QwenASR | K60: STT open source (Whisper, Voxtral, QwenASR) + LLM | L60: Publiques | M60: Partielles (livre audio annoté, tables de conversion ; audios d'équations à produire) | Q60: Oui | S60: 1 | T60: Ouvrir le PDF
A61: 297 | B61: ENGIE | C61: Generate plausible gas consumption scenarios for the upcoming year under unknown weather conditions. | D61: Predictions | E61: Industrie / énergie | F61: Kouvabina Irina | G61: EN | H61: Énergie — scénarios météo / valeurs extrêmes | I61: Scénarios de consommation de gaz sur un an sous météo inconnue : simulateur de température + modèle consommation-température, avec rééchantillonnage des résidus (calibrés sur des températures proches de la normale). | J61: Scénarios, météo extrême, résidus, consommation de gaz | K61: GAM, GEV | L61: Internes (fournies) | M61: Partielles (gaz, températures, simulations) | Q61: Partiel | R61: Classé Predictions ; contient une problématique de génération de scénarios et de valeurs extrêmes (GEV) | S61: 2 | T61: Ouvrir le PDF
A62: 298 | B62: ENGIE | C62: Belgium's Hourly Gas Consumption Model: Accuracy and Relevance | D62: Predictions | E62: Industrie / énergie | F62: Kouvabina Irina | G62: EN | H62: Énergie — prévision de consommation | I62: Évaluer la précision du modèle horaire de consommation de gaz (Belgique) d'ENGIE, puis le recalibrer ou le remplacer. | J62: Consommation de gaz, prévision horaire, météo | K62: GAM + ajustement des résidus (existant), modèles à arbres | L62: Internes (fournies) | M62: Précisées (consommations horaires, températures, vent, calendrier) | Q62: Oui | S62: 2 | T62: Ouvrir le PDF
A63: 299 | B63: Ekimetrics | C63: Prévision de la demande pour un éditeur de presse | D63: Predictions | E63: Conseil / data science | F63: ULIANOVICI ANA | G63: FR | H63: Prévision de demande | I63: Prévision de la demande et optimisation des fournis pour un éditeur de presse (vente au numéro). | J63: Demande, fournis, points de vente | K63: LightGBM | L63: Internes (fournies) | M63: Précisées (points de vente, titres, ventes historiques) | Q63: Oui | S63: 6 | T63: Ouvrir le PDF
A64: 310 | B64: LCL | C64: Détection de la Fraude Documentaire | D64: Predictions | E64: Banque | F64: Bouyahia Mohamed Aymen | G64: FR | H64: ML — vision / fraude documentaire | I64: Détecter la falsification de documents clients (images / scans) par vision par ordinateur et VLM. | J64: Fraude, vision par ordinateur, VLM | K64: VLM, CNN, statistiques de pixels | L64: Internes (fournies) | M64: Partielles (documents authentiques et, si possible, falsifiés) | O64: 1 | P64: Traitement d'image / détection de fraude totalement hors champ ENSAE, surtout en 2A. | Q64: Oui | S64: 1 | T64: Ouvrir le PDF
A65: 316 | B65: Ekimetrics | C65: Joint Uncertainty for Multivariate Electricity-Demand Forecasts | D65: Predictions | E65: Conseil / data science | F65: AGNIMO Yedidia | G65: EN | H65: Prévision de demande d'électricité — incertitude | I65: Prévisions probabilistes jointes de la demande d'électricité multivariée (éCO2mix de RTE). | J65: Prévision probabiliste, dépendance, électricité | K65: « Modèles de prévision standards » (voir fiche) | L65: Publiques | M65: Précisées (RTE éCO2mix, depuis 2012) | Q65: Oui | S65: 6 | T65: Ouvrir le PDF
A66: 341 | B66: Crédit Agricole SA | C66: Traitement de données dans le cadre de modèle de prévisions de taux et d'encours de crédit et dépôts bancaires (ALM) | D66: Predictions | E66: Banque | F66: VIDAL Fanny | G66: FR | H66: Banque — ALM / prévision de taux et d'encours | I66: Traitement de données pour les modèles de prévision de taux et d'encours de crédits et dépôts (marge nette d'intérêt, ALM). | J66: ALM, MNI, désagrégation temporelle | K66: Régression quantile, désagrégation temporelle | L66: Mixte | M66: Précisées (Webstat Banque de France, Insee, Bloomberg) | O66: 3 | P66: Sujet complet et en adéquation avec les attentes du stat app. | Q66: Oui | S66: 1 | T66: Ouvrir le PDF
A67: 357 | B67: Dstudio | C67: Multimodal Buying Intent Prediction with Survival Analysis, Graph Learning & Learning-to-Rank | D67: Predictions | E67: Conseil / data | F67: Saada david | G67: FR | H67: Marketing / data business — survie | I67: Moteur de ranking d'entreprises à forte probabilité d'achat à court terme (survie, graphes, learning-to-rank, signaux faibles). | J67: Intention d'achat, analyse de survie, PU learning, competing risks | K67: Cox, survie paramétrique, RSF, DeepSurv, competing risks, CUSUM, learning-to-rank, graphes | L67: Mixte | M67: Partielles (panel d'entreprises à construire à partir de sources variées) | Q67: Oui | S67: 1 | T67: Ouvrir le PDF
A68: 363 | B68: eleven strategy | C68: Prédiction de la demande et du prix, et allocation optimale dans l'industrie de l'hospitality | D68: Predictions | E68: Conseil | F68: Bazaz Jazayeri Samuel | G68: FR | H68: Prévision de demande / optimisation | I68: Prédiction de la demande et du prix, puis allocation optimale de capacité dans l'hospitality. | J68: Demande, prix, optimisation, modèles pré-entraînés | K68: SARIMAX, LightGBM, Chronos 2.0, Moirai 2.0, optimisation par points intérieurs | L68: Internes (fournies) | M68: Précisées (séries anonymisées ; données clients synthétiques) | Q68: Oui | S68: 1 | T68: Ouvrir le PDF
A69: 323 | B69: CREST | C69: How can we measure health and physical dysregulation? A multiverse analysis of The Irish Longitudinal Study on Aging | D69: Santé | E69: Recherche académique | F69: Präg Patrick | G69: EN | H69: Santé / sociologie — biomarqueurs | I69: Mesurer la dysrégulation physique (allostatic load) avec TILDA par analyse multivers (specification curve). | J69: Allostatic load, biomarqueurs, robustesse | K69: Specification curve analysis (multiverse) | L69: Enquête | M69: Précisées (TILDA) | Q69: Oui | S69: 19 | T69: Ouvrir le PDF
A70: 330 | B70: CHU de Lille | C70: Mobiliser la datascience pour identifier l'heure d'induction anesthésique à partir de signaux mesurés lors des interventions chirurgicales | D70: Santé | E70: Santé (hôpital) | F70: Geay Charlotte | G70: FR | H70: Santé — signaux cliniques | I70: Identifier l'heure d'induction anesthésique à partir des signaux mesurés pendant l'intervention (entrepôt de données du CHU). | J70: Anesthésie, séries temporelles cliniques | K70: Modèles supervisés (régression, RF, réseaux de neurones) | L70: Internes (fournies) | M70: Précisées (entrepôt de données de santé du CHU de Lille) | Q70: Oui | S70: 1 | T70: Ouvrir le PDF
A71: 331 | B71: CREST | C71: Do Subjective Indicators of Wellbeing Predict an Objective Measure of Health? Are Any Deviations Dependent on Sociodemographic Characteristics? | D71: Santé | E71: Recherche académique | F71: Präg Patrick | G71: EN | H71: Santé / sociologie — bien-être | I71: Bien-être subjectif vs mesure objective de santé selon les caractéristiques sociodémographiques (UKHLS, N ≈ 13 000). | J71: Bien-être, santé objective, écarts | K71: Régression, analyse factorielle / clusters | L71: Enquête | M71: Précisées (UKHLS) | N71: SAS, Stata, R | Q71: Oui | S71: 19 | T71: Ouvrir le PDF
A72: 349 | B72: Inria | C72: Modélisation prédictive d'évènement cardiovasculaire ou de trajectoire | D72: Santé | E72: Recherche académique | F72: Katsahian Sandrine | G72: FR | H72: Santé — prédiction | I72: Prédiction d'événements cardiovasculaires (MACE) et clustering de trajectoires (UK Biobank), dans un projet de jumeaux numériques. | J72: Cardiovasculaire, trajectoires, MACE | K72: Clustering de trajectoires (non supervisé), prédiction supervisée | L72: Enquête | M72: Précisées (UK Biobank : variables cardiovasculaires structurées) | Q72: Oui | S72: 3 | T72: Ouvrir le PDF
A73: 350 | B73: Inria | C73: Clustering de trajectoires de patients atteints d'asthme sévère | D73: Santé | E73: Recherche académique | F73: Katsahian Sandrine | G73: FR | H73: Santé — survie / trajectoires | I73: Clustering de trajectoires de patients asthmatiques sévères (SNDS), avec RecForest (forêts de survie pour événements récurrents). | J73: Asthme, événements récurrents, trajectoires, SNDS | K73: RecForest / Random Survival Forests, clustering | L73: Internes (fournies) | M73: Précisées (SNDS : Assurance maladie + PMSI ; modalités d'accès non détaillées) | Q73: Oui | S73: 3 | T73: Ouvrir le PDF
A74: 284 | B74: Ined | C74: Discriminations ethnoraciales et trajectoires d'entrée dans la vie active des descendants d'immigrés | D74: Sociologie Quantitative | E74: Institution publique / recherche | F74: Nguyen Anna | G74: FR | H74: Sociologie / démographie | I74: Discriminations ethnoraciales et trajectoires d'entrée dans la vie active des descendants d'immigrés (TeO2). | J74: Discriminations, trajectoires, séquences | K74: Optimal matching, typologie de trajectoires | L74: Enquête | M74: Précisées (Trajectoires et Origines 2, Ined-Insee) | N74: R (TraMineR) | Q74: Oui | S74: 2 | T74: Ouvrir le PDF
A75: 294 | B75: Ined | C75: Evolution des thématiques de recherche en démographie : le cas des publications de l'Ined | D75: Sociologie Quantitative | E75: Institution publique / recherche | F75: Muller Arno | G75: FR | H75: Sociologie / bibliométrie | I75: Évolution des thématiques de recherche de l'Ined depuis les années 1970, à partir des publications. | J75: Démographie, bibliométrie, analyse textuelle | K75: Analyse textuelle, régressions logistiques / multinomiales | L75: Publiques | M75: Précisées (métadonnées Archined) | Q75: Oui | S75: 2 | T75: Ouvrir le PDF
A76: 319 | B76: CREST | C76: Cultural Consumption and Intersectionality. Analysis of the Survey of Public Participation in the Arts | D76: Sociologie Quantitative | E76: Recherche académique | F76: Präg Patrick | G76: EN | H76: Sociologie quantitative | I76: Consommation culturelle et intersectionnalité (SPPA 2022, ~13 000 adultes américains). | J76: Consommation culturelle, inégalités, intersectionnalité | K76: MAIHDA (multiniveau intersectionnel) | L76: Enquête | M76: Précisées (SPPA 2022) | Q76: Oui | S76: 19 | T76: Ouvrir le PDF
A77: 320 | B77: CREST | C77: Gender Identity Inequalities in Health. Analysis of the European Social Survey | D77: Sociologie Quantitative | E77: Recherche académique | F77: Präg Patrick | G77: EN | H77: Sociologie quantitative / santé | I77: Inégalités de santé selon l'identité de genre (ESS). | J77: Genre, santé, comparaison entre pays | K77: Modèles multiniveaux à effets aléatoires | L77: Enquête | M77: Précisées (ESS, publique) | N77: Stata, R | Q77: Oui | S77: 19 | T77: Ouvrir le PDF
A78: 321 | B78: CREST | C78: Conspiracy Theory Beliefs in Europe: Analysis of the European Social Survey | D78: Sociologie Quantitative | E78: Recherche académique | F78: Präg Patrick | G78: EN | H78: Sociologie quantitative | I78: Croyances conspirationnistes en Europe (ESS 2020-22, 32 pays). | J78: Croyances, multiniveau, comparaison entre pays | K78: Modèles multiniveaux à effets aléatoires | L78: Enquête | M78: Précisées (ESS, publique) | N78: Stata, R | Q78: Oui | S78: 19 | T78: Ouvrir le PDF
A79: 322 | B79: CREST | C79: Social status and health. Analysis of longitudinal survey data | D79: Sociologie Quantitative | E79: Recherche académique | F79: Präg Patrick | G79: EN | H79: Sociologie quantitative / santé | I79: Statut social perçu et santé (données longitudinales ELSA) ; effets asymétriques des hausses et baisses de statut. | J79: Statut subjectif, santé, longitudinal | K79: Effets fixes / aléatoires, décomposition à effets fixes asymétriques (Allison 2019) | L79: Enquête | M79: Précisées (ELSA) | Q79: Oui | S79: 19 | T79: Ouvrir le PDF
A80: 325 | B80: CREST | C80: Has there been a polarization of working hours? Analysis of the European Union Labor Force Survey | D80: Sociologie Quantitative | E80: Recherche académique | F80: Präg Patrick | G80: EN | H80: Sociologie quantitative / travail | I80: Polarisation des durées de travail en Europe (EU-LFS) : durées courtes (sous-emploi) et durées longues (surcharge). | J80: Heures de travail, polarisation, inégalités | K80: Régression quantile inconditionnelle, décomposition d'Oaxaca-Blinder | L80: Enquête | M80: Précisées (EU-LFS ; modalités d'accès à confirmer) | Q80: Oui | S80: 19 | T80: Ouvrir le PDF
A81: 327 | B81: CREST | C81: Sharing or Separating? Trends in Income Pooling among Couples, 1988–2022. Analysis of the ISSP Family and Changing Gender Roles Module | D81: Sociologie Quantitative | E81: Recherche académique | F81: Präg Patrick | G81: EN | H81: Sociologie quantitative | I81: Mise en commun des revenus dans les couples, 1988-2022 (ISSP). | J81: Revenus du couple, individualisation, tendances | K81: Modèles multiniveaux | L81: Enquête | M81: Précisées (ISSP) | Q81: Oui | S81: 19 | T81: Ouvrir le PDF
A82: 328 | B82: CREST | C82: His Job, Her Job? Trends in the Division of Household Labor among Couples, 1988–2022. Analysis of the ISSP Family and Changing Gender Roles Module | D82: Sociologie Quantitative | E82: Recherche académique | F82: Präg Patrick | G82: EN | H82: Sociologie quantitative | I82: Division du travail domestique dans les couples, 1988-2022 (ISSP, 5 vagues). | J82: Travail domestique, tendances, comparaisons internationales | K82: Modèles multiniveaux (individus × pays-vagues × pays) | L82: Enquête | M82: Précisées (ISSP) | Q82: Oui | S82: 19 | T82: Ouvrir le PDF
A83: 329 | B83: CREST | C83: Working Around the Clock? Trends in Evening, Night, and Weekend Work in Europe. Analysis of the European Union Labor Force Survey | D83: Sociologie Quantitative | E83: Recherche académique | F83: Präg Patrick | G83: EN | H83: Sociologie quantitative / travail | I83: Travail en soirée, de nuit et le week-end en Europe (EU-LFS). | J83: Horaires atypiques, comparaison entre pays, tendances | K83: Modèles multiniveaux | L83: Enquête | M83: Précisées (EU-LFS ; modalités d'accès à confirmer) | Q83: Oui | S83: 19 | T83: Ouvrir le PDF
A84: 346 | B84: Insee | C84: Les enfants assistés de la Nièvre pendant la guerre 1914 1918 | D84: Sociologie Quantitative | E84: Institution publique | F84: Loonis vincent | G84: FR | H84: Démographie historique | I84: Enfants assistés de la Nièvre pendant la guerre de 1914-1918 : conscrits nivernais et mortalité (110 000 conscrits). | J84: Démographie historique, assistance publique, mortalité | K84: Statistique descriptive, statistique spatiale, économétrie | L84: Internes (fournies) | M84: Précisées (registres matricules, 110 000 conscrits) | Q84: Oui | S84: 1 | T84: Ouvrir le PDF

Sheet Scoring
A1: Scoring des 83 sujets StatApp : version provisoire (à relire)
A2: Échelle 1 à 5 selon les ancres de la feuille « Critères ». Pour « Coût et risque », 5 = très coûteux ou risqué. Cellules jaunes : à renseigner par KC (A9, F4). D1 en gris italique : sujet non noté par l'ENSAE, valeur 3 par défaut (inconnue, non pénalisée). Colonnes marquées (web) : issues de la recherche web, voir la feuille « Sources web ». Familles et indice calculés par formule : modifier un score les met à jour.
E3: A. Adéquation carrière | N3: B. Signal marque et encadrant | S3: C. Exit | W3: D. Note | AC3: E. Apprentissage et différenciation | AG3: F. Coût et faisabilité | AO3: Familles et indice (formules)
A4: N° sujet | B4: Organisme | C4: Titre (fiche) | D4: Catégorie ENSAE | E4: A1 Actuariat non-vie / ACAS | F4: A2 Réassurance / risque extrême / catastrophe | G4: A3 Assurance vie / prévoyance (exploration) | H4: A4 Quant finance (research / trading) | I4: A5 Conseil généraliste (stratégie / risque) | J4: A6 Conseil spécialisé actuariat | K4: A7 Institutions et développement | L4: A8 Compétences portables | M4: A9 Motivation réelle [KC] | N4: B1 Notoriété de l'organisme (web) | O4: B2 Pertinence de la marque pour nos cibles (web) | P4: B3 Réputation de l'encadrant (web) | Q4: B4 Lisibilité en une ligne | R4: B5 Signal académique | S4: C1 Probabilité de débouché (web) | T4: C2 Recommandation et réseau (web) | U4: C3 Portée internationale (web) | V4: C4 Valeur en entretien | W4: D1 Notation et commentaire ENSAE | X4: D2 Clarté du cahier des charges | Y4: D3 Données : disponibilité et accès | Z4: D4 Adéquation au programme de 2A | AA4: D5 Calibrage scientifique | AB4: D6 Qualité probable de l'encadrement (web) | AC4: E1 Profondeur mathématique et statistique | AD4: E2 Nouveauté des méthodes acquises | AE4: E3 Livrable montrable | AF4: E4 Différenciation | AG4: F1 Budget de temps réaliste | AH4: F2 Difficulté technique | AI4: F3 Charge de préparation des données | AJ4: F4 Compatibilité avec le calendrier [KC] | AK4: F5 Risque d'exécution | AL4: F6 Répartissabilité à 4-5 | AM4: F7 Confidentialité | AN4: F8 Probabilité d'obtenir le sujet | AO4: Fit (max A1-A7) | AP4: Signal (moy. B1-B5) | AQ4: Exit (moy. C1-C4) | AR4: Note (moy. D1, D2, D4, D6) | AS4: Apprentissage (moy. E1-E4) | AT4: Risque (moy. D3, D5, F1-F7) | AU4: Indice (moyenne des six familles) | AV4: Confiance (fiche) | AW4: Confiance (web) | AX4: Note ENSAE | AY4: Ajustements après lecture du commentaire ENSAE
A5: 279 | B5: HeadMind Partners | C5: Newsletter AI | D5: NLP | E5: 1 | F5: 1 | G5: 1 | H5: 1 | I5: 1 | J5: 1 | K5: 1 | L5: 2 | N5: 2 | O5: 1 | P5: 3 | Q5: 3 | R5: 1 | S5: 2 | T5: 2 | U5: 2 | V5: 2 | W5: 1 | X5: 4 | Y5: 2 | Z5: 1 | AA5: 5 | AB5: 3 | AC5: 1 | AD5: 2 | AE5: 4 | AF5: 3 | AG5: 4 | AH5: 2 | AI5: 3 | AK5: 3 | AL5: 3 | AM5: 1 | AN5: 2 | AO5: =MAX(E5:K5) -> 1 | AP5: =AVERAGE(N5:R5) -> 2 | AQ5: =AVERAGE(S5:V5) -> 2 | AR5: =AVERAGE(W5,X5,Z5,AB5) -> 2.25 | AS5: =AVERAGE(AC5:AF5) -> 2.5 | AT5: =AVERAGE(Y5,AA5,AG5:AM5) -> 2.875 | AU5: =(AO5+AP5+AQ5+AR5+AS5+(6-AT5))/6 -> 2.1458333 | AV5: Haute | AW5: Faible | AX5: 1
A6: 280 | B6: HeadMind Partners | C6: Visual Search – Classification d'image | D6: Autre | E6: 1 | F6: 1 | G6: 1 | H6: 1 | I6: 2 | J6: 1 | K6: 1 | L6: 3 | N6: 2 | O6: 1 | P6: 3 | Q6: 3 | R6: 1 | S6: 2 | T6: 2 | U6: 2 | V6: 2 | W6: 1 | X6: 4 | Y6: 3 | Z6: 1 | AA6: 5 | AB6: 3 | AC6: 1 | AD6: 4 | AE6: 4 | AF6: 3 | AG6: 4 | AH6: 4 | AI6: 3 | AK6: 4 | AL6: 3 | AM6: 1 | AN6: 2 | AO6: =MAX(E6:K6) -> 2 | AP6: =AVERAGE(N6:R6) -> 2 | AQ6: =AVERAGE(S6:V6) -> 2 | AR6: =AVERAGE(W6,X6,Z6,AB6) -> 2.25 | AS6: =AVERAGE(AC6:AF6) -> 3 | AT6: =AVERAGE(Y6,AA6,AG6:AM6) -> 3.375 | AU6: =(AO6+AP6+AQ6+AR6+AS6+(6-AT6))/6 -> 2.3125 | AV6: Haute | AW6: Faible | AX6: 1 | AY6: D5 4→5
A7: 281 | B7: HSBC Global Asset Management | C7: Corrélation entre indices Action et Obligataire | D7: Actuariat | E7: 1 | F7: 1 | G7: 5 | H7: 3 | I7: 2 | J7: 4 | K7: 1 | L7: 3 | N7: 5 | O7: 3 | P7: 3 | Q7: 2 | R7: 2 | S7: 3 | T7: 3 | U7: 4 | V7: 4 | W7: 2 | X7: 4 | Y7: 2 | Z7: 2 | AA7: 4 | AB7: 3 | AC7: 3 | AD7: 3 | AE7: 4 | AF7: 4 | AG7: 4 | AH7: 3 | AI7: 4 | AK7: 3 | AL7: 2 | AM7: 1 | AN7: 2 | AO7: =MAX(E7:K7) -> 5 | AP7: =AVERAGE(N7:R7) -> 3 | AQ7: =AVERAGE(S7:V7) -> 3.5 | AR7: =AVERAGE(W7,X7,Z7,AB7) -> 2.75 | AS7: =AVERAGE(AC7:AF7) -> 3.5 | AT7: =AVERAGE(Y7,AA7,AG7:AM7) -> 2.875 | AU7: =(AO7+AP7+AQ7+AR7+AS7+(6-AT7))/6 -> 3.4791667 | AV7: Haute | AW7: Faible | AX7: 2 | AY7: D4 3→2, D5 3→4
A8: 282 | B8: HSBC Global Asset Management | C8: Stratégies optionnelles de protection pour investisseurs de long terme | D8: Finance | E8: 1 | F8: 1 | G8: 3 | H8: 5 | I8: 2 | J8: 2 | K8: 1 | L8: 3 | N8: 5 | O8: 3 | P8: 3 | Q8: 4 | R8: 3 | S8: 3 | T8: 3 | U8: 4 | V8: 4 | W8: 3 | X8: 4 | Y8: 2 | Z8: 5 | AA8: 3 | AB8: 3 | AC8: 4 | AD8: 3 | AE8: 4 | AF8: 3 | AG8: 3 | AH8: 3 | AI8: 2 | AK8: 2 | AL8: 2 | AM8: 1 | AN8: 3 | AO8: =MAX(E8:K8) -> 5 | AP8: =AVERAGE(N8:R8) -> 3.6 | AQ8: =AVERAGE(S8:V8) -> 3.5 | AR8: =AVERAGE(W8,X8,Z8,AB8) -> 3.75 | AS8: =AVERAGE(AC8:AF8) -> 3.5 | AT8: =AVERAGE(Y8,AA8,AG8:AM8) -> 2.25 | AU8: =(AO8+AP8+AQ8+AR8+AS8+(6-AT8))/6 -> 3.85 | AV8: Moyenne | AW8: Faible | AX8: 3 | AY8: D4 4→5
A9: 284 | B9: Ined | C9: Discriminations ethnoraciales et trajectoires d'entrée dans la vie active des descendants d'immigrés | D9: Sociologie Quantitative | E9: 1 | F9: 1 | G9: 1 | H9: 1 | I9: 1 | J9: 1 | K9: 2 | L9: 3 | N9: 3 | O9: 2 | P9: 3 | Q9: 3 | R9: 3 | S9: 2 | T9: 3 | U9: 3 | V9: 3 | W9: 3 | X9: 5 | Y9: 2 | Z9: 2 | AA9: 3 | AB9: 3 | AC9: 2 | AD9: 4 | AE9: 3 | AF9: 4 | AG9: 3 | AH9: 3 | AI9: 4 | AK9: 2 | AL9: 3 | AM9: 1 | AN9: 1 | AO9: =MAX(E9:K9) -> 2 | AP9: =AVERAGE(N9:R9) -> 2.8 | AQ9: =AVERAGE(S9:V9) -> 2.75 | AR9: =AVERAGE(W9,X9,Z9,AB9) -> 3.25 | AS9: =AVERAGE(AC9:AF9) -> 3.25 | AT9: =AVERAGE(Y9,AA9,AG9:AM9) -> 2.625 | AU9: =(AO9+AP9+AQ9+AR9+AS9+(6-AT9))/6 -> 2.9041667 | AV9: Haute | AW9: Faible | AX9: non noté
A10: 285 | B10: SCOR | C10: Life and health insurance pricing with geographical data | D10: Actuariat | E10: 3 | F10: 1 | G10: 5 | H10: 1 | I10: 2 | J10: 4 | K10: 1 | L10: 5 | N10: 4 | O10: 5 | P10: 3 | Q10: 5 | R10: 3 | S10: 5 | T10: 4 | U10: 5 | V10: 4 | W10: 3 | X10: 4 | Y10: 4 | Z10: 5 | AA10: 2 | AB10: 3 | AC10: 3 | AD10: 4 | AE10: 2 | AF10: 3 | AG10: 3 | AH10: 3 | AI10: 4 | AK10: 3 | AL10: 2 | AM10: 4 | AN10: 5 | AO10: =MAX(E10:K10) -> 5 | AP10: =AVERAGE(N10:R10) -> 4 | AQ10: =AVERAGE(S10:V10) -> 4.5 | AR10: =AVERAGE(W10,X10,Z10,AB10) -> 3.75 | AS10: =AVERAGE(AC10:AF10) -> 3 | AT10: =AVERAGE(Y10,AA10,AG10:AM10) -> 3.125 | AU10: =(AO10+AP10+AQ10+AR10+AS10+(6-AT10))/6 -> 3.8541667 | AV10: Haute | AW10: Faible | AX10: 3
A11: 288 | B11: Société Générale | C11: L'incertitude des systèmes multi-agents | D11: Autre | E11: 1 | F11: 1 | G11: 1 | H11: 1 | I11: 2 | J11: 1 | K11: 1 | L11: 3 | N11: 5 | O11: 3 | P11: 3 | Q11: 3 | R11: 4 | S11: 3 | T11: 3 | U11: 4 | V11: 3 | W11: 2 | X11: 4 | Y11: 3 | Z11: 1 | AA11: 5 | AB11: 3 | AC11: 3 | AD11: 5 | AE11: 4 | AF11: 3 | AG11: 5 | AH11: 5 | AI11: 3 | AK11: 5 | AL11: 3 | AM11: 2 | AN11: 3 | AO11: =MAX(E11:K11) -> 2 | AP11: =AVERAGE(N11:R11) -> 3.6 | AQ11: =AVERAGE(S11:V11) -> 3.25 | AR11: =AVERAGE(W11,X11,Z11,AB11) -> 2.5 | AS11: =AVERAGE(AC11:AF11) -> 3.75 | AT11: =AVERAGE(Y11,AA11,AG11:AM11) -> 3.875 | AU11: =(AO11+AP11+AQ11+AR11+AS11+(6-AT11))/6 -> 2.8708333 | AV11: Haute | AW11: Faible | AX11: 2
A12: 289 | B12: DG Trésor | C12: Analyse sectorielle des fluctuations du prix du pétrole | D12: Macroeconomie | E12: 1 | F12: 1 | G12: 1 | H12: 2 | I12: 2 | J12: 1 | K12: 3 | L12: 3 | N12: 4 | O12: 4 | P12: 3 | Q12: 4 | R12: 3 | S12: 3 | T12: 4 | U12: 3 | V12: 4 | W12: 3 | X12: 3 | Y12: 1 | Z12: 5 | AA12: 2 | AB12: 3 | AC12: 3 | AD12: 3 | AE12: 3 | AF12: 3 | AG12: 2 | AH12: 2 | AI12: 3 | AK12: 1 | AL12: 3 | AM12: 1 | AN12: 3 | AO12: =MAX(E12:K12) -> 3 | AP12: =AVERAGE(N12:R12) -> 3.6 | AQ12: =AVERAGE(S12:V12) -> 3.5 | AR12: =AVERAGE(W12,X12,Z12,AB12) -> 3.5 | AS12: =AVERAGE(AC12:AF12) -> 3 | AT12: =AVERAGE(Y12,AA12,AG12:AM12) -> 1.875 | AU12: =(AO12+AP12+AQ12+AR12+AS12+(6-AT12))/6 -> 3.4541667 | AV12: Haute | AW12: Faible | AX12: non noté
A13: 290 | B13: DG Trésor | C13: L'impact économique du vieillissement | D13: Macroeconomie | E13: 1 | F13: 1 | G13: 2 | H13: 1 | I13: 2 | J13: 1 | K13: 3 | L13: 3 | N13: 4 | O13: 4 | P13: 3 | Q13: 5 | R13: 3 | S13: 3 | T13: 4 | U13: 3 | V13: 3 | W13: 3 | X13: 3 | Y13: 1 | Z13: 4 | AA13: 3 | AB13: 3 | AC13: 3 | AD13: 2 | AE13: 3 | AF13: 3 | AG13: 2 | AH13: 3 | AI13: 2 | AK13: 2 | AL13: 2 | AM13: 1 | AN13: 3 | AO13: =MAX(E13:K13) -> 3 | AP13: =AVERAGE(N13:R13) -> 3.8 | AQ13: =AVERAGE(S13:V13) -> 3.25 | AR13: =AVERAGE(W13,X13,Z13,AB13) -> 3.25 | AS13: =AVERAGE(AC13:AF13) -> 2.75 | AT13: =AVERAGE(Y13,AA13,AG13:AM13) -> 2 | AU13: =(AO13+AP13+AQ13+AR13+AS13+(6-AT13))/6 -> 3.3416667 | AV13: Moyenne | AW13: Faible | AX13: non noté
A14: 291 | B14: RTE | C14: Analyse longitudinale de la base OPERAT - Comment les consommations énergétiques des établissements tertiaire… | D14: Environnement Energie et Mobilité | E14: 1 | F14: 1 | G14: 1 | H14: 1 | I14: 1 | J14: 1 | K14: 2 | L14: 3 | N14: 4 | O14: 2 | P14: 3 | Q14: 2 | R14: 2 | S14: 3 | T14: 2 | U14: 2 | V14: 3 | W14: 3 | X14: 3 | Y14: 2 | Z14: 4 | AA14: 4 | AB14: 3 | AC14: 2 | AD14: 2 | AE14: 3 | AF14: 3 | AG14: 3 | AH14: 2 | AI14: 3 | AK14: 2 | AL14: 3 | AM14: 2 | AN14: 2 | AO14: =MAX(E14:K14) -> 2 | AP14: =AVERAGE(N14:R14) -> 2.6 | AQ14: =AVERAGE(S14:V14) -> 2.5 | AR14: =AVERAGE(W14,X14,Z14,AB14) -> 3.25 | AS14: =AVERAGE(AC14:AF14) -> 2.5 | AT14: =AVERAGE(Y14,AA14,AG14:AM14) -> 2.625 | AU14: =(AO14+AP14+AQ14+AR14+AS14+(6-AT14))/6 -> 2.7041667 | AV14: Moyenne | AW14: Faible | AX14: non noté
A15: 292 | B15: CREST ENSAE | C15: Semantic Credit Risk Pricing with Large Language Models | D15: Actuariat | E15: 2 | F15: 1 | G15: 1 | H15: 2 | I15: 2 | J15: 2 | K15: 1 | L15: 4 | N15: 4 | O15: 3 | P15: 2 | Q15: 4 | R15: 4 | S15: 2 | T15: 3 | U15: 4 | V15: 4 | W15: 3 | X15: 4 | Y15: 1 | Z15: 3 | AA15: 3 | AB15: 3 | AC15: 2 | AD15: 5 | AE15: 5 | AF15: 3 | AG15: 3 | AH15: 4 | AI15: 1 | AK15: 4 | AL15: 2 | AM15: 1 | AN15: 4 | AO15: =MAX(E15:K15) -> 2 | AP15: =AVERAGE(N15:R15) -> 3.4 | AQ15: =AVERAGE(S15:V15) -> 3.25 | AR15: =AVERAGE(W15,X15,Z15,AB15) -> 3.25 | AS15: =AVERAGE(AC15:AF15) -> 3.75 | AT15: =AVERAGE(Y15,AA15,AG15:AM15) -> 2.375 | AU15: =(AO15+AP15+AQ15+AR15+AS15+(6-AT15))/6 -> 3.2125 | AV15: Haute | AW15: Faible | AX15: non noté
A16: 293 | B16: QuantCube Technology | C16: Nowcasting hiérarchique de la consommation des ménages en Espagne | D16: Macroeconomie | E16: 1 | F16: 1 | G16: 1 | H16: 2 | I16: 2 | J16: 1 | K16: 3 | L16: 4 | N16: 2 | O16: 3 | P16: 3 | Q16: 4 | R16: 4 | S16: 2 | T16: 2 | U16: 3 | V16: 4 | W16: 3 | X16: 5 | Y16: 3 | Z16: 3 | AA16: 4 | AB16: 3 | AC16: 4 | AD16: 5 | AE16: 4 | AF16: 5 | AG16: 4 | AH16: 4 | AI16: 4 | AK16: 3 | AL16: 2 | AM16: 3 | AN16: 2 | AO16: =MAX(E16:K16) -> 3 | AP16: =AVERAGE(N16:R16) -> 3.2 | AQ16: =AVERAGE(S16:V16) -> 2.75 | AR16: =AVERAGE(W16,X16,Z16,AB16) -> 3.5 | AS16: =AVERAGE(AC16:AF16) -> 4.5 | AT16: =AVERAGE(Y16,AA16,AG16:AM16) -> 3.375 | AU16: =(AO16+AP16+AQ16+AR16+AS16+(6-AT16))/6 -> 3.2625 | AV16: Haute | AW16: Faible | AX16: non noté
A17: 294 | B17: Ined | C17: Evolution des thématiques de recherche en démographie : le cas des publications de l'Ined | D17: Sociologie Quantitative | E17: 1 | F17: 1 | G17: 1 | H17: 1 | I17: 1 | J17: 1 | K17: 2 | L17: 3 | N17: 3 | O17: 2 | P17: 3 | Q17: 3 | R17: 3 | S17: 2 | T17: 3 | U17: 3 | V17: 3 | W17: 3 | X17: 3 | Y17: 2 | Z17: 3 | AA17: 3 | AB17: 3 | AC17: 2 | AD17: 3 | AE17: 3 | AF17: 4 | AG17: 3 | AH17: 3 | AI17: 4 | AK17: 2 | AL17: 3 | AM17: 1 | AN17: 1 | AO17: =MAX(E17:K17) -> 2 | AP17: =AVERAGE(N17:R17) -> 2.8 | AQ17: =AVERAGE(S17:V17) -> 2.75 | AR17: =AVERAGE(W17,X17,Z17,AB17) -> 3 | AS17: =AVERAGE(AC17:AF17) -> 3 | AT17: =AVERAGE(Y17,AA17,AG17:AM17) -> 2.625 | AU17: =(AO17+AP17+AQ17+AR17+AS17+(6-AT17))/6 -> 2.8208333 | AV17: Haute | AW17: Faible | AX17: non noté
A18: 295 | B18: QuantCube Technology | C18: Nowcasting des Nonfarm Payrolls américains à partir de données alternatives haute fréquence | D18: Macroeconomie | E18: 1 | F18: 1 | G18: 1 | H18: 3 | I18: 2 | J18: 1 | K18: 2 | L18: 4 | N18: 2 | O18: 3 | P18: 3 | Q18: 4 | R18: 3 | S18: 2 | T18: 2 | U18: 3 | V18: 5 | W18: 3 | X18: 5 | Y18: 3 | Z18: 3 | AA18: 3 | AB18: 3 | AC18: 4 | AD18: 4 | AE18: 4 | AF18: 3 | AG18: 4 | AH18: 4 | AI18: 4 | AK18: 3 | AL18: 2 | AM18: 3 | AN18: 3 | AO18: =MAX(E18:K18) -> 3 | AP18: =AVERAGE(N18:R18) -> 3 | AQ18: =AVERAGE(S18:V18) -> 3 | AR18: =AVERAGE(W18,X18,Z18,AB18) -> 3.5 | AS18: =AVERAGE(AC18:AF18) -> 3.75 | AT18: =AVERAGE(Y18,AA18,AG18:AM18) -> 3.25 | AU18: =(AO18+AP18+AQ18+AR18+AS18+(6-AT18))/6 -> 3.1666667 | AV18: Haute | AW18: Faible | AX18: non noté
A19: 296 | B19: Partners Group | C19: Mandates representation and optimization via cross trades | D19: Finance | E19: 1 | F19: 1 | G19: 1 | H19: 3 | I19: 2 | J19: 1 | K19: 1 | L19: 3 | N19: 4 | O19: 3 | P19: 3 | Q19: 2 | R19: 2 | S19: 4 | T19: 3 | U19: 5 | V19: 3 | W19: 2 | X19: 1 | Y19: 5 | Z19: 3 | AA19: 4 | AB19: 3 | AC19: 3 | AD19: 3 | AE19: 2 | AF19: 4 | AG19: 4 | AH19: 4 | AI19: 4 | AK19: 4 | AL19: 3 | AM19: 4 | AN19: 2 | AO19: =MAX(E19:K19) -> 3 | AP19: =AVERAGE(N19:R19) -> 2.8 | AQ19: =AVERAGE(S19:V19) -> 3.75 | AR19: =AVERAGE(W19,X19,Z19,AB19) -> 2.25 | AS19: =AVERAGE(AC19:AF19) -> 3 | AT19: =AVERAGE(Y19,AA19,AG19:AM19) -> 4 | AU19: =(AO19+AP19+AQ19+AR19+AS19+(6-AT19))/6 -> 2.8 | AV19: Moyenne | AW19: Faible | AX19: 2 | AY19: D2 2→1, D3 4→5
A20: 297 | B20: ENGIE | C20: Generate plausible gas consumption scenarios for the upcoming year under unknown weather conditions. | D20: Predictions | E20: 2 | F20: 4 | G20: 1 | H20: 2 | I20: 3 | J20: 1 | K20: 1 | L20: 4 | N20: 5 | O20: 2 | P20: 3 | Q20: 3 | R20: 3 | S20: 3 | T20: 2 | U20: 5 | V20: 4 | W20: 3 | X20: 3 | Y20: 3 | Z20: 3 | AA20: 3 | AB20: 3 | AC20: 4 | AD20: 4 | AE20: 3 | AF20: 4 | AG20: 3 | AH20: 3 | AI20: 3 | AK20: 3 | AL20: 2 | AM20: 3 | AN20: 2 | AO20: =MAX(E20:K20) -> 4 | AP20: =AVERAGE(N20:R20) -> 3.2 | AQ20: =AVERAGE(S20:V20) -> 3.5 | AR20: =AVERAGE(W20,X20,Z20,AB20) -> 3 | AS20: =AVERAGE(AC20:AF20) -> 3.75 | AT20: =AVERAGE(Y20,AA20,AG20:AM20) -> 2.875 | AU20: =(AO20+AP20+AQ20+AR20+AS20+(6-AT20))/6 -> 3.4291667 | AV20: Moyenne | AW20: Faible | AX20: non noté
A21: 298 | B21: ENGIE | C21: Belgium's Hourly Gas Consumption Model: Accuracy and Relevance | D21: Predictions | E21: 1 | F21: 1 | G21: 1 | H21: 1 | I21: 2 | J21: 1 | K21: 1 | L21: 3 | N21: 5 | O21: 2 | P21: 3 | Q21: 3 | R21: 2 | S21: 3 | T21: 2 | U21: 5 | V21: 3 | W21: 3 | X21: 3 | Y21: 3 | Z21: 4 | AA21: 3 | AB21: 3 | AC21: 2 | AD21: 2 | AE21: 2 | AF21: 2 | AG21: 3 | AH21: 2 | AI21: 2 | AK21: 3 | AL21: 3 | AM21: 4 | AN21: 2 | AO21: =MAX(E21:K21) -> 2 | AP21: =AVERAGE(N21:R21) -> 3 | AQ21: =AVERAGE(S21:V21) -> 3.25 | AR21: =AVERAGE(W21,X21,Z21,AB21) -> 3.25 | AS21: =AVERAGE(AC21:AF21) -> 2 | AT21: =AVERAGE(Y21,AA21,AG21:AM21) -> 2.875 | AU21: =(AO21+AP21+AQ21+AR21+AS21+(6-AT21))/6 -> 2.7708333 | AV21: Moyenne | AW21: Faible | AX21: non noté
A22: 299 | B22: Ekimetrics | C22: Prévision de la demande pour un éditeur de presse | D22: Predictions | E22: 1 | F22: 1 | G22: 1 | H22: 1 | I22: 3 | J22: 1 | K22: 1 | L22: 3 | N22: 3 | O22: 3 | P22: 3 | Q22: 4 | R22: 2 | S22: 4 | T22: 3 | U22: 4 | V22: 4 | W22: 3 | X22: 2 | Y22: 4 | Z22: 3 | AA22: 3 | AB22: 3 | AC22: 2 | AD22: 2 | AE22: 2 | AF22: 2 | AG22: 3 | AH22: 2 | AI22: 4 | AK22: 3 | AL22: 3 | AM22: 4 | AN22: 2 | AO22: =MAX(E22:K22) -> 3 | AP22: =AVERAGE(N22:R22) -> 3 | AQ22: =AVERAGE(S22:V22) -> 3.75 | AR22: =AVERAGE(W22,X22,Z22,AB22) -> 2.75 | AS22: =AVERAGE(AC22:AF22) -> 2 | AT22: =AVERAGE(Y22,AA22,AG22:AM22) -> 3.25 | AU22: =(AO22+AP22+AQ22+AR22+AS22+(6-AT22))/6 -> 2.875 | AV22: Moyenne | AW22: Faible | AX22: non noté
A23: 300 | B23: European University Institute | C23: The Effects of Geopolitical Risk on Innovation: Evidence from International Patent Data | D23: Macroeconomie | E23: 1 | F23: 1 | G23: 1 | H23: 2 | I23: 2 | J23: 1 | K23: 3 | L23: 4 | N23: 4 | O23: 3 | P23: 3 | Q23: 4 | R23: 4 | S23: 2 | T23: 3 | U23: 5 | V23: 4 | W23: 3 | X23: 3 | Y23: 2 | Z23: 4 | AA23: 3 | AB23: 3 | AC23: 3 | AD23: 4 | AE23: 4 | AF23: 4 | AG23: 4 | AH23: 3 | AI23: 4 | AK23: 3 | AL23: 2 | AM23: 1 | AN23: 2 | AO23: =MAX(E23:K23) -> 3 | AP23: =AVERAGE(N23:R23) -> 3.6 | AQ23: =AVERAGE(S23:V23) -> 3.5 | AR23: =AVERAGE(W23,X23,Z23,AB23) -> 3.25 | AS23: =AVERAGE(AC23:AF23) -> 3.75 | AT23: =AVERAGE(Y23,AA23,AG23:AM23) -> 2.75 | AU23: =(AO23+AP23+AQ23+AR23+AS23+(6-AT23))/6 -> 3.3916667 | AV23: Moyenne | AW23: Faible | AX23: non noté
A24: 301 | B24: Withings SAS | C24: Souscription et résiliation d'un abonnement de santé connectée : détecter les signaux d'usage précurseurs et… | D24: Marketing Quantitatif | E24: 1 | F24: 1 | G24: 2 | H24: 2 | I24: 4 | J24: 1 | K24: 1 | L24: 5 | N24: 4 | O24: 2 | P24: 3 | Q24: 3 | R24: 3 | S24: 2 | T24: 2 | U24: 3 | V24: 5 | W24: 3 | X24: 5 | Y24: 2 | Z24: 4 | AA24: 3 | AB24: 3 | AC24: 4 | AD24: 5 | AE24: 3 | AF24: 3 | AG24: 4 | AH24: 4 | AI24: 4 | AK24: 3 | AL24: 2 | AM24: 4 | AN24: 3 | AO24: =MAX(E24:K24) -> 4 | AP24: =AVERAGE(N24:R24) -> 3 | AQ24: =AVERAGE(S24:V24) -> 3 | AR24: =AVERAGE(W24,X24,Z24,AB24) -> 3.75 | AS24: =AVERAGE(AC24:AF24) -> 3.75 | AT24: =AVERAGE(Y24,AA24,AG24:AM24) -> 3.25 | AU24: =(AO24+AP24+AQ24+AR24+AS24+(6-AT24))/6 -> 3.375 | AV24: Haute | AW24: Faible | AX24: non noté
A25: 302 | B25: WOAH | C25: Animal Health as Market and Trade Intelligence | D25: Microéconomie Appliquée | E25: 1 | F25: 3 | G25: 1 | H25: 3 | I25: 2 | J25: 1 | K25: 5 | L25: 5 | N25: 3 | O25: 3 | P25: 4 | Q25: 3 | R25: 3 | S25: 3 | T25: 3 | U25: 5 | V25: 4 | W25: 3 | X25: 2 | Y25: 2 | Z25: 4 | AA25: 4 | AB25: 3 | AC25: 3 | AD25: 5 | AE25: 4 | AF25: 5 | AG25: 4 | AH25: 4 | AI25: 5 | AK25: 3 | AL25: 1 | AM25: 1 | AN25: 2 | AO25: =MAX(E25:K25) -> 5 | AP25: =AVERAGE(N25:R25) -> 3.2 | AQ25: =AVERAGE(S25:V25) -> 3.75 | AR25: =AVERAGE(W25,X25,Z25,AB25) -> 3 | AS25: =AVERAGE(AC25:AF25) -> 4.25 | AT25: =AVERAGE(Y25,AA25,AG25:AM25) -> 3 | AU25: =(AO25+AP25+AQ25+AR25+AS25+(6-AT25))/6 -> 3.7 | AV25: Moyenne | AW25: Moyenne | AX25: non noté
A26: 303 | B26: WOAH | C26: Embeddings for Epidemic Intelligence | D26: NLP | E26: 1 | F26: 2 | G26: 1 | H26: 1 | I26: 2 | J26: 1 | K26: 4 | L26: 5 | N26: 3 | O26: 3 | P26: 4 | Q26: 4 | R26: 4 | S26: 3 | T26: 3 | U26: 5 | V26: 5 | W26: 3 | X26: 5 | Y26: 3 | Z26: 2 | AA26: 4 | AB26: 3 | AC26: 4 | AD26: 5 | AE26: 4 | AF26: 4 | AG26: 5 | AH26: 4 | AI26: 5 | AK26: 4 | AL26: 2 | AM26: 1 | AN26: 2 | AO26: =MAX(E26:K26) -> 4 | AP26: =AVERAGE(N26:R26) -> 3.6 | AQ26: =AVERAGE(S26:V26) -> 4 | AR26: =AVERAGE(W26,X26,Z26,AB26) -> 3.25 | AS26: =AVERAGE(AC26:AF26) -> 4.25 | AT26: =AVERAGE(Y26,AA26,AG26:AM26) -> 3.5 | AU26: =(AO26+AP26+AQ26+AR26+AS26+(6-AT26))/6 -> 3.6 | AV26: Haute | AW26: Moyenne | AX26: non noté
A27: 304 | B27: GazTransport et Technigaz | C27: Identification des anomalies de trajectoires de méthaniers pour l'obtention de statistiques agrégées sur les… | D27: Environnement Energie et Mobilité | E27: 1 | F27: 1 | G27: 1 | H27: 1 | I27: 2 | J27: 1 | K27: 1 | L27: 4 | N27: 3 | O27: 1 | P27: 3 | Q27: 2 | R27: 2 | S27: 2 | T27: 2 | U27: 3 | V27: 4 | W27: 3 | X27: 4 | Y27: 3 | Z27: 3 | AA27: 3 | AB27: 3 | AC27: 2 | AD27: 3 | AE27: 3 | AF27: 3 | AG27: 4 | AH27: 3 | AI27: 3 | AK27: 3 | AL27: 2 | AM27: 3 | AN27: 2 | AO27: =MAX(E27:K27) -> 2 | AP27: =AVERAGE(N27:R27) -> 2.2 | AQ27: =AVERAGE(S27:V27) -> 2.75 | AR27: =AVERAGE(W27,X27,Z27,AB27) -> 3.25 | AS27: =AVERAGE(AC27:AF27) -> 2.75 | AT27: =AVERAGE(Y27,AA27,AG27:AM27) -> 3 | AU27: =(AO27+AP27+AQ27+AR27+AS27+(6-AT27))/6 -> 2.6583333 | AV27: Haute | AW27: Faible | AX27: non noté
A28: 305 | B28: CREST | C28: Disaster Risk Reduction and Climate Change Adaptation in European Metropolises | D28: Environnement Energie et Mobilité | E28: 1 | F28: 4 | G28: 1 | H28: 1 | I28: 2 | J28: 1 | K28: 4 | L28: 4 | N28: 4 | O28: 3 | P28: 5 | Q28: 4 | R28: 5 | S28: 2 | T28: 3 | U28: 5 | V28: 3 | W28: 3 | X28: 2 | Y28: 3 | Z28: 2 | AA28: 4 | AB28: 4 | AC28: 3 | AD28: 5 | AE28: 4 | AF28: 5 | AG28: 4 | AH28: 4 | AI28: 4 | AK28: 3 | AL28: 2 | AM28: 2 | AN28: 2 | AO28: =MAX(E28:K28) -> 4 | AP28: =AVERAGE(N28:R28) -> 4.2 | AQ28: =AVERAGE(S28:V28) -> 3.25 | AR28: =AVERAGE(W28,X28,Z28,AB28) -> 2.75 | AS28: =AVERAGE(AC28:AF28) -> 4.25 | AT28: =AVERAGE(Y28,AA28,AG28:AM28) -> 3.25 | AU28: =(AO28+AP28+AQ28+AR28+AS28+(6-AT28))/6 -> 3.5333333 | AV28: Moyenne | AW28: Moyenne | AX28: non noté
A29: 306 | B29: CREST UMR 9194 | C29: Résultats des élections municipales à Paris et caractéristiques des quartiers | D29: Microéconomie Appliquée | E29: 1 | F29: 1 | G29: 1 | H29: 1 | I29: 1 | J29: 1 | K29: 2 | L29: 3 | N29: 4 | O29: 3 | P29: 4 | Q29: 4 | R29: 3 | S29: 2 | T29: 3 | U29: 4 | V29: 3 | W29: 3 | X29: 3 | Y29: 1 | Z29: 4 | AA29: 3 | AB29: 4 | AC29: 2 | AD29: 3 | AE29: 4 | AF29: 4 | AG29: 3 | AH29: 2 | AI29: 3 | AK29: 2 | AL29: 3 | AM29: 1 | AN29: 3 | AO29: =MAX(E29:K29) -> 2 | AP29: =AVERAGE(N29:R29) -> 3.6 | AQ29: =AVERAGE(S29:V29) -> 3 | AR29: =AVERAGE(W29,X29,Z29,AB29) -> 3.5 | AS29: =AVERAGE(AC29:AF29) -> 3.25 | AT29: =AVERAGE(Y29,AA29,AG29:AM29) -> 2.25 | AU29: =(AO29+AP29+AQ29+AR29+AS29+(6-AT29))/6 -> 3.1833333 | AV29: Haute | AW29: Moyenne | AX29: non noté
A30: 307 | B30: CREST UMR 9194 | C30: Prix des forêts, composition du couvert forestier et caractéristiques locales | D30: Microéconomie Appliquée | E30: 1 | F30: 2 | G30: 1 | H30: 1 | I30: 2 | J30: 1 | K30: 2 | L30: 4 | N30: 4 | O30: 3 | P30: 4 | Q30: 3 | R30: 4 | S30: 2 | T30: 3 | U30: 4 | V30: 4 | W30: 3 | X30: 4 | Y30: 2 | Z30: 4 | AA30: 2 | AB30: 4 | AC30: 3 | AD30: 3 | AE30: 4 | AF30: 4 | AG30: 3 | AH30: 2 | AI30: 4 | AK30: 2 | AL30: 3 | AM30: 1 | AN30: 2 | AO30: =MAX(E30:K30) -> 2 | AP30: =AVERAGE(N30:R30) -> 3.6 | AQ30: =AVERAGE(S30:V30) -> 3.25 | AR30: =AVERAGE(W30,X30,Z30,AB30) -> 3.75 | AS30: =AVERAGE(AC30:AF30) -> 3.5 | AT30: =AVERAGE(Y30,AA30,AG30:AM30) -> 2.375 | AU30: =(AO30+AP30+AQ30+AR30+AS30+(6-AT30))/6 -> 3.2875 | AV30: Haute | AW30: Moyenne | AX30: non noté
A31: 308 | B31: Ekimetrics | C31: Sensibilité au choix des lois a priori dans les modèles bayésiens hiérarchiques : effets sur l'estimation et… | D31: Marketing Quantitatif | E31: 1 | F31: 1 | G31: 1 | H31: 2 | I31: 3 | J31: 1 | K31: 1 | L31: 5 | N31: 3 | O31: 3 | P31: 3 | Q31: 2 | R31: 5 | S31: 4 | T31: 3 | U31: 4 | V31: 3 | W31: 3 | X31: 5 | Y31: 1 | Z31: 2 | AA31: 5 | AB31: 3 | AC31: 5 | AD31: 5 | AE31: 5 | AF31: 5 | AG31: 5 | AH31: 5 | AI31: 1 | AK31: 3 | AL31: 2 | AM31: 2 | AN31: 1 | AO31: =MAX(E31:K31) -> 3 | AP31: =AVERAGE(N31:R31) -> 3.2 | AQ31: =AVERAGE(S31:V31) -> 3.5 | AR31: =AVERAGE(W31,X31,Z31,AB31) -> 3.25 | AS31: =AVERAGE(AC31:AF31) -> 5 | AT31: =AVERAGE(Y31,AA31,AG31:AM31) -> 3 | AU31: =(AO31+AP31+AQ31+AR31+AS31+(6-AT31))/6 -> 3.4916667 | AV31: Haute | AW31: Faible | AX31: non noté
A32: 309 | B32: Ekimetrics | C32: Apprentissage de lois a priori par transfert entre portefeuilles : une approche de meta-learning bayésien | D32: Actuariat | E32: 4 | F32: 1 | G32: 1 | H32: 2 | I32: 3 | J32: 3 | K32: 1 | L32: 5 | N32: 3 | O32: 3 | P32: 3 | Q32: 2 | R32: 4 | S32: 4 | T32: 3 | U32: 4 | V32: 3 | W32: 3 | X32: 5 | Y32: 1 | Z32: 2 | AA32: 4 | AB32: 3 | AC32: 5 | AD32: 5 | AE32: 4 | AF32: 5 | AG32: 4 | AH32: 5 | AI32: 1 | AK32: 3 | AL32: 2 | AM32: 2 | AN32: 2 | AO32: =MAX(E32:K32) -> 4 | AP32: =AVERAGE(N32:R32) -> 3 | AQ32: =AVERAGE(S32:V32) -> 3.5 | AR32: =AVERAGE(W32,X32,Z32,AB32) -> 3.25 | AS32: =AVERAGE(AC32:AF32) -> 4.75 | AT32: =AVERAGE(Y32,AA32,AG32:AM32) -> 2.75 | AU32: =(AO32+AP32+AQ32+AR32+AS32+(6-AT32))/6 -> 3.625 | AV32: Haute | AW32: Faible | AX32: non noté
A33: 310 | B33: LCL | C33: Détection de la Fraude Documentaire | D33: Predictions | E33: 1 | F33: 1 | G33: 1 | H33: 1 | I33: 2 | J33: 1 | K33: 1 | L33: 3 | N33: 4 | O33: 2 | P33: 3 | Q33: 4 | R33: 2 | S33: 2 | T33: 2 | U33: 1 | V33: 3 | W33: 1 | X33: 3 | Y33: 5 | Z33: 1 | AA33: 5 | AB33: 3 | AC33: 2 | AD33: 4 | AE33: 3 | AF33: 3 | AG33: 5 | AH33: 5 | AI33: 5 | AK33: 5 | AL33: 3 | AM33: 3 | AN33: 2 | AO33: =MAX(E33:K33) -> 2 | AP33: =AVERAGE(N33:R33) -> 3 | AQ33: =AVERAGE(S33:V33) -> 2 | AR33: =AVERAGE(W33,X33,Z33,AB33) -> 2 | AS33: =AVERAGE(AC33:AF33) -> 3 | AT33: =AVERAGE(Y33,AA33,AG33:AM33) -> 4.5 | AU33: =(AO33+AP33+AQ33+AR33+AS33+(6-AT33))/6 -> 2.25 | AV33: Moyenne | AW33: Faible | AX33: 1 | AY33: D5 4→5
A34: 311 | B34: CREST et Univ. Paris 1 Panthéon-Sorbonne | C34: Les discriminations salariales entre hommes et femmes : étude des enquêtes du Céreq | D34: Microéconomie Appliquée | E34: 1 | F34: 1 | G34: 1 | H34: 1 | I34: 1 | J34: 1 | K34: 2 | L34: 3 | N34: 4 | O34: 3 | P34: 4 | Q34: 4 | R34: 3 | S34: 2 | T34: 3 | U34: 4 | V34: 4 | W34: 3 | X34: 3 | Y34: 2 | Z34: 5 | AA34: 3 | AB34: 4 | AC34: 3 | AD34: 2 | AE34: 3 | AF34: 3 | AG34: 3 | AH34: 2 | AI34: 3 | AK34: 2 | AL34: 3 | AM34: 1 | AN34: 3 | AO34: =MAX(E34:K34) -> 2 | AP34: =AVERAGE(N34:R34) -> 3.6 | AQ34: =AVERAGE(S34:V34) -> 3.25 | AR34: =AVERAGE(W34,X34,Z34,AB34) -> 3.75 | AS34: =AVERAGE(AC34:AF34) -> 2.75 | AT34: =AVERAGE(Y34,AA34,AG34:AM34) -> 2.375 | AU34: =(AO34+AP34+AQ34+AR34+AS34+(6-AT34))/6 -> 3.1625 | AV34: Haute | AW34: Moyenne | AX34: non noté
A35: 312 | B35: Univ. Paris 1 Panthéon-Sorbonne (CES) | C35: L'efficacité économique des hôpitaux publics et privés : étude économétrique sur données françaises | D35: Microéconomie Appliquée | E35: 1 | F35: 1 | G35: 1 | H35: 1 | I35: 1 | J35: 1 | K35: 3 | L35: 3 | N35: 4 | O35: 2 | P35: 4 | Q35: 4 | R35: 4 | S35: 2 | T35: 3 | U35: 3 | V35: 3 | W35: 3 | X35: 3 | Y35: 1 | Z35: 4 | AA35: 3 | AB35: 4 | AC35: 3 | AD35: 3 | AE35: 3 | AF35: 4 | AG35: 3 | AH35: 3 | AI35: 3 | AK35: 2 | AL35: 3 | AM35: 1 | AN35: 2 | AO35: =MAX(E35:K35) -> 3 | AP35: =AVERAGE(N35:R35) -> 3.6 | AQ35: =AVERAGE(S35:V35) -> 2.75 | AR35: =AVERAGE(W35,X35,Z35,AB35) -> 3.5 | AS35: =AVERAGE(AC35:AF35) -> 3.25 | AT35: =AVERAGE(Y35,AA35,AG35:AM35) -> 2.375 | AU35: =(AO35+AP35+AQ35+AR35+AS35+(6-AT35))/6 -> 3.2875 | AV35: Haute | AW35: Faible | AX35: non noté
A36: 313 | B36: Inria | C36: Quantifying and Mitigating Cultural Bias in Language Models | D36: NLP | E36: 1 | F36: 1 | G36: 1 | H36: 1 | I36: 1 | J36: 1 | K36: 1 | L36: 3 | N36: 5 | O36: 2 | P36: 3 | Q36: 4 | R36: 4 | S36: 2 | T36: 3 | U36: 5 | V36: 4 | W36: 3 | X36: 5 | Y36: 1 | Z36: 2 | AA36: 3 | AB36: 3 | AC36: 3 | AD36: 4 | AE36: 4 | AF36: 3 | AG36: 3 | AH36: 4 | AI36: 1 | AK36: 3 | AL36: 3 | AM36: 1 | AN36: 3 | AO36: =MAX(E36:K36) -> 1 | AP36: =AVERAGE(N36:R36) -> 3.6 | AQ36: =AVERAGE(S36:V36) -> 3.5 | AR36: =AVERAGE(W36,X36,Z36,AB36) -> 3.25 | AS36: =AVERAGE(AC36:AF36) -> 3.5 | AT36: =AVERAGE(Y36,AA36,AG36:AM36) -> 2.375 | AU36: =(AO36+AP36+AQ36+AR36+AS36+(6-AT36))/6 -> 3.0791667 | AV36: Haute | AW36: Faible | AX36: non noté
A37: 314 | B37: Ekimetrics | C37: Why Is the Model Uncertain? Explaining and Reducing Predictive Uncertainty in Machine Learning | D37: Autre | E37: 1 | F37: 1 | G37: 1 | H37: 2 | I37: 2 | J37: 1 | K37: 1 | L37: 4 | N37: 3 | O37: 3 | P37: 3 | Q37: 4 | R37: 4 | S37: 4 | T37: 3 | U37: 5 | V37: 5 | W37: 3 | X37: 5 | Y37: 1 | Z37: 3 | AA37: 3 | AB37: 3 | AC37: 4 | AD37: 5 | AE37: 5 | AF37: 4 | AG37: 3 | AH37: 3 | AI37: 1 | AK37: 2 | AL37: 2 | AM37: 1 | AN37: 3 | AO37: =MAX(E37:K37) -> 2 | AP37: =AVERAGE(N37:R37) -> 3.4 | AQ37: =AVERAGE(S37:V37) -> 4.25 | AR37: =AVERAGE(W37,X37,Z37,AB37) -> 3.5 | AS37: =AVERAGE(AC37:AF37) -> 4.5 | AT37: =AVERAGE(Y37,AA37,AG37:AM37) -> 2 | AU37: =(AO37+AP37+AQ37+AR37+AS37+(6-AT37))/6 -> 3.6083333 | AV37: Haute | AW37: Faible | AX37: non noté
A38: 315 | B38: Ekimetrics | C38: Efficient Evaluation of LLM-based Agents under a Limited Budget | D38: NLP | E38: 1 | F38: 1 | G38: 1 | H38: 2 | I38: 2 | J38: 1 | K38: 1 | L38: 4 | N38: 3 | O38: 3 | P38: 3 | Q38: 4 | R38: 5 | S38: 4 | T38: 3 | U38: 5 | V38: 5 | W38: 3 | X38: 5 | Y38: 1 | Z38: 3 | AA38: 3 | AB38: 3 | AC38: 4 | AD38: 4 | AE38: 5 | AF38: 5 | AG38: 3 | AH38: 3 | AI38: 2 | AK38: 2 | AL38: 2 | AM38: 1 | AN38: 3 | AO38: =MAX(E38:K38) -> 2 | AP38: =AVERAGE(N38:R38) -> 3.6 | AQ38: =AVERAGE(S38:V38) -> 4.25 | AR38: =AVERAGE(W38,X38,Z38,AB38) -> 3.5 | AS38: =AVERAGE(AC38:AF38) -> 4.5 | AT38: =AVERAGE(Y38,AA38,AG38:AM38) -> 2.125 | AU38: =(AO38+AP38+AQ38+AR38+AS38+(6-AT38))/6 -> 3.6208333 | AV38: Haute | AW38: Faible | AX38: non noté
A39: 316 | B39: Ekimetrics | C39: Joint Uncertainty for Multivariate Electricity-Demand Forecasts | D39: Predictions | E39: 1 | F39: 1 | G39: 1 | H39: 2 | I39: 2 | J39: 1 | K39: 1 | L39: 4 | N39: 3 | O39: 3 | P39: 3 | Q39: 4 | R39: 5 | S39: 4 | T39: 3 | U39: 5 | V39: 5 | W39: 3 | X39: 5 | Y39: 1 | Z39: 3 | AA39: 3 | AB39: 3 | AC39: 5 | AD39: 5 | AE39: 5 | AF39: 5 | AG39: 3 | AH39: 4 | AI39: 2 | AK39: 2 | AL39: 2 | AM39: 1 | AN39: 2 | AO39: =MAX(E39:K39) -> 2 | AP39: =AVERAGE(N39:R39) -> 3.6 | AQ39: =AVERAGE(S39:V39) -> 4.25 | AR39: =AVERAGE(W39,X39,Z39,AB39) -> 3.5 | AS39: =AVERAGE(AC39:AF39) -> 5 | AT39: =AVERAGE(Y39,AA39,AG39:AM39) -> 2.25 | AU39: =(AO39+AP39+AQ39+AR39+AS39+(6-AT39))/6 -> 3.6833333 | AV39: Haute | AW39: Faible | AX39: non noté
A40: 317 | B40: CREST | C40: Cartographier la diversité dans la science, l'innovation et l'entrepreneuriat en France | D40: Microéconomie Appliquée | E40: 1 | F40: 1 | G40: 1 | H40: 1 | I40: 1 | J40: 1 | K40: 2 | L40: 4 | N40: 4 | O40: 3 | P40: 4 | Q40: 4 | R40: 5 | S40: 2 | T40: 3 | U40: 4 | V40: 4 | W40: 3 | X40: 4 | Y40: 3 | Z40: 3 | AA40: 3 | AB40: 4 | AC40: 2 | AD40: 3 | AE40: 5 | AF40: 4 | AG40: 4 | AH40: 3 | AI40: 4 | AK40: 3 | AL40: 2 | AM40: 1 | AN40: 2 | AO40: =MAX(E40:K40) -> 2 | AP40: =AVERAGE(N40:R40) -> 4 | AQ40: =AVERAGE(S40:V40) -> 3.25 | AR40: =AVERAGE(W40,X40,Z40,AB40) -> 3.5 | AS40: =AVERAGE(AC40:AF40) -> 3.5 | AT40: =AVERAGE(Y40,AA40,AG40:AM40) -> 2.875 | AU40: =(AO40+AP40+AQ40+AR40+AS40+(6-AT40))/6 -> 3.2291667 | AV40: Haute | AW40: Moyenne | AX40: non noté
A41: 318 | B41: RITM (Univ. Paris-Saclay) | C41: Exposition au bruit et réussite scolaire | D41: Microéconomie Appliquée | E41: 1 | F41: 1 | G41: 1 | H41: 1 | I41: 1 | J41: 1 | K41: 2 | L41: 3 | N41: 3 | O41: 2 | P41: 4 | Q41: 5 | R41: 4 | S41: 2 | T41: 3 | U41: 2 | V41: 4 | W41: 3 | X41: 3 | Y41: 2 | Z41: 4 | AA41: 3 | AB41: 3 | AC41: 3 | AD41: 3 | AE41: 4 | AF41: 4 | AG41: 3 | AH41: 3 | AI41: 4 | AK41: 2 | AL41: 3 | AM41: 1 | AN41: 2 | AO41: =MAX(E41:K41) -> 2 | AP41: =AVERAGE(N41:R41) -> 3.6 | AQ41: =AVERAGE(S41:V41) -> 2.75 | AR41: =AVERAGE(W41,X41,Z41,AB41) -> 3.25 | AS41: =AVERAGE(AC41:AF41) -> 3.5 | AT41: =AVERAGE(Y41,AA41,AG41:AM41) -> 2.625 | AU41: =(AO41+AP41+AQ41+AR41+AS41+(6-AT41))/6 -> 3.0791667 | AV41: Haute | AW41: Faible | AX41: non noté
A42: 319 | B42: CREST | C42: Cultural Consumption and Intersectionality. Analysis of the Survey of Public Participation in the Arts | D42: Sociologie Quantitative | E42: 1 | F42: 1 | G42: 1 | H42: 1 | I42: 1 | J42: 1 | K42: 1 | L42: 3 | N42: 4 | O42: 3 | P42: 4 | Q42: 3 | R42: 4 | S42: 2 | T42: 3 | U42: 5 | V42: 3 | W42: 3 | X42: 4 | Y42: 1 | Z42: 2 | AA42: 2 | AB42: 4 | AC42: 3 | AD42: 4 | AE42: 3 | AF42: 4 | AG42: 3 | AH42: 3 | AI42: 2 | AK42: 1 | AL42: 3 | AM42: 1 | AN42: 1 | AO42: =MAX(E42:K42) -> 1 | AP42: =AVERAGE(N42:R42) -> 3.6 | AQ42: =AVERAGE(S42:V42) -> 3.25 | AR42: =AVERAGE(W42,X42,Z42,AB42) -> 3.25 | AS42: =AVERAGE(AC42:AF42) -> 3.5 | AT42: =AVERAGE(Y42,AA42,AG42:AM42) -> 2 | AU42: =(AO42+AP42+AQ42+AR42+AS42+(6-AT42))/6 -> 3.1 | AV42: Haute | AW42: Moyenne | AX42: non noté
A43: 320 | B43: CREST | C43: Gender Identity Inequalities in Health. Analysis of the European Social Survey | D43: Sociologie Quantitative | E43: 1 | F43: 1 | G43: 2 | H43: 1 | I43: 1 | J43: 1 | K43: 1 | L43: 3 | N43: 4 | O43: 3 | P43: 4 | Q43: 4 | R43: 4 | S43: 2 | T43: 3 | U43: 5 | V43: 3 | W43: 3 | X43: 4 | Y43: 1 | Z43: 2 | AA43: 2 | AB43: 4 | AC43: 3 | AD43: 3 | AE43: 3 | AF43: 4 | AG43: 3 | AH43: 3 | AI43: 2 | AK43: 1 | AL43: 3 | AM43: 1 | AN43: 1 | AO43: =MAX(E43:K43) -> 2 | AP43: =AVERAGE(N43:R43) -> 3.8 | AQ43: =AVERAGE(S43:V43) -> 3.25 | AR43: =AVERAGE(W43,X43,Z43,AB43) -> 3.25 | AS43: =AVERAGE(AC43:AF43) -> 3.25 | AT43: =AVERAGE(Y43,AA43,AG43:AM43) -> 2 | AU43: =(AO43+AP43+AQ43+AR43+AS43+(6-AT43))/6 -> 3.2583333 | AV43: Haute | AW43: Moyenne | AX43: non noté
A44: 321 | B44: CREST | C44: Conspiracy Theory Beliefs in Europe: Analysis of the European Social Survey | D44: Sociologie Quantitative | E44: 1 | F44: 1 | G44: 1 | H44: 1 | I44: 1 | J44: 1 | K44: 1 | L44: 3 | N44: 4 | O44: 3 | P44: 4 | Q44: 4 | R44: 3 | S44: 2 | T44: 3 | U44: 5 | V44: 3 | W44: 3 | X44: 4 | Y44: 1 | Z44: 2 | AA44: 2 | AB44: 4 | AC44: 3 | AD44: 3 | AE44: 3 | AF44: 4 | AG44: 3 | AH44: 3 | AI44: 2 | AK44: 1 | AL44: 3 | AM44: 1 | AN44: 1 | AO44: =MAX(E44:K44) -> 1 | AP44: =AVERAGE(N44:R44) -> 3.6 | AQ44: =AVERAGE(S44:V44) -> 3.25 | AR44: =AVERAGE(W44,X44,Z44,AB44) -> 3.25 | AS44: =AVERAGE(AC44:AF44) -> 3.25 | AT44: =AVERAGE(Y44,AA44,AG44:AM44) -> 2 | AU44: =(AO44+AP44+AQ44+AR44+AS44+(6-AT44))/6 -> 3.0583333 | AV44: Haute | AW44: Moyenne | AX44: non noté
A45: 322 | B45: CREST | C45: Social status and health. Analysis of longitudinal survey data | D45: Sociologie Quantitative | E45: 1 | F45: 1 | G45: 2 | H45: 1 | I45: 1 | J45: 1 | K45: 1 | L45: 4 | N45: 4 | O45: 3 | P45: 4 | Q45: 4 | R45: 5 | S45: 2 | T45: 3 | U45: 5 | V45: 4 | W45: 3 | X45: 4 | Y45: 2 | Z45: 4 | AA45: 2 | AB45: 4 | AC45: 3 | AD45: 3 | AE45: 4 | AF45: 4 | AG45: 3 | AH45: 3 | AI45: 3 | AK45: 1 | AL45: 3 | AM45: 1 | AN45: 2 | AO45: =MAX(E45:K45) -> 2 | AP45: =AVERAGE(N45:R45) -> 4 | AQ45: =AVERAGE(S45:V45) -> 3.5 | AR45: =AVERAGE(W45,X45,Z45,AB45) -> 3.75 | AS45: =AVERAGE(AC45:AF45) -> 3.5 | AT45: =AVERAGE(Y45,AA45,AG45:AM45) -> 2.25 | AU45: =(AO45+AP45+AQ45+AR45+AS45+(6-AT45))/6 -> 3.4166667 | AV45: Haute | AW45: Moyenne | AX45: non noté
A46: 323 | B46: CREST | C46: How can we measure health and physical dysregulation? A multiverse analysis of The Irish Longitudinal Study o… | D46: Santé | E46: 1 | F46: 1 | G46: 2 | H46: 1 | I46: 1 | J46: 1 | K46: 1 | L46: 4 | N46: 4 | O46: 3 | P46: 4 | Q46: 2 | R46: 5 | S46: 2 | T46: 3 | U46: 5 | V46: 3 | W46: 3 | X46: 4 | Y46: 3 | Z46: 3 | AA46: 3 | AB46: 4 | AC46: 3 | AD46: 4 | AE46: 3 | AF46: 4 | AG46: 3 | AH46: 3 | AI46: 3 | AK46: 2 | AL46: 3 | AM46: 1 | AN46: 1 | AO46: =MAX(E46:K46) -> 2 | AP46: =AVERAGE(N46:R46) -> 3.6 | AQ46: =AVERAGE(S46:V46) -> 3.25 | AR46: =AVERAGE(W46,X46,Z46,AB46) -> 3.5 | AS46: =AVERAGE(AC46:AF46) -> 3.5 | AT46: =AVERAGE(Y46,AA46,AG46:AM46) -> 2.625 | AU46: =(AO46+AP46+AQ46+AR46+AS46+(6-AT46))/6 -> 3.2041667 | AV46: Haute | AW46: Moyenne | AX46: non noté
A47: 324 | B47: Banque de France | C47: Modélisation du risque de crédit en intégrant les engagements hors bilan | D47: Finance | E47: 1 | F47: 1 | G47: 1 | H47: 4 | I47: 3 | J47: 1 | K47: 3 | L47: 3 | N47: 4 | O47: 4 | P47: 3 | Q47: 4 | R47: 4 | S47: 3 | T47: 4 | U47: 3 | V47: 5 | W47: 3 | X47: 5 | Y47: 3 | Z47: 3 | AA47: 3 | AB47: 3 | AC47: 4 | AD47: 3 | AE47: 4 | AF47: 4 | AG47: 4 | AH47: 3 | AI47: 5 | AK47: 3 | AL47: 2 | AM47: 1 | AN47: 3 | AO47: =MAX(E47:K47) -> 4 | AP47: =AVERAGE(N47:R47) -> 3.8 | AQ47: =AVERAGE(S47:V47) -> 3.75 | AR47: =AVERAGE(W47,X47,Z47,AB47) -> 3.5 | AS47: =AVERAGE(AC47:AF47) -> 3.75 | AT47: =AVERAGE(Y47,AA47,AG47:AM47) -> 3 | AU47: =(AO47+AP47+AQ47+AR47+AS47+(6-AT47))/6 -> 3.6333333 | AV47: Haute | AW47: Faible | AX47: 3
A48: 325 | B48: CREST | C48: Has there been a polarization of working hours? Analysis of the European Union Labor Force Survey | D48: Sociologie Quantitative | E48: 1 | F48: 1 | G48: 1 | H48: 1 | I48: 1 | J48: 1 | K48: 2 | L48: 4 | N48: 4 | O48: 3 | P48: 4 | Q48: 4 | R48: 4 | S48: 2 | T48: 3 | U48: 5 | V48: 4 | W48: 3 | X48: 4 | Y48: 3 | Z48: 4 | AA48: 3 | AB48: 4 | AC48: 3 | AD48: 4 | AE48: 3 | AF48: 4 | AG48: 3 | AH48: 3 | AI48: 3 | AK48: 2 | AL48: 3 | AM48: 1 | AN48: 2 | AO48: =MAX(E48:K48) -> 2 | AP48: =AVERAGE(N48:R48) -> 3.8 | AQ48: =AVERAGE(S48:V48) -> 3.5 | AR48: =AVERAGE(W48,X48,Z48,AB48) -> 3.75 | AS48: =AVERAGE(AC48:AF48) -> 3.5 | AT48: =AVERAGE(Y48,AA48,AG48:AM48) -> 2.625 | AU48: =(AO48+AP48+AQ48+AR48+AS48+(6-AT48))/6 -> 3.3208333 | AV48: Haute | AW48: Moyenne | AX48: non noté
A49: 326 | B49: Banque de France | C49: Un modèle de gravité pour expliquer les flux touristiques entrants en France par nationalité | D49: Macroeconomie | E49: 1 | F49: 1 | G49: 1 | H49: 1 | I49: 2 | J49: 1 | K49: 3 | L49: 3 | N49: 4 | O49: 4 | P49: 3 | Q49: 4 | R49: 2 | S49: 3 | T49: 4 | U49: 3 | V49: 3 | W49: 3 | X49: 5 | Y49: 2 | Z49: 5 | AA49: 4 | AB49: 3 | AC49: 2 | AD49: 2 | AE49: 3 | AF49: 3 | AG49: 2 | AH49: 1 | AI49: 2 | AK49: 1 | AL49: 3 | AM49: 2 | AN49: 2 | AO49: =MAX(E49:K49) -> 3 | AP49: =AVERAGE(N49:R49) -> 3.4 | AQ49: =AVERAGE(S49:V49) -> 3.25 | AR49: =AVERAGE(W49,X49,Z49,AB49) -> 4 | AS49: =AVERAGE(AC49:AF49) -> 2.5 | AT49: =AVERAGE(Y49,AA49,AG49:AM49) -> 2.125 | AU49: =(AO49+AP49+AQ49+AR49+AS49+(6-AT49))/6 -> 3.3375 | AV49: Haute | AW49: Faible | AX49: non noté
A50: 327 | B50: CREST | C50: Sharing or Separating? Trends in Income Pooling among Couples, 1988–2022. Analysis of the ISSP Family and Cha… | D50: Sociologie Quantitative | E50: 1 | F50: 1 | G50: 1 | H50: 1 | I50: 1 | J50: 1 | K50: 1 | L50: 3 | N50: 4 | O50: 3 | P50: 4 | Q50: 3 | R50: 4 | S50: 2 | T50: 3 | U50: 5 | V50: 3 | W50: 3 | X50: 4 | Y50: 1 | Z50: 3 | AA50: 3 | AB50: 4 | AC50: 3 | AD50: 3 | AE50: 3 | AF50: 4 | AG50: 3 | AH50: 3 | AI50: 3 | AK50: 1 | AL50: 3 | AM50: 1 | AN50: 1 | AO50: =MAX(E50:K50) -> 1 | AP50: =AVERAGE(N50:R50) -> 3.6 | AQ50: =AVERAGE(S50:V50) -> 3.25 | AR50: =AVERAGE(W50,X50,Z50,AB50) -> 3.5 | AS50: =AVERAGE(AC50:AF50) -> 3.25 | AT50: =AVERAGE(Y50,AA50,AG50:AM50) -> 2.25 | AU50: =(AO50+AP50+AQ50+AR50+AS50+(6-AT50))/6 -> 3.0583333 | AV50: Haute | AW50: Moyenne | AX50: non noté
A51: 328 | B51: CREST | C51: His Job, Her Job? Trends in the Division of Household Labor among Couples, 1988–2022. Analysis of the ISSP Fa… | D51: Sociologie Quantitative | E51: 1 | F51: 1 | G51: 1 | H51: 1 | I51: 1 | J51: 1 | K51: 1 | L51: 3 | N51: 4 | O51: 3 | P51: 4 | Q51: 3 | R51: 4 | S51: 2 | T51: 3 | U51: 5 | V51: 3 | W51: 3 | X51: 4 | Y51: 1 | Z51: 3 | AA51: 3 | AB51: 4 | AC51: 3 | AD51: 3 | AE51: 3 | AF51: 4 | AG51: 3 | AH51: 3 | AI51: 3 | AK51: 1 | AL51: 3 | AM51: 1 | AN51: 1 | AO51: =MAX(E51:K51) -> 1 | AP51: =AVERAGE(N51:R51) -> 3.6 | AQ51: =AVERAGE(S51:V51) -> 3.25 | AR51: =AVERAGE(W51,X51,Z51,AB51) -> 3.5 | AS51: =AVERAGE(AC51:AF51) -> 3.25 | AT51: =AVERAGE(Y51,AA51,AG51:AM51) -> 2.25 | AU51: =(AO51+AP51+AQ51+AR51+AS51+(6-AT51))/6 -> 3.0583333 | AV51: Haute | AW51: Moyenne | AX51: non noté
A52: 329 | B52: CREST | C52: Working Around the Clock? Trends in Evening, Night, and Weekend Work in Europe. Analysis of the European Unio… | D52: Sociologie Quantitative | E52: 1 | F52: 1 | G52: 1 | H52: 1 | I52: 1 | J52: 1 | K52: 2 | L52: 3 | N52: 4 | O52: 3 | P52: 4 | Q52: 3 | R52: 4 | S52: 2 | T52: 3 | U52: 5 | V52: 3 | W52: 3 | X52: 4 | Y52: 3 | Z52: 3 | AA52: 3 | AB52: 4 | AC52: 3 | AD52: 3 | AE52: 3 | AF52: 4 | AG52: 3 | AH52: 3 | AI52: 3 | AK52: 2 | AL52: 3 | AM52: 1 | AN52: 1 | AO52: =MAX(E52:K52) -> 2 | AP52: =AVERAGE(N52:R52) -> 3.6 | AQ52: =AVERAGE(S52:V52) -> 3.25 | AR52: =AVERAGE(W52,X52,Z52,AB52) -> 3.5 | AS52: =AVERAGE(AC52:AF52) -> 3.25 | AT52: =AVERAGE(Y52,AA52,AG52:AM52) -> 2.625 | AU52: =(AO52+AP52+AQ52+AR52+AS52+(6-AT52))/6 -> 3.1625 | AV52: Haute | AW52: Moyenne | AX52: non noté
A53: 330 | B53: CHU de Lille | C53: Mobiliser la datascience pour identifier l'heure d'induction anesthésique à partir de signaux mesurés lors de… | D53: Santé | E53: 1 | F53: 1 | G53: 1 | H53: 1 | I53: 1 | J53: 1 | K53: 1 | L53: 3 | N53: 3 | O53: 1 | P53: 3 | Q53: 2 | R53: 2 | S53: 2 | T53: 2 | U53: 1 | V53: 3 | W53: 3 | X53: 3 | Y53: 5 | Z53: 2 | AA53: 3 | AB53: 3 | AC53: 2 | AD53: 3 | AE53: 1 | AF53: 3 | AG53: 3 | AH53: 3 | AI53: 4 | AK53: 4 | AL53: 3 | AM53: 5 | AN53: 1 | AO53: =MAX(E53:K53) -> 1 | AP53: =AVERAGE(N53:R53) -> 2.2 | AQ53: =AVERAGE(S53:V53) -> 2 | AR53: =AVERAGE(W53,X53,Z53,AB53) -> 2.75 | AS53: =AVERAGE(AC53:AF53) -> 2.25 | AT53: =AVERAGE(Y53,AA53,AG53:AM53) -> 3.75 | AU53: =(AO53+AP53+AQ53+AR53+AS53+(6-AT53))/6 -> 2.075 | AV53: Moyenne | AW53: Faible | AX53: non noté
A54: 331 | B54: CREST | C54: Do Subjective Indicators of Wellbeing Predict an Objective Measure of Health? Are Any Deviations Dependent on… | D54: Santé | E54: 1 | F54: 1 | G54: 2 | H54: 1 | I54: 1 | J54: 1 | K54: 1 | L54: 3 | N54: 4 | O54: 3 | P54: 4 | Q54: 3 | R54: 4 | S54: 2 | T54: 3 | U54: 5 | V54: 3 | W54: 3 | X54: 4 | Y54: 2 | Z54: 4 | AA54: 2 | AB54: 4 | AC54: 2 | AD54: 3 | AE54: 3 | AF54: 4 | AG54: 3 | AH54: 2 | AI54: 3 | AK54: 1 | AL54: 3 | AM54: 1 | AN54: 2 | AO54: =MAX(E54:K54) -> 2 | AP54: =AVERAGE(N54:R54) -> 3.6 | AQ54: =AVERAGE(S54:V54) -> 3.25 | AR54: =AVERAGE(W54,X54,Z54,AB54) -> 3.75 | AS54: =AVERAGE(AC54:AF54) -> 3 | AT54: =AVERAGE(Y54,AA54,AG54:AM54) -> 2.125 | AU54: =(AO54+AP54+AQ54+AR54+AS54+(6-AT54))/6 -> 3.2458333 | AV54: Haute | AW54: Moyenne | AX54: non noté
A55: 332 | B55: Symbiotics Asset Management | C55: Constructing Yield Curves in Illiquid Emerging Market | D55: Finance | E55: 1 | F55: 1 | G55: 1 | H55: 4 | I55: 2 | J55: 1 | K55: 4 | L55: 3 | N55: 2 | O55: 4 | P55: 3 | Q55: 4 | R55: 4 | S55: 3 | T55: 3 | U55: 5 | V55: 4 | W55: 3 | X55: 5 | Y55: 4 | Z55: 3 | AA55: 2 | AB55: 3 | AC55: 3 | AD55: 3 | AE55: 4 | AF55: 4 | AG55: 3 | AH55: 3 | AI55: 4 | AK55: 3 | AL55: 2 | AM55: 1 | AN55: 2 | AO55: =MAX(E55:K55) -> 4 | AP55: =AVERAGE(N55:R55) -> 3.4 | AQ55: =AVERAGE(S55:V55) -> 3.75 | AR55: =AVERAGE(W55,X55,Z55,AB55) -> 3.5 | AS55: =AVERAGE(AC55:AF55) -> 3.5 | AT55: =AVERAGE(Y55,AA55,AG55:AM55) -> 2.75 | AU55: =(AO55+AP55+AQ55+AR55+AS55+(6-AT55))/6 -> 3.5666667 | AV55: Moyenne | AW55: Faible | AX55: 3
A56: 333 | B56: Symbiotics Asset Management | C56: Simplifying Corporate Default Risk Prediction Using Public Financial Data | D56: Finance | E56: 1 | F56: 1 | G56: 1 | H56: 3 | I56: 2 | J56: 1 | K56: 2 | L56: 5 | N56: 2 | O56: 4 | P56: 3 | Q56: 4 | R56: 4 | S56: 3 | T56: 3 | U56: 5 | V56: 5 | W56: 3 | X56: 5 | Y56: 2 | Z56: 4 | AA56: 2 | AB56: 3 | AC56: 3 | AD56: 3 | AE56: 5 | AF56: 3 | AG56: 3 | AH56: 2 | AI56: 4 | AK56: 2 | AL56: 2 | AM56: 1 | AN56: 3 | AO56: =MAX(E56:K56) -> 3 | AP56: =AVERAGE(N56:R56) -> 3.4 | AQ56: =AVERAGE(S56:V56) -> 4 | AR56: =AVERAGE(W56,X56,Z56,AB56) -> 3.75 | AS56: =AVERAGE(AC56:AF56) -> 3.5 | AT56: =AVERAGE(Y56,AA56,AG56:AM56) -> 2.25 | AU56: =(AO56+AP56+AQ56+AR56+AS56+(6-AT56))/6 -> 3.5666667 | AV56: Haute | AW56: Faible | AX56: 3
A57: 334 | B57: Thales | C57: Algorithmes de deep learning pour le débruitage audio | D57: NLP | E57: 1 | F57: 1 | G57: 1 | H57: 1 | I57: 1 | J57: 1 | K57: 1 | L57: 2 | N57: 5 | O57: 1 | P57: 3 | Q57: 4 | R57: 2 | S57: 2 | T57: 2 | U57: 4 | V57: 3 | W57: 1 | X57: 2 | Y57: 1 | Z57: 1 | AA57: 5 | AB57: 3 | AC57: 2 | AD57: 4 | AE57: 4 | AF57: 3 | AG57: 4 | AH57: 4 | AI57: 2 | AK57: 5 | AL57: 3 | AM57: 2 | AN57: 2 | AO57: =MAX(E57:K57) -> 1 | AP57: =AVERAGE(N57:R57) -> 3 | AQ57: =AVERAGE(S57:V57) -> 2.75 | AR57: =AVERAGE(W57,X57,Z57,AB57) -> 1.75 | AS57: =AVERAGE(AC57:AF57) -> 3.25 | AT57: =AVERAGE(Y57,AA57,AG57:AM57) -> 3.25 | AU57: =(AO57+AP57+AQ57+AR57+AS57+(6-AT57))/6 -> 2.4166667 | AV57: Faible | AW57: Faible | AX57: 1 | AY57: D5 4→5
A58: 337 | B58: Sia Partners | C58: Prédiction de la popularité de contenus vidéo marketing pour les marques de luxe par analyse multimodale (com… | D58: Marketing Quantitatif | E58: 1 | F58: 1 | G58: 1 | H58: 1 | I58: 4 | J58: 1 | K58: 1 | L58: 4 | N58: 3 | O58: 4 | P58: 3 | Q58: 3 | R58: 2 | S58: 4 | T58: 3 | U58: 4 | V58: 4 | W58: 2 | X58: 3 | Y58: 5 | Z58: 1 | AA58: 5 | AB58: 3 | AC58: 1 | AD58: 4 | AE58: 4 | AF58: 3 | AG58: 5 | AH58: 5 | AI58: 5 | AK58: 5 | AL58: 2 | AM58: 2 | AN58: 3 | AO58: =MAX(E58:K58) -> 4 | AP58: =AVERAGE(N58:R58) -> 3 | AQ58: =AVERAGE(S58:V58) -> 3.75 | AR58: =AVERAGE(W58,X58,Z58,AB58) -> 2.25 | AS58: =AVERAGE(AC58:AF58) -> 3 | AT58: =AVERAGE(Y58,AA58,AG58:AM58) -> 4.25 | AU58: =(AO58+AP58+AQ58+AR58+AS58+(6-AT58))/6 -> 2.9583333 | AV58: Haute | AW58: Faible | AX58: 2 | AY58: D5 4→5
A59: 338 | B59: Société Générale | C59: Explaining Cheapest-to-Deliver (CTD) Bond Transitions in Government Bond Futures | D59: Finance | E59: 1 | F59: 1 | G59: 1 | H59: 4 | I59: 2 | J59: 1 | K59: 1 | L59: 3 | N59: 5 | O59: 3 | P59: 3 | Q59: 3 | R59: 2 | S59: 3 | T59: 3 | U59: 5 | V59: 3 | W59: 3 | X59: 2 | Y59: 4 | Z59: 3 | AA59: 3 | AB59: 3 | AC59: 3 | AD59: 3 | AE59: 3 | AF59: 4 | AG59: 3 | AH59: 3 | AI59: 3 | AK59: 3 | AL59: 2 | AM59: 3 | AN59: 3 | AO59: =MAX(E59:K59) -> 4 | AP59: =AVERAGE(N59:R59) -> 3.2 | AQ59: =AVERAGE(S59:V59) -> 3.5 | AR59: =AVERAGE(W59,X59,Z59,AB59) -> 2.75 | AS59: =AVERAGE(AC59:AF59) -> 3.25 | AT59: =AVERAGE(Y59,AA59,AG59:AM59) -> 3 | AU59: =(AO59+AP59+AQ59+AR59+AS59+(6-AT59))/6 -> 3.2833333 | AV59: Moyenne | AW59: Faible | AX59: 3
A60: 339 | B60: INRAE | C60: Les arbitrages spatiaux des ménages : coûts du logement, coûts de mobilité et contraintes temporelles | D60: Environnement Energie et Mobilité | E60: 1 | F60: 1 | G60: 1 | H60: 1 | I60: 2 | J60: 1 | K60: 3 | L60: 4 | N60: 4 | O60: 2 | P60: 3 | Q60: 3 | R60: 4 | S60: 2 | T60: 2 | U60: 3 | V60: 4 | W60: 3 | X60: 5 | Y60: 2 | Z60: 3 | AA60: 3 | AB60: 3 | AC60: 3 | AD60: 4 | AE60: 3 | AF60: 4 | AG60: 3 | AH60: 3 | AI60: 4 | AK60: 2 | AL60: 2 | AM60: 1 | AN60: 2 | AO60: =MAX(E60:K60) -> 3 | AP60: =AVERAGE(N60:R60) -> 3.2 | AQ60: =AVERAGE(S60:V60) -> 2.75 | AR60: =AVERAGE(W60,X60,Z60,AB60) -> 3.5 | AS60: =AVERAGE(AC60:AF60) -> 3.5 | AT60: =AVERAGE(Y60,AA60,AG60:AM60) -> 2.5 | AU60: =(AO60+AP60+AQ60+AR60+AS60+(6-AT60))/6 -> 3.2416667 | AV60: Haute | AW60: Faible | AX60: non noté
A61: 340 | B61: Devoteam SAS | C61: Evaluating Multilingual Reasoning in Language Models | D61: NLP | E61: 1 | F61: 1 | G61: 1 | H61: 1 | I61: 1 | J61: 1 | K61: 1 | L61: 3 | N61: 3 | O61: 2 | P61: 3 | Q61: 4 | R61: 4 | S61: 3 | T61: 2 | U61: 4 | V61: 4 | W61: 1 | X61: 4 | Y61: 1 | Z61: 1 | AA61: 3 | AB61: 3 | AC61: 3 | AD61: 3 | AE61: 4 | AF61: 3 | AG61: 3 | AH61: 3 | AI61: 1 | AK61: 3 | AL61: 3 | AM61: 1 | AN61: 3 | AO61: =MAX(E61:K61) -> 1 | AP61: =AVERAGE(N61:R61) -> 3.2 | AQ61: =AVERAGE(S61:V61) -> 3.25 | AR61: =AVERAGE(W61,X61,Z61,AB61) -> 2.25 | AS61: =AVERAGE(AC61:AF61) -> 3.25 | AT61: =AVERAGE(Y61,AA61,AG61:AM61) -> 2.25 | AU61: =(AO61+AP61+AQ61+AR61+AS61+(6-AT61))/6 -> 2.7833333 | AV61: Haute | AW61: Faible | AX61: 1 | AY61: D4 2→1
A62: 341 | B62: Crédit Agricole SA | C62: Traitement de données dans le cadre de modèle de prévisions de taux et d'encours de crédit et dépôts bancaire… | D62: Predictions | E62: 1 | F62: 1 | G62: 2 | H62: 3 | I62: 2 | J62: 1 | K62: 1 | L62: 3 | N62: 5 | O62: 3 | P62: 3 | Q62: 2 | R62: 2 | S62: 3 | T62: 3 | U62: 3 | V62: 4 | W62: 3 | X62: 5 | Y62: 1 | Z62: 4 | AA62: 3 | AB62: 3 | AC62: 3 | AD62: 3 | AE62: 3 | AF62: 3 | AG62: 2 | AH62: 2 | AI62: 3 | AK62: 1 | AL62: 2 | AM62: 2 | AN62: 2 | AO62: =MAX(E62:K62) -> 3 | AP62: =AVERAGE(N62:R62) -> 3 | AQ62: =AVERAGE(S62:V62) -> 3.25 | AR62: =AVERAGE(W62,X62,Z62,AB62) -> 3.75 | AS62: =AVERAGE(AC62:AF62) -> 3 | AT62: =AVERAGE(Y62,AA62,AG62:AM62) -> 2 | AU62: =(AO62+AP62+AQ62+AR62+AS62+(6-AT62))/6 -> 3.3333333 | AV62: Haute | AW62: Faible | AX62: 3
A63: 342 | B63: CREST | C63: Quel prix pour l'eau potable – Demande, hétérogénéité et ciblage des subventions en Inde rurale | D63: Environnement Energie et Mobilité | E63: 1 | F63: 1 | G63: 1 | H63: 2 | I63: 2 | J63: 1 | K63: 4 | L63: 5 | N63: 4 | O63: 3 | P63: 5 | Q63: 4 | R63: 5 | S63: 2 | T63: 3 | U63: 4 | V63: 5 | W63: 3 | X63: 5 | Y63: 3 | Z63: 3 | AA63: 3 | AB63: 4 | AC63: 4 | AD63: 5 | AE63: 4 | AF63: 4 | AG63: 4 | AH63: 4 | AI63: 3 | AK63: 3 | AL63: 2 | AM63: 3 | AN63: 4 | AO63: =MAX(E63:K63) -> 4 | AP63: =AVERAGE(N63:R63) -> 4.2 | AQ63: =AVERAGE(S63:V63) -> 3.5 | AR63: =AVERAGE(W63,X63,Z63,AB63) -> 3.75 | AS63: =AVERAGE(AC63:AF63) -> 4.25 | AT63: =AVERAGE(Y63,AA63,AG63:AM63) -> 3.125 | AU63: =(AO63+AP63+AQ63+AR63+AS63+(6-AT63))/6 -> 3.7625 | AV63: Haute | AW63: Moyenne | AX63: non noté
A64: 343 | B64: Devoteam SAS | C64: Une hallucination a-t-elle une forme – Géométrie interne des représentations et détection des erreurs des mod… | D64: NLP | E64: 1 | F64: 1 | G64: 1 | H64: 2 | I64: 1 | J64: 1 | K64: 1 | L64: 4 | N64: 3 | O64: 2 | P64: 3 | Q64: 3 | R64: 5 | S64: 3 | T64: 2 | U64: 3 | V64: 4 | W64: 2 | X64: 5 | Y64: 1 | Z64: 1 | AA64: 5 | AB64: 3 | AC64: 5 | AD64: 5 | AE64: 4 | AF64: 5 | AG64: 4 | AH64: 5 | AI64: 2 | AK64: 2 | AL64: 2 | AM64: 1 | AN64: 2 | AO64: =MAX(E64:K64) -> 2 | AP64: =AVERAGE(N64:R64) -> 3.2 | AQ64: =AVERAGE(S64:V64) -> 3 | AR64: =AVERAGE(W64,X64,Z64,AB64) -> 2.75 | AS64: =AVERAGE(AC64:AF64) -> 4.75 | AT64: =AVERAGE(Y64,AA64,AG64:AM64) -> 2.75 | AU64: =(AO64+AP64+AQ64+AR64+AS64+(6-AT64))/6 -> 3.1583333 | AV64: Haute | AW64: Faible | AX64: 2 | AY64: D4 2→1, D5 4→5
A65: 344 | B65: INRAE | C65: Homo economicus prend-il le volant – Rationalité limitée et coûts de mobilité | D65: Environnement Energie et Mobilité | E65: 1 | F65: 1 | G65: 1 | H65: 1 | I65: 2 | J65: 1 | K65: 2 | L65: 3 | N65: 4 | O65: 2 | P65: 3 | Q65: 3 | R65: 3 | S65: 2 | T65: 2 | U65: 3 | V65: 4 | W65: 3 | X65: 5 | Y65: 2 | Z65: 5 | AA65: 2 | AB65: 3 | AC65: 2 | AD65: 3 | AE65: 3 | AF65: 3 | AG65: 2 | AH65: 2 | AI65: 2 | AK65: 1 | AL65: 3 | AM65: 2 | AN65: 2 | AO65: =MAX(E65:K65) -> 2 | AP65: =AVERAGE(N65:R65) -> 3 | AQ65: =AVERAGE(S65:V65) -> 2.75 | AR65: =AVERAGE(W65,X65,Z65,AB65) -> 4 | AS65: =AVERAGE(AC65:AF65) -> 2.75 | AT65: =AVERAGE(Y65,AA65,AG65:AM65) -> 2 | AU65: =(AO65+AP65+AQ65+AR65+AS65+(6-AT65))/6 -> 3.0833333 | AV65: Haute | AW65: Faible | AX65: non noté
A66: 345 | B66: Sans entreprise (application) | C66: Rapprochement automatique d'adresses d'entreprises avec la Base Adresse Nationale | D66: NLP | E66: 1 | F66: 1 | G66: 1 | H66: 1 | I66: 1 | J66: 1 | K66: 2 | L66: 3 | N66: 1 | O66: 1 | P66: 3 | Q66: 3 | R66: 2 | S66: 1 | T66: 1 | U66: 1 | V66: 3 | W66: 2 | X66: 4 | Y66: 1 | Z66: 2 | AA66: 4 | AB66: 3 | AC66: 2 | AD66: 3 | AE66: 4 | AF66: 3 | AG66: 2 | AH66: 2 | AI66: 2 | AK66: 1 | AL66: 3 | AM66: 1 | AN66: 2 | AO66: =MAX(E66:K66) -> 2 | AP66: =AVERAGE(N66:R66) -> 2 | AQ66: =AVERAGE(S66:V66) -> 1.5 | AR66: =AVERAGE(W66,X66,Z66,AB66) -> 2.75 | AS66: =AVERAGE(AC66:AF66) -> 3 | AT66: =AVERAGE(Y66,AA66,AG66:AM66) -> 2 | AU66: =(AO66+AP66+AQ66+AR66+AS66+(6-AT66))/6 -> 2.5416667 | AV66: Haute | AW66: Faible | AX66: 2 | AY66: D4 3→2
A67: 346 | B67: Insee | C67: Les enfants assistés de la Nièvre pendant la guerre 1914 1918 | D67: Sociologie Quantitative | E67: 1 | F67: 1 | G67: 3 | H67: 1 | I67: 1 | J67: 1 | K67: 2 | L67: 3 | N67: 4 | O67: 2 | P67: 3 | Q67: 3 | R67: 3 | S67: 3 | T67: 3 | U67: 2 | V67: 4 | W67: 3 | X67: 4 | Y67: 2 | Z67: 3 | AA67: 2 | AB67: 3 | AC67: 3 | AD67: 3 | AE67: 3 | AF67: 5 | AG67: 3 | AH67: 2 | AI67: 3 | AK67: 2 | AL67: 3 | AM67: 1 | AN67: 1 | AO67: =MAX(E67:K67) -> 3 | AP67: =AVERAGE(N67:R67) -> 3 | AQ67: =AVERAGE(S67:V67) -> 3 | AR67: =AVERAGE(W67,X67,Z67,AB67) -> 3.25 | AS67: =AVERAGE(AC67:AF67) -> 3.5 | AT67: =AVERAGE(Y67,AA67,AG67:AM67) -> 2.25 | AU67: =(AO67+AP67+AQ67+AR67+AS67+(6-AT67))/6 -> 3.25 | AV67: Haute | AW67: Faible | AX67: non noté
A68: 347 | B68: BNP Paribas Cardif | C68: Implémentation d'un outil de veille réglementaire assisté par l'intelligence artificielle en assurance | D68: Actuariat | E68: 1 | F68: 1 | G68: 2 | H68: 1 | I68: 2 | J68: 3 | K68: 1 | L68: 3 | N68: 4 | O68: 4 | P68: 3 | Q68: 4 | R68: 2 | S68: 4 | T68: 3 | U68: 3 | V68: 3 | W68: 2 | X68: 4 | Y68: 1 | Z68: 1 | AA68: 5 | AB68: 3 | AC68: 1 | AD68: 3 | AE68: 4 | AF68: 3 | AG68: 3 | AH68: 3 | AI68: 3 | AK68: 3 | AL68: 2 | AM68: 1 | AN68: 3 | AO68: =MAX(E68:K68) -> 3 | AP68: =AVERAGE(N68:R68) -> 3.4 | AQ68: =AVERAGE(S68:V68) -> 3.25 | AR68: =AVERAGE(W68,X68,Z68,AB68) -> 2.5 | AS68: =AVERAGE(AC68:AF68) -> 2.75 | AT68: =AVERAGE(Y68,AA68,AG68:AM68) -> 2.625 | AU68: =(AO68+AP68+AQ68+AR68+AS68+(6-AT68))/6 -> 3.0458333 | AV68: Haute | AW68: Faible | AX68: 2 | AY68: D5 4→5
A69: 348 | B69: KORFED SAS | C69: Modélisation et prédiction du risque auto : comparaison des méthodes actuarielles, du Machine Learning et de… | D69: Actuariat | E69: 5 | F69: 1 | G69: 1 | H69: 1 | I69: 2 | J69: 3 | K69: 1 | L69: 4 | N69: 1 | O69: 2 | P69: 3 | Q69: 3 | R69: 3 | S69: 1 | T69: 1 | U69: 1 | V69: 4 | W69: 3 | X69: 4 | Y69: 5 | Z69: 5 | AA69: 2 | AB69: 2 | AC69: 3 | AD69: 3 | AE69: 3 | AF69: 3 | AG69: 4 | AH69: 3 | AI69: 3 | AK69: 4 | AL69: 1 | AM69: 3 | AN69: 3 | AO69: =MAX(E69:K69) -> 5 | AP69: =AVERAGE(N69:R69) -> 2.4 | AQ69: =AVERAGE(S69:V69) -> 1.75 | AR69: =AVERAGE(W69,X69,Z69,AB69) -> 3.5 | AS69: =AVERAGE(AC69:AF69) -> 3 | AT69: =AVERAGE(Y69,AA69,AG69:AM69) -> 3.125 | AU69: =(AO69+AP69+AQ69+AR69+AS69+(6-AT69))/6 -> 3.0875 | AV69: Moyenne | AW69: Faible | AX69: 3 | AY69: D3 4→5
A70: 349 | B70: Inria | C70: Modélisation prédictive d'évènement cardiovasculaire ou de trajectoire | D70: Santé | E70: 1 | F70: 1 | G70: 2 | H70: 1 | I70: 1 | J70: 1 | K70: 1 | L70: 4 | N70: 5 | O70: 2 | P70: 4 | Q70: 4 | R70: 4 | S70: 2 | T70: 3 | U70: 4 | V70: 4 | W70: 3 | X70: 2 | Y70: 3 | Z70: 3 | AA70: 4 | AB70: 3 | AC70: 4 | AD70: 5 | AE70: 3 | AF70: 4 | AG70: 4 | AH70: 5 | AI70: 3 | AK70: 3 | AL70: 3 | AM70: 3 | AN70: 2 | AO70: =MAX(E70:K70) -> 2 | AP70: =AVERAGE(N70:R70) -> 3.8 | AQ70: =AVERAGE(S70:V70) -> 3.25 | AR70: =AVERAGE(W70,X70,Z70,AB70) -> 2.75 | AS70: =AVERAGE(AC70:AF70) -> 4 | AT70: =AVERAGE(Y70,AA70,AG70:AM70) -> 3.5 | AU70: =(AO70+AP70+AQ70+AR70+AS70+(6-AT70))/6 -> 3.05 | AV70: Moyenne | AW70: Faible | AX70: non noté
A71: 350 | B71: Inria | C71: Clustering de trajectoires de patients atteints d'asthme sévère | D71: Santé | E71: 1 | F71: 1 | G71: 2 | H71: 1 | I71: 1 | J71: 1 | K71: 2 | L71: 4 | N71: 5 | O71: 2 | P71: 4 | Q71: 4 | R71: 4 | S71: 2 | T71: 3 | U71: 4 | V71: 3 | W71: 3 | X71: 2 | Y71: 5 | Z71: 2 | AA71: 4 | AB71: 3 | AC71: 4 | AD71: 5 | AE71: 2 | AF71: 4 | AG71: 5 | AH71: 4 | AI71: 5 | AK71: 5 | AL71: 3 | AM71: 4 | AN71: 1 | AO71: =MAX(E71:K71) -> 2 | AP71: =AVERAGE(N71:R71) -> 3.8 | AQ71: =AVERAGE(S71:V71) -> 3 | AR71: =AVERAGE(W71,X71,Z71,AB71) -> 2.5 | AS71: =AVERAGE(AC71:AF71) -> 3.75 | AT71: =AVERAGE(Y71,AA71,AG71:AM71) -> 4.375 | AU71: =(AO71+AP71+AQ71+AR71+AS71+(6-AT71))/6 -> 2.7791667 | AV71: Moyenne | AW71: Faible | AX71: non noté
A72: 351 | B72: ENPC | C72: Mesurer l'économie productive dans les quartiers de gare du Grand Paris Express | D72: Environnement Energie et Mobilité | E72: 1 | F72: 1 | G72: 1 | H72: 1 | I72: 2 | J72: 1 | K72: 3 | L72: 4 | N72: 4 | O72: 2 | P72: 3 | Q72: 4 | R72: 4 | S72: 2 | T72: 3 | U72: 3 | V72: 4 | W72: 3 | X72: 5 | Y72: 1 | Z72: 3 | AA72: 3 | AB72: 3 | AC72: 3 | AD72: 4 | AE72: 5 | AF72: 4 | AG72: 4 | AH72: 3 | AI72: 5 | AK72: 2 | AL72: 2 | AM72: 1 | AN72: 2 | AO72: =MAX(E72:K72) -> 3 | AP72: =AVERAGE(N72:R72) -> 3.4 | AQ72: =AVERAGE(S72:V72) -> 3 | AR72: =AVERAGE(W72,X72,Z72,AB72) -> 3.5 | AS72: =AVERAGE(AC72:AF72) -> 4 | AT72: =AVERAGE(Y72,AA72,AG72:AM72) -> 2.625 | AU72: =(AO72+AP72+AQ72+AR72+AS72+(6-AT72))/6 -> 3.3791667 | AV72: Haute | AW72: Faible | AX72: non noté
A73: 352 | B73: Euro-Information Développements | C73: Dictée Vocale de code LaTex | D73: NLP | E73: 1 | F73: 1 | G73: 1 | H73: 1 | I73: 1 | J73: 1 | K73: 1 | L73: 2 | N73: 2 | O73: 2 | P73: 3 | Q73: 3 | R73: 1 | S73: 2 | T73: 2 | U73: 1 | V73: 3 | W73: 3 | X73: 3 | Y73: 3 | Z73: 1 | AA73: 4 | AB73: 3 | AC73: 1 | AD73: 3 | AE73: 4 | AF73: 3 | AG73: 4 | AH73: 4 | AI73: 4 | AK73: 4 | AL73: 3 | AM73: 2 | AN73: 2 | AO73: =MAX(E73:K73) -> 1 | AP73: =AVERAGE(N73:R73) -> 2.2 | AQ73: =AVERAGE(S73:V73) -> 2 | AR73: =AVERAGE(W73,X73,Z73,AB73) -> 2.5 | AS73: =AVERAGE(AC73:AF73) -> 2.75 | AT73: =AVERAGE(Y73,AA73,AG73:AM73) -> 3.5 | AU73: =(AO73+AP73+AQ73+AR73+AS73+(6-AT73))/6 -> 2.1583333 | AV73: Moyenne | AW73: Faible | AX73: non noté
A74: 353 | B74: CREST | C74: When a critical material becomes scarce, do firms dig in and innovate around it, or pivot into new activities… | D74: Environnement Energie et Mobilité | E74: 1 | F74: 2 | G74: 1 | H74: 2 | I74: 2 | J74: 1 | K74: 3 | L74: 5 | N74: 4 | O74: 3 | P74: 5 | Q74: 2 | R74: 5 | S74: 2 | T74: 3 | U74: 5 | V74: 4 | W74: 3 | X74: 4 | Y74: 3 | Z74: 3 | AA74: 4 | AB74: 4 | AC74: 4 | AD74: 5 | AE74: 4 | AF74: 5 | AG74: 5 | AH74: 4 | AI74: 5 | AK74: 4 | AL74: 2 | AM74: 2 | AN74: 3 | AO74: =MAX(E74:K74) -> 3 | AP74: =AVERAGE(N74:R74) -> 3.8 | AQ74: =AVERAGE(S74:V74) -> 3.5 | AR74: =AVERAGE(W74,X74,Z74,AB74) -> 3.5 | AS74: =AVERAGE(AC74:AF74) -> 4.5 | AT74: =AVERAGE(Y74,AA74,AG74:AM74) -> 3.625 | AU74: =(AO74+AP74+AQ74+AR74+AS74+(6-AT74))/6 -> 3.4458333 | AV74: Moyenne | AW74: Moyenne | AX74: non noté
A75: 354 | B75: Lazard Frères | C75: Dynamique de la dette française | D75: Macroeconomie | E75: 1 | F75: 1 | G75: 1 | H75: 4 | I75: 3 | J75: 1 | K75: 4 | L75: 3 | N75: 4 | O75: 3 | P75: 3 | Q75: 5 | R75: 3 | S75: 3 | T75: 3 | U75: 3 | V75: 5 | W75: 3 | X75: 3 | Y75: 2 | Z75: 3 | AA75: 4 | AB75: 3 | AC75: 3 | AD75: 3 | AE75: 3 | AF75: 3 | AG75: 4 | AH75: 3 | AI75: 3 | AK75: 2 | AL75: 2 | AM75: 1 | AN75: 4 | AO75: =MAX(E75:K75) -> 4 | AP75: =AVERAGE(N75:R75) -> 3.6 | AQ75: =AVERAGE(S75:V75) -> 3.5 | AR75: =AVERAGE(W75,X75,Z75,AB75) -> 3 | AS75: =AVERAGE(AC75:AF75) -> 3 | AT75: =AVERAGE(Y75,AA75,AG75:AM75) -> 2.625 | AU75: =(AO75+AP75+AQ75+AR75+AS75+(6-AT75))/6 -> 3.4125 | AV75: Moyenne | AW75: Faible | AX75: non noté
A76: 355 | B76: Ornikar Assurance | C76: Mesure de l'assurabilité en assurance Auto | D76: Finance | E76: 4 | F76: 3 | G76: 1 | H76: 1 | I76: 3 | J76: 3 | K76: 2 | L76: 3 | N76: 3 | O76: 2 | P76: 3 | Q76: 4 | R76: 3 | S76: 3 | T76: 2 | U76: 1 | V76: 3 | W76: 3 | X76: 2 | Y76: 4 | Z76: 3 | AA76: 4 | AB76: 3 | AC76: 2 | AD76: 3 | AE76: 2 | AF76: 4 | AG76: 3 | AH76: 3 | AI76: 3 | AK76: 4 | AL76: 3 | AM76: 4 | AN76: 3 | AO76: =MAX(E76:K76) -> 4 | AP76: =AVERAGE(N76:R76) -> 3 | AQ76: =AVERAGE(S76:V76) -> 2.25 | AR76: =AVERAGE(W76,X76,Z76,AB76) -> 2.75 | AS76: =AVERAGE(AC76:AF76) -> 2.75 | AT76: =AVERAGE(Y76,AA76,AG76:AM76) -> 3.5 | AU76: =(AO76+AP76+AQ76+AR76+AS76+(6-AT76))/6 -> 2.875 | AV76: Moyenne | AW76: Faible | AX76: non noté
A77: 356 | B77: VIA AM | C77: Finding Factors Using NLP/LLMs on 10-K/10-Q/8-K Filings | D77: Finance | E77: 1 | F77: 1 | G77: 1 | H77: 5 | I77: 1 | J77: 1 | K77: 1 | L77: 5 | N77: 2 | O77: 3 | P77: 3 | Q77: 4 | R77: 4 | S77: 3 | T77: 3 | U77: 4 | V77: 5 | W77: 3 | X77: 5 | Y77: 3 | Z77: 3 | AA77: 4 | AB77: 3 | AC77: 4 | AD77: 5 | AE77: 5 | AF77: 3 | AG77: 5 | AH77: 4 | AI77: 5 | AK77: 4 | AL77: 2 | AM77: 1 | AN77: 4 | AO77: =MAX(E77:K77) -> 5 | AP77: =AVERAGE(N77:R77) -> 3.2 | AQ77: =AVERAGE(S77:V77) -> 3.75 | AR77: =AVERAGE(W77,X77,Z77,AB77) -> 3.5 | AS77: =AVERAGE(AC77:AF77) -> 4.25 | AT77: =AVERAGE(Y77,AA77,AG77:AM77) -> 3.5 | AU77: =(AO77+AP77+AQ77+AR77+AS77+(6-AT77))/6 -> 3.7 | AV77: Haute | AW77: Faible | AX77: non noté
A78: 357 | B78: Dstudio | C78: Multimodal Buying Intent Prediction with Survival Analysis, Graph Learning & Learning-to-Rank | D78: Predictions | E78: 1 | F78: 1 | G78: 1 | H78: 1 | I78: 2 | J78: 1 | K78: 1 | L78: 5 | N78: 1 | O78: 2 | P78: 3 | Q78: 2 | R78: 3 | S78: 2 | T78: 2 | U78: 1 | V78: 4 | W78: 3 | X78: 4 | Y78: 5 | Z78: 2 | AA78: 5 | AB78: 3 | AC78: 3 | AD78: 5 | AE78: 3 | AF78: 3 | AG78: 5 | AH78: 5 | AI78: 5 | AK78: 5 | AL78: 2 | AM78: 4 | AN78: 2 | AO78: =MAX(E78:K78) -> 2 | AP78: =AVERAGE(N78:R78) -> 2.2 | AQ78: =AVERAGE(S78:V78) -> 2.25 | AR78: =AVERAGE(W78,X78,Z78,AB78) -> 3 | AS78: =AVERAGE(AC78:AF78) -> 3.5 | AT78: =AVERAGE(Y78,AA78,AG78:AM78) -> 4.5 | AU78: =(AO78+AP78+AQ78+AR78+AS78+(6-AT78))/6 -> 2.4083333 | AV78: Moyenne | AW78: Faible | AX78: non noté
A79: 358 | B79: Drees | C79: Coefficients géographiques frontaliers | D79: Microéconomie Appliquée | E79: 1 | F79: 1 | G79: 1 | H79: 1 | I79: 1 | J79: 1 | K79: 3 | L79: 3 | N79: 3 | O79: 2 | P79: 3 | Q79: 2 | R79: 2 | S79: 2 | T79: 3 | U79: 1 | V79: 3 | W79: 3 | X79: 3 | Y79: 3 | Z79: 4 | AA79: 3 | AB79: 3 | AC79: 3 | AD79: 3 | AE79: 3 | AF79: 4 | AG79: 3 | AH79: 2 | AI79: 3 | AK79: 3 | AL79: 3 | AM79: 2 | AN79: 1 | AO79: =MAX(E79:K79) -> 3 | AP79: =AVERAGE(N79:R79) -> 2.4 | AQ79: =AVERAGE(S79:V79) -> 2.25 | AR79: =AVERAGE(W79,X79,Z79,AB79) -> 3.25 | AS79: =AVERAGE(AC79:AF79) -> 3.25 | AT79: =AVERAGE(Y79,AA79,AG79:AM79) -> 2.75 | AU79: =(AO79+AP79+AQ79+AR79+AS79+(6-AT79))/6 -> 2.9 | AV79: Moyenne | AW79: Faible | AX79: non noté
A80: 359 | B80: CREST | C80: Unpacking the drivers of turnover in industrial firms | D80: Microéconomie Appliquée | E80: 1 | F80: 1 | G80: 1 | H80: 1 | I80: 1 | J80: 1 | K80: 3 | L80: 4 | N80: 4 | O80: 3 | P80: 3 | Q80: 4 | R80: 4 | S80: 2 | T80: 3 | U80: 5 | V80: 3 | W80: 3 | X80: 2 | Y80: 4 | Z80: 3 | AA80: 3 | AB80: 3 | AC80: 4 | AD80: 4 | AE80: 2 | AF80: 4 | AG80: 4 | AH80: 4 | AI80: 4 | AK80: 4 | AL80: 3 | AM80: 5 | AN80: 2 | AO80: =MAX(E80:K80) -> 3 | AP80: =AVERAGE(N80:R80) -> 3.6 | AQ80: =AVERAGE(S80:V80) -> 3.25 | AR80: =AVERAGE(W80,X80,Z80,AB80) -> 2.75 | AS80: =AVERAGE(AC80:AF80) -> 3.5 | AT80: =AVERAGE(Y80,AA80,AG80:AM80) -> 3.875 | AU80: =(AO80+AP80+AQ80+AR80+AS80+(6-AT80))/6 -> 3.0375 | AV80: Moyenne | AW80: Faible | AX80: non noté
A81: 360 | B81: EDF R&D | C81: Méthodes statistiques pour la prévision de production renouvelable | D81: Environnement Energie et Mobilité | E81: 1 | F81: 1 | G81: 1 | H81: 2 | I81: 1 | J81: 1 | K81: 1 | L81: 4 | N81: 5 | O81: 2 | P81: 3 | Q81: 4 | R81: 3 | S81: 3 | T81: 3 | U81: 3 | V81: 4 | W81: 3 | X81: 1 | Y81: 3 | Z81: 3 | AA81: 4 | AB81: 3 | AC81: 2 | AD81: 4 | AE81: 3 | AF81: 3 | AG81: 3 | AH81: 4 | AI81: 2 | AK81: 4 | AL81: 3 | AM81: 3 | AN81: 3 | AO81: =MAX(E81:K81) -> 2 | AP81: =AVERAGE(N81:R81) -> 3.4 | AQ81: =AVERAGE(S81:V81) -> 3.25 | AR81: =AVERAGE(W81,X81,Z81,AB81) -> 2.5 | AS81: =AVERAGE(AC81:AF81) -> 3 | AT81: =AVERAGE(Y81,AA81,AG81:AM81) -> 3.25 | AU81: =(AO81+AP81+AQ81+AR81+AS81+(6-AT81))/6 -> 2.8166667 | AV81: Faible | AW81: Faible | AX81: non noté
... A87: 366 | B87: BPCE SA | C87: Estimation des pertes extrêmes en risque de crédit | D87: Finance | E87: 1 | F87: 5 | G87: 1 | H87: 4 | I87: 2 | J87: 2 | K87: 1 | L87: 4 | N87: 4 | O87: 3 | P87: 3 | Q87: 5 | R87: 3 | S87: 3 | T87: 3 | U87: 2 | V87: 5 | W87: 3 | X87: 4 | Y87: 4 | Z87: 3 | AA87: 2 | AB87: 3 | AC87: 5 | AD87: 4 | AE87: 3 | AF87: 4 | AG87: 3 | AH87: 3 | AI87: 3 | AK87: 3 | AL87: 2 | AM87: 3 | AN87: 4 | AO87: =MAX(E87:K87) -> 5 | AP87: =AVERAGE(N87:R87) -> 3.6 | AQ87: =AVERAGE(S87:V87) -> 3.25 | AR87: =AVERAGE(W87,X87,Z87,AB87) -> 3.25 | AS87: =AVERAGE(AC87:AF87) -> 4 | AT87: =AVERAGE(Y87,AA87,AG87:AM87) -> 2.875 | AU87: =(AO87+AP87+AQ87+AR87+AS87+(6-AT87))/6 -> 3.7041667 | AV87: Moyenne | AW87: Faible | AX87: non noté

Sheet Classement
A1: Classement provisoire des sujets : High priority, Mid priority, Ne pas toucher
A2: Classes et rangs fixés par les règles de la feuille « Règles de classement » ; le rang suit l'indice (moyenne simple des six familles, sans pondération), départagé par le fit puis le signal. Les familles et l'indice se recalculent si vous modifiez un score dans « Scoring » ; la classe et le rang, eux, restent figés. Avis et conseil rédigés à la lecture de la fiche et de la recherche web.
A4: Classe | B4: Code | C4: Sous-catégorie | D4: Rang | E4: N° | F4: Organisme | G4: Titre (fiche) | H4: Fit | I4: Signal | J4: Exit | K4: Note | L4: Apprentissage | M4: Risque | N4: Indice | O4: Demande (F8) | P4: Avis | Q4: Conseil | R4: Confiance | S4: Fiche PDF
A5: High | B5: H1 | C5: Cœur de cible | D5: 1 | E5: 285 | F5: SCOR | G5: Life and health insurance pricing with geographical data | H5: =INDEX(Scoring!$AO$5:$AO$87,MATCH($E5,Scoring!$A$5:$A$87,0)) -> 5 | I5: =INDEX(Scoring!$AP$5:$AP$87,MATCH($E5,Scoring!$A$5:$A$87,0)) -> 4 | J5: =INDEX(Scoring!$AQ$5:$AQ$87,MATCH($E5,Scoring!$A$5:$A$87,0)) -> 4.5 | K5: =INDEX(Scoring!$AR$5:$AR$87,MATCH($E5,Scoring!$A$5:$A$87,0)) -> 3.75 | L5: =INDEX(Scoring!$AS$5:$AS$87,MATCH($E5,Scoring!$A$5:$A$87,0)) -> 3 | M5: =INDEX(Scoring!$AT$5:$AT$87,MATCH($E5,Scoring!$A$5:$A$87,0)) -> 3.125 | N5: =INDEX(Scoring!$AU$5:$AU$87,MATCH($E5,Scoring!$A$5:$A$87,0)) -> 3.8541667 | O5: =INDEX(Scoring!$AN$5:$AN$87,MATCH($E5,Scoring!$A$5:$A$87,0)) -> 5 | P5: Tarification vie et prévoyance avec données géographiques chez SCOR : GLM, fréquence-sévérité, modèles de durée, ML. Excellente adéquation au 2A, signal réassureur direct, mais données internes donc confidentialité probable. | Q5: Candidat de premier rang pour votre profil réassurance et prévoyance. À mettre très haut dans les vœux, en sachant que la demande sera forte. Clarifier dès le départ ce qui sera citable. | R5: Fiche : Haute Web : Faible | S5: Ouvrir le PDF
A6: High | B6: H1 | C6: Cœur de cible | D6: 2 | E6: 282 | F6: HSBC Global Asset Management | G6: Stratégies optionnelles de protection pour investisseurs de long terme | H6: =INDEX(Scoring!$AO$5:$AO$87,MATCH($E6,Scoring!$A$5:$A$87,0)) -> 5 | I6: =INDEX(Scoring!$AP$5:$AP$87,MATCH($E6,Scoring!$A$5:$A$87,0)) -> 3.6 | J6: =INDEX(Scoring!$AQ$5:$AQ$87,MATCH($E6,Scoring!$A$5:$A$87,0)) -> 3.5 | K6: =INDEX(Scoring!$AR$5:$AR$87,MATCH($E6,Scoring!$A$5:$A$87,0)) -> 3.75 | L6: =INDEX(Scoring!$AS$5:$AS$87,MATCH($E6,Scoring!$A$5:$A$87,0)) -> 3.5 | M6: =INDEX(Scoring!$AT$5:$AT$87,MATCH($E6,Scoring!$A$5:$A$87,0)) -> 2.25 | N6: =INDEX(Scoring!$AU$5:$AU$87,MATCH($E6,Scoring!$A$5:$A$87,0)) -> 3.85 | O6: =INDEX(Scoring!$AN$5:$AN$87,MATCH($E6,Scoring!$A$5:$A$87,0)) -> 3 | P6: Comparaison de stratégies de protection optionnelle (puts, collars, CPPI/OBPI) sur horizon long par simulation stochastique et backtest. Bon contenu de finance quantitative, avec un lien assurance vie et retraite. La fiche ne détaille qu'une partie des données. | Q6: Bon candidat quant, proche du sujet 361 du même encadrant : n'en retenir qu'un seul sur les deux. Confirmer que les séries de volatilité implicite sont bien fournies. | R6: Fiche : Moyenne Web : Faible | S6: Ouvrir le PDF
A7: High | B7: H1 | C7: Cœur de cible | D7: 3 | E7: 342 | F7: CREST | G7: Quel prix pour l'eau potable – Demande, hétérogénéité et ciblage des subventions en Inde rurale | H7: =INDEX(Scoring!$AO$5:$AO$87,MATCH($E7,Scoring!$A$5:$A$87,0)) -> 4 | I7: =INDEX(Scoring!$AP$5:$AP$87,MATCH($E7,Scoring!$A$5:$A$87,0)) -> 4.2 | J7: =INDEX(Scoring!$AQ$5:$AQ$87,MATCH($E7,Scoring!$A$5:$A$87,0)) -> 3.5 | K7: =INDEX(Scoring!$AR$5:$AR$87,MATCH($E7,Scoring!$A$5:$A$87,0)) -> 3.75 | L7: =INDEX(Scoring!$AS$5:$AS$87,MATCH($E7,Scoring!$A$5:$A$87,0)) -> 4.25 | M7: =INDEX(Scoring!$AT$5:$AT$87,MATCH($E7,Scoring!$A$5:$A$87,0)) -> 3.125 | N7: =INDEX(Scoring!$AU$5:$AU$87,MATCH($E7,Scoring!$A$5:$A$87,0)) -> 3.7625 | O7: =INDEX(Scoring!$AN$5:$AN$87,MATCH($E7,Scoring!$A$5:$A$87,0)) -> 4 | P7: Demande d'eau potable en Inde rurale à partir d'un essai randomisé de 60 000 ménages (données du papier AER 2026) : élasticités, hétérogénéité des effets (causal forests) et règles de ciblage des subventions (Empirical Welfare Maximization). Encadrant de premier plan, très forte profondeur, très bon signal académique et développement. | Q7: L'un des meilleurs candidats pour le profil institutions et développement, et excellent pour la poursuite en recherche. Demande probablement forte ; confirmer l'accès aux données auprès de l'encadrant. | R7: Fiche : Haute Web : Moyenne | S7: Ouvrir le PDF
A8: High | B8: H1 | C8: Cœur de cible | D8: 4 | E8: 366 | F8: BPCE SA | G8: Estimation des pertes extrêmes en risque de crédit | H8: =INDEX(Scoring!$AO$5:$AO$87,MATCH($E8,Scoring!$A$5:$A$87,0)) -> 5 | I8: =INDEX(Scoring!$AP$5:$AP$87,MATCH($E8,Scoring!$A$5:$A$87,0)) -> 3.6 | J8: =INDEX(Scoring!$AQ$5:$AQ$87,MATCH($E8,Scoring!$A$5:$A$87,0)) -> 3.25 | K8: =INDEX(Scoring!$AR$5:$AR$87,MATCH($E8,Scoring!$A$5:$A$87,0)) -> 3.25 | L8: =INDEX(Scoring!$AS$5:$AS$87,MATCH($E8,Scoring!$A$5:$A$87,0)) -> 4 | M8: =INDEX(Scoring!$AT$5:$AT$87,MATCH($E8,Scoring!$A$5:$A$87,0)) -> 2.875 | N8: =INDEX(Scoring!$AU$5:$AU$87,MATCH($E8,Scoring!$A$5:$A$87,0)) -> 3.7041667 | O8: =INDEX(Scoring!$AN$5:$AN$87,MATCH($E8,Scoring!$A$5:$A$87,0)) -> 4 | P8: Estimer la VaR à 99,9 % d'un portefeuille de crédit par copules (Gaussienne, Student, Archimédiennes) et mesurer l'effet du choix de copule sur le capital. Cœur de métier du risque extrême, très bonne profondeur mathématique, titre clair. | Q8: Cœur du risque extrême (copules, dépendance de queue). Demande forte probable ; la provenance des séries de défauts reste à confirmer. | R8: Fiche : Moyenne Web : Faible | S8: Ouvrir le PDF
A9: High | B9: H1 | C9: Cœur de cible | D9: 5 | E9: 324 | F9: Banque de France | G9: Modélisation du risque de crédit en intégrant les engagements hors bilan | H9: =INDEX(Scoring!$AO$5:$AO$87,MATCH($E9,Scoring!$A$5:$A$87,0)) -> 4 | I9: =INDEX(Scoring!$AP$5:$AP$87,MATCH($E9,Scoring!$A$5:$A$87,0)) -> 3.8 | J9: =INDEX(Scoring!$AQ$5:$AQ$87,MATCH($E9,Scoring!$A$5:$A$87,0)) -> 3.75 | K9: =INDEX(Scoring!$AR$5:$AR$87,MATCH($E9,Scoring!$A$5:$A$87,0)) -> 3.5 | L9: =INDEX(Scoring!$AS$5:$AS$87,MATCH($E9,Scoring!$A$5:$A$87,0)) -> 3.75 | M9: =INDEX(Scoring!$AT$5:$AT$87,MATCH($E9,Scoring!$A$5:$A$87,0)) -> 3 | N9: =INDEX(Scoring!$AU$5:$AU$87,MATCH($E9,Scoring!$A$5:$A$87,0)) -> 3.6333333 | O9: =INDEX(Scoring!$AN$5:$AN$87,MATCH($E9,Scoring!$A$5:$A$87,0)) -> 3 | P9: Intégrer les engagements hors bilan dans les modèles de risque de crédit (Merton/KMV et score d'Altman), avec les hyperscalers en étude de cas et validation par les spreads de CDS. Cahier des charges très complet, sujet d'actualité, données Bloomberg fournies. | Q9: Bon sujet de finance de crédit, rigoureux. Le travail de reconstitution des engagements hors bilan à partir des comptes est la vraie charge ; à répartir tôt. | R9: Fiche : Haute Web : Faible | S9: Ouvrir le PDF
A10: High | B10: H1 | C10: Cœur de cible | D10: 6 | E10: 361 | F10: HSBC Global Asset Management | G10: Gestion d'actif – Conception de portefeuilles optionnels protégés sous contrainte Solvabilité II | H10: =INDEX(Scoring!$AO$5:$AO$87,MATCH($E10,Scoring!$A$5:$A$87,0)) -> 4 | I10: =INDEX(Scoring!$AP$5:$AP$87,MATCH($E10,Scoring!$A$5:$A$87,0)) -> 3.4 | J10: =INDEX(Scoring!$AQ$5:$AQ$87,MATCH($E10,Scoring!$A$5:$A$87,0)) -> 3.5 | K10: =INDEX(Scoring!$AR$5:$AR$87,MATCH($E10,Scoring!$A$5:$A$87,0)) -> 3.5 | L10: =INDEX(Scoring!$AS$5:$AS$87,MATCH($E10,Scoring!$A$5:$A$87,0)) -> 3.5 | M10: =INDEX(Scoring!$AT$5:$AT$87,MATCH($E10,Scoring!$A$5:$A$87,0)) -> 2.375 | N10: =INDEX(Scoring!$AU$5:$AU$87,MATCH($E10,Scoring!$A$5:$A$87,0)) -> 3.5875 | O10: =INDEX(Scoring!$AN$5:$AN$87,MATCH($E10,Scoring!$A$5:$A$87,0)) -> 3 | P10: Concevoir des portefeuilles optionnels protégés sous contrainte Solvabilité II, avec calcul simplifié du SCR. Cahier des charges très complet et lien direct avec l'assurance vie et la retraite. Recoupe fortement le sujet 282 du même encadrant. | Q10: Le plus assurantiel des deux sujets d'options (282 et 361). Ne choisir qu'un seul des deux. | R10: Fiche : Haute Web : Faible | S10: Ouvrir le PDF
A11: High | B11: H1 | C11: Cœur de cible | D11: 7 | E11: 332 | F11: Symbiotics Asset Management | G11: Constructing Yield Curves in Illiquid Emerging Market | H11: =INDEX(Scoring!$AO$5:$AO$87,MATCH($E11,Scoring!$A$5:$A$87,0)) -> 4 | I11: =INDEX(Scoring!$AP$5:$AP$87,MATCH($E11,Scoring!$A$5:$A$87,0)) -> 3.4 | J11: =INDEX(Scoring!$AQ$5:$AQ$87,MATCH($E11,Scoring!$A$5:$A$87,0)) -> 3.75 | K11: =INDEX(Scoring!$AR$5:$AR$87,MATCH($E11,Scoring!$A$5:$A$87,0)) -> 3.5 | L11: =INDEX(Scoring!$AS$5:$AS$87,MATCH($E11,Scoring!$A$5:$A$87,0)) -> 3.5 | M11: =INDEX(Scoring!$AT$5:$AT$87,MATCH($E11,Scoring!$A$5:$A$87,0)) -> 2.75 | N11: =INDEX(Scoring!$AU$5:$AU$87,MATCH($E11,Scoring!$A$5:$A$87,0)) -> 3.5666667 | O11: =INDEX(Scoring!$AN$5:$AN$87,MATCH($E11,Scoring!$A$5:$A$87,0)) -> 2 | P11: Réplication d'une méthode de courbe des taux de Nelson-Siegel adaptée aux marchés illiquides (Kazakhstan), puis transfert à d'autres marchés émergents. Question de recherche claire, lien direct avec les institutions de développement. Risque : données rares en marchés frontières. | Q11: Bonne piste pour le profil institutions et développement. Vérifier avec l'encadrant quelles données de marché sont réellement disponibles avant de choisir les pays. | R11: Fiche : Moyenne Web : Faible | S11: Ouvrir le PDF
A12: High | B12: H2 | C12: Pari à fort potentiel | D12: 1 | E12: 364 | F12: Symbiotics Asset Management | G12: Statistical Modelling, Stress Testing and Optimal Structuring of a Blended Finance Fund | H12: =INDEX(Scoring!$AO$5:$AO$87,MATCH($E12,Scoring!$A$5:$A$87,0)) -> 5 | I12: =INDEX(Scoring!$AP$5:$AP$87,MATCH($E12,Scoring!$A$5:$A$87,0)) -> 3.2 | J12: =INDEX(Scoring!$AQ$5:$AQ$87,MATCH($E12,Scoring!$A$5:$A$87,0)) -> 4 | K12: =INDEX(Scoring!$AR$5:$AR$87,MATCH($E12,Scoring!$A$5:$A$87,0)) -> 3 | L12: =INDEX(Scoring!$AS$5:$AS$87,MATCH($E12,Scoring!$A$5:$A$87,0)) -> 4.25 | M12: =INDEX(Scoring!$AT$5:$AT$87,MATCH($E12,Scoring!$A$5:$A$87,0)) -> 3.125 | N12: =INDEX(Scoring!$AU$5:$AU$87,MATCH($E12,Scoring!$A$5:$A$87,0)) -> 3.7208333 | O12: =INDEX(Scoring!$AN$5:$AN$87,MATCH($E12,Scoring!$A$5:$A$87,0)) -> 2 | P12: Structurer un fonds de finance mixte (tranches junior et senior) : risque de crédit de portefeuille, cascade de paiements par Monte-Carlo, stress, optimisation. Le tranchage first-loss est proche de la logique d'une réassurance en excédent de sinistre. Données et modèles encore « à définir ». | Q12: Sujet à très fort alpha pour les profils institutions, développement et risque. Faire préciser le périmètre et les données avant de s'engager. | R12: Fiche : Moyenne Web : Faible | S12: Ouvrir le PDF
A13: High | B13: H2 | C13: Pari à fort potentiel | D13: 2 | E13: 302 | F13: WOAH | G13: Animal Health as Market and Trade Intelligence | H13: =INDEX(Scoring!$AO$5:$AO$87,MATCH($E13,Scoring!$A$5:$A$87,0)) -> 5 | I13: =INDEX(Scoring!$AP$5:$AP$87,MATCH($E13,Scoring!$A$5:$A$87,0)) -> 3.2 | J13: =INDEX(Scoring!$AQ$5:$AQ$87,MATCH($E13,Scoring!$A$5:$A$87,0)) -> 3.75 | K13: =INDEX(Scoring!$AR$5:$AR$87,MATCH($E13,Scoring!$A$5:$A$87,0)) -> 3 | L13: =INDEX(Scoring!$AS$5:$AS$87,MATCH($E13,Scoring!$A$5:$A$87,0)) -> 4.25 | M13: =INDEX(Scoring!$AT$5:$AT$87,MATCH($E13,Scoring!$A$5:$A$87,0)) -> 3 | N13: =INDEX(Scoring!$AU$5:$AU$87,MATCH($E13,Scoring!$A$5:$A$87,0)) -> 3.7 | O13: =INDEX(Scoring!$AN$5:$AN$87,MATCH($E13,Scoring!$A$5:$A$87,0)) -> 2 | P13: Épizooties et marchés de la viande, à l'OMSA/WOAH : études d'événements, GARCH-DCC, régimes à seuil, VAR, différences de différences, gravité, sur de nombreuses sources publiques. Organisation internationale, travail en anglais, grande variété de méthodes. Mais objectif flou (preuves de concept d'un programme de travail) et menu trop large. | Q13: Bon sujet pour le profil institutions internationales et séries temporelles de marché. Exiger un périmètre resserré (par exemple une maladie, un marché, deux méthodes) avant de s'engager. | R13: Fiche : Moyenne Web : Moyenne | S13: Ouvrir le PDF
A14: High | B14: H2 | C14: Pari à fort potentiel | D14: 3 | E14: 356 | F14: VIA AM | G14: Finding Factors Using NLP/LLMs on 10-K/10-Q/8-K Filings | H14: =INDEX(Scoring!$AO$5:$AO$87,MATCH($E14,Scoring!$A$5:$A$87,0)) -> 5 | I14: =INDEX(Scoring!$AP$5:$AP$87,MATCH($E14,Scoring!$A$5:$A$87,0)) -> 3.2 | J14: =INDEX(Scoring!$AQ$5:$AQ$87,MATCH($E14,Scoring!$A$5:$A$87,0)) -> 3.75 | K14: =INDEX(Scoring!$AR$5:$AR$87,MATCH($E14,Scoring!$A$5:$A$87,0)) -> 3.5 | L14: =INDEX(Scoring!$AS$5:$AS$87,MATCH($E14,Scoring!$A$5:$A$87,0)) -> 4.25 | M14: =INDEX(Scoring!$AT$5:$AT$87,MATCH($E14,Scoring!$A$5:$A$87,0)) -> 3.5 | N14: =INDEX(Scoring!$AU$5:$AU$87,MATCH($E14,Scoring!$A$5:$A$87,0)) -> 3.7 | O14: =INDEX(Scoring!$AN$5:$AN$87,MATCH($E14,Scoring!$A$5:$A$87,0)) -> 4 | P14: Facteurs textuels (NLP/LLM) sur les dépôts SEC pour prévoir les rendements, en trois étapes jusqu'à l'intégration en portefeuille multifactoriel. Signal quant très fort : papier de référence (Lazy Prices), pipeline complet, livrable montrable. Coût élevé. | Q14: Pari à fort potentiel pour le profil quant. Demande forte attendue (quant et LLM) ; réserver au meilleur groupe, avec un périmètre réduit aux deux premières étapes. | R14: Fiche : Haute Web : Faible | S14: Ouvrir le PDF
A15: High | B15: H2 | C15: Pari à fort potentiel | D15: 4 | E15: 309 | F15: Ekimetrics | G15: Apprentissage de lois a priori par transfert entre portefeuilles : une approche de meta-learning bayésien | H15: =INDEX(Scoring!$AO$5:$AO$87,MATCH($E15,Scoring!$A$5:$A$87,0)) -> 4 | I15: =INDEX(Scoring!$AP$5:$AP$87,MATCH($E15,Scoring!$A$5:$A$87,0)) -> 3 | J15: =INDEX(Scoring!$AQ$5:$AQ$87,MATCH($E15,Scoring!$A$5:$A$87,0)) -> 3.5 | K15: =INDEX(Scoring!$AR$5:$AR$87,MATCH($E15,Scoring!$A$5:$A$87,0)) -> 3.25 | L15: =INDEX(Scoring!$AS$5:$AS$87,MATCH($E15,Scoring!$A$5:$A$87,0)) -> 4.75 | M15: =INDEX(Scoring!$AT$5:$AT$87,MATCH($E15,Scoring!$A$5:$A$87,0)) -> 2.75 | N15: =INDEX(Scoring!$AU$5:$AU$87,MATCH($E15,Scoring!$A$5:$A$87,0)) -> 3.625 | O15: =INDEX(Scoring!$AN$5:$AN$87,MATCH($E15,Scoring!$A$5:$A$87,0)) -> 2 | P15: Meta-learning bayésien et crédibilité de Bühlmann-Straub sur données simulées, avec un volet de tarification non-vie. Très forte profondeur et très différenciant, mais niveau élevé (PyMC, NUTS) et titre peu vendeur. | Q15: Pari à fort potentiel si le groupe est à l'aise en bayésien. La crédibilité est un sujet d'examen de la filière non-vie, donc utile pour l'ACAS. Vérifier le niveau réel du groupe avant de s'engager. | R15: Fiche : Haute Web : Faible | S15: Ouvrir le PDF
A16: High | B16: H2 | C16: Pari à fort potentiel | D16: 5 | E16: 303 | F16: WOAH | G16: Embeddings for Epidemic Intelligence | H16: =INDEX(Scoring!$AO$5:$AO$87,MATCH($E16,Scoring!$A$5:$A$87,0)) -> 4 | I16: =INDEX(Scoring!$AP$5:$AP$87,MATCH($E16,Scoring!$A$5:$A$87,0)) -> 3.6 | J16: =INDEX(Scoring!$AQ$5:$AQ$87,MATCH($E16,Scoring!$A$5:$A$87,0)) -> 4 | K16: =INDEX(Scoring!$AR$5:$AR$87,MATCH($E16,Scoring!$A$5:$A$87,0)) -> 3.25 | L16: =INDEX(Scoring!$AS$5:$AS$87,MATCH($E16,Scoring!$A$5:$A$87,0)) -> 4.25 | M16: =INDEX(Scoring!$AT$5:$AT$87,MATCH($E16,Scoring!$A$5:$A$87,0)) -> 3.5 | N16: =INDEX(Scoring!$AU$5:$AU$87,MATCH($E16,Scoring!$A$5:$A$87,0)) -> 3.6 | O16: =INDEX(Scoring!$AN$5:$AN$87,MATCH($E16,Scoring!$A$5:$A$87,0)) -> 2 | P16: Embeddings multilingues pour la veille épidémique à l'OMSA/WOAH : pipeline de recherche sémantique comparé à une base lexicale, avec correction de la sensibilité et de la spécificité par modèles à classes latentes (Hui-Walter). Contenu statistique réel, organisation internationale, travail en anglais. Charge élevée (corpus à construire, annotation). | Q16: Pari intéressant pour le profil institutions internationales ; la partie classes latentes est le point différenciant. À cadrer avec peu de modèles d'embedding. | R16: Fiche : Haute Web : Moyenne | S16: Ouvrir le PDF
... A87: Ne pas toucher | B87: N3 | C87: Coût supérieur à la valeur | D87: 1 | E87: 293 | F87: QuantCube Technology | G87: Nowcasting hiérarchique de la consommation des ménages en Espagne | H87: =INDEX(Scoring!$AO$5:$AO$87,MATCH($E87,Scoring!$A$5:$A$87,0)) -> 3 | I87: =INDEX(Scoring!$AP$5:$AP$87,MATCH($E87,Scoring!$A$5:$A$87,0)) -> 3.2 | J87: =INDEX(Scoring!$AQ$5:$AQ$87,MATCH($E87,Scoring!$A$5:$A$87,0)) -> 2.75 | K87: =INDEX(Scoring!$AR$5:$AR$87,MATCH($E87,Scoring!$A$5:$A$87,0)) -> 3.5 | L87: =INDEX(Scoring!$AS$5:$AS$87,MATCH($E87,Scoring!$A$5:$A$87,0)) -> 4.5 | M87: =INDEX(Scoring!$AT$5:$AT$87,MATCH($E87,Scoring!$A$5:$A$87,0)) -> 3.375 | N87: =INDEX(Scoring!$AU$5:$AU$87,MATCH($E87,Scoring!$A$5:$A$87,0)) -> 3.2625 | O87: =INDEX(Scoring!$AN$5:$AN$87,MATCH($E87,Scoring!$A$5:$A$87,0)) -> 2 | P87: Nowcasting hiérarchique de la consommation des ménages espagnols : réconciliation temporelle et transversale (MinT), modèles à facteurs à fréquences mixtes, données alternatives de QuantCube. Très riche, avec une vraie question de recherche, mais niveau élevé et encadrement par une jeune entreprise. | Q87: Coût supérieur à la valeur pour vos objectifs : la réconciliation croisée est avancée, les données de QuantCube sont propriétaires et le niveau est élevé. À ne choisir que par goût de la prévision macro, avec un périmètre fortement réduit. | R87: Fiche : Haute Web : Faible | S87: Ouvrir le PDF

Sheet Règles de classement
A1: Règles de classement et définitions
A3: Code | B3: Classe | C3: Sous-catégorie | D3: Règle (appliquée dans cet ordre : N2, N3, H1, H2, H3, M2, M1, M3, N1) | E3: Nb de sujets
A4: H1 | B4: High | C4: Cœur de cible | D4: Fit ≥ 4, Signal ≥ 3,4, Exit ≥ 3,2, Risque ≤ 3,2, données (D3) ≤ 4, calibrage (D5) < 4, adéquation 2A (D4) ≥ 3. | E4: =COUNTIF(Classement!$B$5:$B$87,A4) -> 7
A5: H2 | B5: High | C5: Pari à fort potentiel | D5: Fort potentiel (Fit ≥ 4 avec Signal ≥ 3,4 ou Apprentissage ≥ 4 ; ou Signal ≥ 4 et Apprentissage ≥ 4 avec Fit ≥ 3) mais ne remplit pas H1 : risque, données, niveau ou adéquation 2A. Inclut les sujets à fort fit dont seul un blocage pèse, s'ils ont aussi Signal ≥ 3,4 ou Apprentissage ≥ 4 ; sinon ils vont en M2. | E5: =COUNTIF(Classement!$B$5:$B$87,A5) -> 7
A6: H3 | B6: High | C6: Valeur sûre | D6: Fit ≥ 3, Signal ≥ 3,4, Exit ≥ 3,2, Note ≥ 3,5, Risque ≤ 2,6 : bon fit, bonne note probable, effort modéré. | E6: =COUNTIF(Classement!$B$5:$B$87,A6) -> 3
A7: M1 | B7: Mid | C7: Bon signal, fit partiel | D7: Signal ≥ 3,6 avec Fit = 3 : bon signal, adéquation partielle. | E7: =COUNTIF(Classement!$B$5:$B$87,A7) -> 3
A8: M2 | B8: Mid | C8: Bon fit, signal limité | D8: Fit ≥ 4 et Signal < 3,4 (bon fit, marque ou encadrant limités). | E8: =COUNTIF(Classement!$B$5:$B$87,A8) -> 8
A9: M3 | B9: Mid | C9: Plan B polyvalent | D9: Compétences portables (A8 ≥ 3), Risque < 3,3, Signal ≥ 2,8, Apprentissage ≥ 3, et Fit ≥ 3 ou Apprentissage ≥ 3,5 : plan B pour compléter les 12 vœux. | E9: =COUNTIF(Classement!$B$5:$B$87,A9) -> 17
A10: N1 | B10: Ne pas toucher | C10: Hors parcours | D10: Tout le reste, sans blocage : peu ou pas de lien avec les voies visées, et peu d'apprentissage ou de signal pour compenser. | E10: =COUNTIF(Classement!$B$5:$B$87,A10) -> 19
A11: N2 | B11: Ne pas toucher | C11: Risque trop élevé | D11: Blocage (note ENSAE 1, ou données D3, calibrage D5 ou risque d'exécution F5 au maximum) ou Risque ≥ 3,5, sans fort fit (≥ 4) qui le compense. | E11: =COUNTIF(Classement!$B$5:$B$87,A11) -> 18
A12: N3 | B12: Ne pas toucher | C12: Coût supérieur à la valeur | D12: Risque ≥ 3,3 avec Fit ≤ 3 et Signal < 3,6 : l'effort dépasse ce que le sujet rapporte. | E12: =COUNTIF(Classement!$B$5:$B$87,A12) -> 1
D13: Total | E13: =SUM(E4:E12) -> 83
A15: Définitions des familles (feuille Scoring)
A16: Fit | B16: Meilleure adéquation à l'une des sept voies de carrière : maximum de A1 à A7. Un seul bon fit suffit, la moyenne pénaliserait les sujets spécialisés. A8 (compétences portables) est lu à part.
A17: Signal | B17: Moyenne de B1 à B5 : marque, encadrant, lisibilité, signal académique.
A18: Exit | B18: Moyenne de C1 à C4 : débouché, réseau, portée internationale, valeur en entretien.
A19: Note | B19: Moyenne de D1, D2, D4 et D6 : note ENSAE (3 par défaut si non noté), clarté du cahier des charges, adéquation au programme de 2A, encadrement. D3 et D5 sont dans le risque.
A20: Apprentissage | B20: Moyenne de E1 à E4 : profondeur, nouveauté des méthodes, livrable montrable, différenciation.
A21: Risque | B21: Moyenne de D3, D5 et F1 à F7 (F4 inclus dès que KC le renseigne). Plus haut = plus risqué ou coûteux. F8 (probabilité d'obtenir le sujet) est lu à part sous « Demande ».
A22: Indice | B22: Moyenne simple de Fit, Signal, Exit, Note, Apprentissage et (6 − Risque). Aucune pondération entre familles. Sert uniquement à ordonner les sujets au sein d'une sous-catégorie.
A23: Non utilisés | B23: A9 (motivation) et F4 (calendrier) sont à renseigner par KC. Ils ne sont pas dans l'indice tant qu'ils sont vides ; F4 entre dans le risque dès qu'il est rempli.

Sheet Sources web
A1: Sources de la recherche web (WebSearch, mode standard) : organismes et encadrants
A2: Scores 1 à 5 selon les ancres de « Critères ». Confiance : Haute = plusieurs sources concordantes ; Moyenne = source unique ou information partielle ; Faible = rien de vérifiable, valeur par défaut. Les offres d'emploi et les pages d'organismes sont des indices, pas des preuves de recrutement.
A4: Organisme | B4: B1 Notoriété | C4: B2 Pertinence marque | D4: C1 Débouché | E4: C2 Réseau | F4: C3 International | G4: D6 Encadrement | H4: Confiance | I4: Ce qui a été trouvé | J4: Source
A5: Banque de France | B5: 4 | C5: 4 | D5: 3 | E5: 4 | F5: 3 | G5: 3 | H5: Moyenne | I5: DGSEI : études, statistiques ; stages économie/statistique à Paris | J5: https://www.jobteaser.com/da/job-offers/0d850949-b970-4c67-b803-5c85fcf10a2d-banque-de-france-stage-analyste-de-donnees-monetaires-h-f
A6: BNP Paribas Cardif | B6: 4 | C6: 4 | D6: 4 | E6: 3 | F6: 3 | G6: 3 | H6: Moyenne | I6: Stages actuariat (Paris, Milan, Turquie) ; Datalab ; témoignage d'un ENSAE data scientist | J6: https://group.bnpparibas/en/careers/job-offer/actuarial-intern ; https://www.ensae.fr/index.php/en/testimonials/boris-noumedem-data-scientist-bnp-paribas-cardif
A7: BPCE SA | B7: 4 | C7: 3 | D7: 3 | E7: 3 | F7: 2 | G7: 3 | H7: Faible | I7: Groupe bancaire, non recherché | J7: Aucune source consultée : valeur par défaut
A8: CANOPY ENERGIES | B8: 1 | C8: 2 | D8: 2 | E8: 2 | F8: 3 | G8: 2 | H8: Moyenne | I8: Développeur solaire de 2008, 21-50 salariés, projets en Europe et Afrique | J8: https://www.enfsolar.com/canopy-energies
A9: CHU de Lille | B9: 3 | C9: 1 | D9: 2 | E9: 2 | F9: 1 | G9: 3 | H9: Faible | I9: Hôpital universitaire, non recherché | J9: Aucune source consultée : valeur par défaut
A10: CREST | B10: 4 | C10: 3 | D10: 2 | E10: 3 | F10: 4 | G10: 3 | H10: Moyenne | I10: Laboratoire commun ENSAE / École polytechnique / CNRS ; plusieurs ERC | J10: https://crest.science/user/Bruno-CREPON ; https://www.ensae.fr/faculty/4685-patrick-prag ; https://crest.science/user/Samuel-RUFAT
A11: Crédit Agricole SA | B11: 5 | C11: 3 | D11: 3 | E11: 3 | F11: 3 | G11: 3 | H11: Faible | I11: Grande banque, non recherchée | J11: Aucune source consultée : valeur par défaut
A12: Devoteam SAS | B12: 3 | C12: 2 | D12: 3 | E12: 2 | F12: 3 | G12: 3 | H12: Faible | I12: Conseil et ESN, non recherché | J12: Aucune source consultée : valeur par défaut
A13: DG Trésor | B13: 4 | C13: 4 | D13: 3 | E13: 4 | F13: 3 | G13: 3 | H13: Moyenne | I13: Direction économique de l'État ; recrutements via Passerelles ; stage non confirmé | J13: https://www.passerelles.economie.gouv.fr/offre-de-emploi/emploi-dgt-aft-eb-economiste-adjoint-e-au-responsable-du-pole-analyse-macro-economique-h-f_22960.aspx
A14: Drees | B14: 3 | C14: 2 | D14: 2 | E14: 3 | F14: 1 | G14: 3 | H14: Faible | I14: Service statistique des ministères sociaux, non recherché | J14: Aucune source consultée : valeur par défaut
A15: Dstudio | B15: 1 | C15: 2 | D15: 2 | E15: 2 | F15: 1 | G15: 3 | H15: Faible | I15: Cabinet de conseil data/IA parisien, créé par un ancien Chief Data & AI Officer | J15: Aucune source consultée : valeur par défaut
A16: Ecole Nationale des Ponts et Chaussées | B16: 4 | C16: 2 | D16: 2 | E16: 3 | F16: 3 | G16: 3 | H16: Faible | I16: École d'ingénieurs, non recherchée | J16: Aucune source consultée : valeur par défaut
... A47: WOAH | B47: 3 | C47: 3 | D47: 3 | E47: 3 | F47: 5 | G47: 3 | H47: Moyenne | I47: Organisation intergouvernementale (Paris) ; stages et postes au siège, travail en anglais | J47: https://www.woah.org/en/job-offer/internship-mapping-and-assessing-dataset-for-rapid-risk-assessment-in-animal-health-emergencies-epidemic-intelligence-data-integration-department-woah-hq-paris-france/
A49: Note : C3 gagne 1 point (plafond 5) quand la fiche est en anglais. D6 vaut 4 pour les encadrants membres de l'ENSAE ou du CREST (historique d'encadrement d'élèves), 3 sinon.
A51: Encadrant | B51: B3 Réputation | C51: Confiance | D51: Ce qui a été trouvé | E51: Source
A52: Crepon Bruno | B52: 5 | C52: Haute | D52: Professeur ENSAE, co-chaire J-PAL emploi, publications QJE/JPE/AEJ | E52: https://crest.science/user/Bruno-CREPON
A53: Gary Bobo Robert | B53: 4 | C53: Haute | D53: Professeur Paris 1 et ENSAE ; 37 articles (JPubE, EER, RAND) | E53: https://www.ensae.fr/faculty/910-robert-gary-bobo
A54: Kamionka Thierry | B54: 4 | C54: Haute | D54: Directeur de recherche CNRS, CREST, éditeur de la Revue économique | E54: https://www.ensae.fr/faculty/543-thierry-kamionka
A55: Präg Patrick | B55: 4 | C55: Moyenne | D55: Professeur associé de sociologie quantitative CREST/ENSAE, Nuffield College | E55: https://www.ensae.fr/faculty/4685-patrick-prag
A56: Zerbib Olivier David | B56: 5 | C56: Haute | D56: Professeur EDHEC, éditeur associé de Review of Finance, Management Science | E56: https://researchportal.ip-paris.fr/en/persons/olivier-david-zerbib/
A57: Signorelli Sara | B57: 4 | C57: Moyenne | D57: Professeure assistante CREST, PhD PSE 2021, ex-Amsterdam | E57: https://www.polytechnique-insights.com/en/contributors/sara-signorelli/
A58: Rufat Samuel | B58: 5 | C58: Haute | D58: Membre du CREST, ERC Consolidator Grant FiBeGa | E58: https://crest.science/user/Samuel-RUFAT
A59: Katsahian Sandrine | B59: 4 | C59: Moyenne | D59: CIC 14-18 HEGP (AP-HP), publications en modèles multi-états | E59: https://dblp.org/pid/166/7913
A60: Guillot Gilles | B60: 4 | C60: Moyenne | D60: Responsable du département Data Integration & Analytics au WOAH ; ex-DTU, ex-VP biostat IPRI | E60: https://fr.linkedin.com/in/gguil
A61: Garrouste Manon | B61: 4 | C61: Haute | D61: Professeure d'économie Paris-Saclay (2024), ENSAE, ANR | E61: https://www.ritm.universite-paris-saclay.fr/?p=12128
A62: BOUSCASSE HELENE | B62: 3 | C62: Moyenne | D62: Chargée de recherche INRAE, publications en choix modal et mobilité | E62: https://www2.dijon.inrae.fr/cesaer/?p=7258
A63: NIAKH Fallou | B63: 2 | C63: Faible | D63: Non trouvé | E63: Aucune source trouvée
A65: Les autres encadrants (praticiens en entreprise ou administration) n'ont rien donné de vérifiable : B3 = 3 par défaut, confiance Faible.
